Workbook

Sheet README
A1: OZ 2.0 Candidate Tracts — Excel Export
A2: WFRC & MAG Region · Wasatch Front, Utah · Generated June 01, 2026
A4: ABOUT THIS WORKBOOK
A5: This workbook is a machine-generated backup of the WFRC/MAG Opportunity Zone 2.0 candidate tract analysis. It contains all metrics calculated in the R/GIS pipeline for every census tract on the federal OZ 2.0 eligible list within the nine-county Wasatch Front region. The Summary sheet mirrors the one-page PDF summary table. Per-county sheets mirror the detail PDF pages and include an embedded tract map. All values update automatically when the pipeline is re-run with new data.
A11: SHEETS IN THIS WORKBOOK
A12: Sheet Name | B12: Description
A13: README | B13: This sheet: methodology, column glossary, and abbreviation key.
A14: Summary | B14: All-tract summary table: one row per tract, 14 columns matching the PDF summary. Values cross-referenced from All Data.
A15: Box Elder County | B15: Box Elder County: per-tract detail blocks with embedded map images. Values cross-referenced from All Data.
A16: Weber County | B16: Weber County: per-tract detail blocks with embedded map images. Values cross-referenced from All Data.
A17: Davis County | B17: Davis County: per-tract detail blocks with embedded map images. Values cross-referenced from All Data.
A18: Salt Lake County | B18: Salt Lake County: per-tract detail blocks with embedded map images. Values cross-referenced from All Data.
A19: Tooele County | B19: Tooele County: per-tract detail blocks with embedded map images. Values cross-referenced from All Data.
A20: Utah County | B20: Utah County: per-tract detail blocks with embedded map images. Values cross-referenced from All Data.
A21: All Data | B21: Flat database: all 42 metrics for every tract in one filterable Excel Table. Derived columns use in-sheet formulas.
A23: ABBREVIATIONS & GLOSSARY
A24: Term | B24: Full Name | C24: Description
A25: ATO | B25: Access to Opportunities | C25: Composite 0-100 index combining driving and transit access to jobs and households.
A26: ERU | B26: Equivalent Residential Unit | C26: Growth density metric: 1 household = 1 ERU, 1 job = 0.4 ERU.
A27: SAP | B27: Station Area Plan | C27: Adopted housing plan within 1/2-mile of a rail or BRT stop.
A28: WC / MUorC | B28: Wasatch Choice / Metro-Urban-City Center | C28: WFRC/MAG regional growth center framework. MUorC = Metropolitan, Urban, or City center types.
A29: OZ 1.0 | B29: Opportunity Zones (2018 round) | C29: Prior federal OZ designations; overlap shown for context.
A30: OZ 2.0 | B30: Opportunity Zones 2.0 (current) | C30: Current federal eligible tract list under evaluation.
A31: TAZ | B31: Traffic Analysis Zone | C31: WFRC/MAG forecast unit; growth projections are area-proportioned from TAZ to tract.
A32: DEVACRES | B32: Developable Acres | C32: Developable land within a TAZ from the ATO layer; used as intersection weight for ATO scores.
A33: GEOID | B33: Census Tract Geographic ID | C33: 11-digit FIPS code: 2-digit state + 3-digit county + 6-digit tract.
A35: DATA SOURCES
A36: Federal OZ 2.0 Eligibility List — U.S. Treasury / HUD
A37: Urban Institute OZ Tool Classification — Urban Institute
A38: Wasatch Choice for 2050 Centers & Districts — WFRC/MAG
A39: ACS Population, Households, Income, Poverty, Unemployment — U.S. Census Bureau
A40: UTA Rail/BRT Stops — Utah Transit Authority
A41: Station Area Plans (SAP) — WFRC/MAG
A42: Freeway Interchanges — WFRC/MAG
A43: Housing Inventory — WFRC/MAG
A44: Access to Opportunities (ATO) Scores — WFRC/MAG
A45: TAZ Growth Projections 2027-2037 — WFRC/MAG

Sheet Summary
A1: OZ 2.0 Eligible Census Tracts — Wasatch Front Region | June 01, 2026
A2: # | B2: IDENTITY | E2: PROFILE | J2: FOUR KEY MEASURES | N2: INVESTMENT
A3: # | B3: County | C3: Tract | D3: GEOID | E3: Population | F3: Households | G3: Total Acres | H3: Dev Acres | I3: OZ 1.0 % | J3: WC MUorC % | K3: ATO /100 | L3: SAP HH/ac | M3: ERU/ac | N3: Investment Likelihood
A4: Box Elder County — 2 Eligible Tracts
A5: 01 | B5: Box Elder | C5: Tract 9606.01 | D5: 49003960601 | E5: ==IFERROR(INDEX('All Data'!$D:$D,MATCH($D5&"",'All Data'!$A:$A,0)),"-") | F5: ==IFERROR(INDEX('All Data'!$E:$E,MATCH($D5&"",'All Data'!$A:$A,0)),"-") | G5: ==IFERROR(INDEX('All Data'!$F:$F,MATCH($D5&"",'All Data'!$A:$A,0)),"-") | H5: ==IFERROR(INDEX('All Data'!$G:$G,MATCH($D5&"",'All Data'!$A:$A,0)),"-") | I5: ==IFERROR(INDEX('All Data'!$I:$I,MATCH($D5&"",'All Data'!$A:$A,0)),"-") | J5: ==IFERROR(INDEX('All Data'!$J:$J,MATCH($D5&"",'All Data'!$A:$A,0)),"-") | K5: ==IFERROR(INDEX('All Data'!$AF:$AF,MATCH($D5&"",'All Data'!$A:$A,0)),"-") | L5: ==IFERROR(INDEX('All Data'!$AA:$AA,MATCH($D5&"",'All Data'!$A:$A,0)),"-") | M5: ==IFERROR(INDEX('All Data'!$AK:$AK,MATCH($D5&"",'All Data'!$A:$A,0)),"-") | N5: ==IFERROR(INDEX('All Data'!$AP:$AP,MATCH($D5&"",'All Data'!$A:$A,0)),"-")
A6: 02 | B6: Box Elder | C6: Tract 9607.02 | D6: 49003960702 | E6: ==IFERROR(INDEX('All Data'!$D:$D,MATCH($D6&"",'All Data'!$A:$A,0)),"-") | F6: ==IFERROR(INDEX('All Data'!$E:$E,MATCH($D6&"",'All Data'!$A:$A,0)),"-") | G6: ==IFERROR(INDEX('All Data'!$F:$F,MATCH($D6&"",'All Data'!$A:$A,0)),"-") | H6: ==IFERROR(INDEX('All Data'!$G:$G,MATCH($D6&"",'All Data'!$A:$A,0)),"-") | I6: ==IFERROR(INDEX('All Data'!$I:$I,MATCH($D6&"",'All Data'!$A:$A,0)),"-") | J6: ==IFERROR(INDEX('All Data'!$J:$J,MATCH($D6&"",'All Data'!$A:$A,0)),"-") | K6: ==IFERROR(INDEX('All Data'!$AF:$AF,MATCH($D6&"",'All Data'!$A:$A,0)),"-") | L6: ==IFERROR(INDEX('All Data'!$AA:$AA,MATCH($D6&"",'All Data'!$A:$A,0)),"-") | M6: ==IFERROR(INDEX('All Data'!$AK:$AK,MATCH($D6&"",'All Data'!$A:$A,0)),"-") | N6: ==IFERROR(INDEX('All Data'!$AP:$AP,MATCH($D6&"",'All Data'!$A:$A,0)),"-")
A7: Weber County — 16 Eligible Tracts
A8: 01 | B8: Weber | C8: Tract 2002.02 | D8: 49057200202 | E8: ==IFERROR(INDEX('All Data'!$D:$D,MATCH($D8&"",'All Data'!$A:$A,0)),"-") | F8: ==IFERROR(INDEX('All Data'!$E:$E,MATCH($D8&"",'All Data'!$A:$A,0)),"-") | G8: ==IFERROR(INDEX('All Data'!$F:$F,MATCH($D8&"",'All Data'!$A:$A,0)),"-") | H8: ==IFERROR(INDEX('All Data'!$G:$G,MATCH($D8&"",'All Data'!$A:$A,0)),"-") | I8: ==IFERROR(INDEX('All Data'!$I:$I,MATCH($D8&"",'All Data'!$A:$A,0)),"-") | J8: ==IFERROR(INDEX('All Data'!$J:$J,MATCH($D8&"",'All Data'!$A:$A,0)),"-") | K8: ==IFERROR(INDEX('All Data'!$AF:$AF,MATCH($D8&"",'All Data'!$A:$A,0)),"-") | L8: ==IFERROR(INDEX('All Data'!$AA:$AA,MATCH($D8&"",'All Data'!$A:$A,0)),"-") | M8: ==IFERROR(INDEX('All Data'!$AK:$AK,MATCH($D8&"",'All Data'!$A:$A,0)),"-") | N8: ==IFERROR(INDEX('All Data'!$AP:$AP,MATCH($D8&"",'All Data'!$A:$A,0)),"-")
A9: 02 | B9: Weber | C9: Tract 2003.02 | D9: 49057200302 | E9: ==IFERROR(INDEX('All Data'!$D:$D,MATCH($D9&"",'All Data'!$A:$A,0)),"-") | F9: ==IFERROR(INDEX('All Data'!$E:$E,MATCH($D9&"",'All Data'!$A:$A,0)),"-") | G9: ==IFERROR(INDEX('All Data'!$F:$F,MATCH($D9&"",'All Data'!$A:$A,0)),"-") | H9: ==IFERROR(INDEX('All Data'!$G:$G,MATCH($D9&"",'All Data'!$A:$A,0)),"-") | I9: ==IFERROR(INDEX('All Data'!$I:$I,MATCH($D9&"",'All Data'!$A:$A,0)),"-") | J9: ==IFERROR(INDEX('All Data'!$J:$J,MATCH($D9&"",'All Data'!$A:$A,0)),"-") | K9: ==IFERROR(INDEX('All Data'!$AF:$AF,MATCH($D9&"",'All Data'!$A:$A,0)),"-") | L9: ==IFERROR(INDEX('All Data'!$AA:$AA,MATCH($D9&"",'All Data'!$A:$A,0)),"-") | M9: ==IFERROR(INDEX('All Data'!$AK:$AK,MATCH($D9&"",'All Data'!$A:$A,0)),"-") | N9: ==IFERROR(INDEX('All Data'!$AP:$AP,MATCH($D9&"",'All Data'!$A:$A,0)),"-")
A10: 03 | B10: Weber | C10: Tract 2004 | D10: 49057200400 | E10: ==IFERROR(INDEX('All Data'!$D:$D,MATCH($D10&"",'All Data'!$A:$A,0)),"-") | F10: ==IFERROR(INDEX('All Data'!$E:$E,MATCH($D10&"",'All Data'!$A:$A,0)),"-") | G10: ==IFERROR(INDEX('All Data'!$F:$F,MATCH($D10&"",'All Data'!$A:$A,0)),"-") | H10: ==IFERROR(INDEX('All Data'!$G:$G,MATCH($D10&"",'All Data'!$A:$A,0)),"-") | I10: ==IFERROR(INDEX('All Data'!$I:$I,MATCH($D10&"",'All Data'!$A:$A,0)),"-") | J10: ==IFERROR(INDEX('All Data'!$J:$J,MATCH($D10&"",'All Data'!$A:$A,0)),"-") | K10: ==IFERROR(INDEX('All Data'!$AF:$AF,MATCH($D10&"",'All Data'!$A:$A,0)),"-") | L10: ==IFERROR(INDEX('All Data'!$AA:$AA,MATCH($D10&"",'All Data'!$A:$A,0)),"-") | M10: ==IFERROR(INDEX('All Data'!$AK:$AK,MATCH($D10&"",'All Data'!$A:$A,0)),"-") | N10: ==IFERROR(INDEX('All Data'!$AP:$AP,MATCH($D10&"",'All Data'!$A:$A,0)),"-")
A11: 04 | B11: Weber | C11: Tract 2005 | D11: 49057200500 | E11: ==IFERROR(INDEX('All Data'!$D:$D,MATCH($D11&"",'All Data'!$A:$A,0)),"-") | F11: ==IFERROR(INDEX('All Data'!$E:$E,MATCH($D11&"",'All Data'!$A:$A,0)),"-") | G11: ==IFERROR(INDEX('All Data'!$F:$F,MATCH($D11&"",'All Data'!$A:$A,0)),"-") | H11: ==IFERROR(INDEX('All Data'!$G:$G,MATCH($D11&"",'All Data'!$A:$A,0)),"-") | I11: ==IFERROR(INDEX('All Data'!$I:$I,MATCH($D11&"",'All Data'!$A:$A,0)),"-") | J11: ==IFERROR(INDEX('All Data'!$J:$J,MATCH($D11&"",'All Data'!$A:$A,0)),"-") | K11: ==IFERROR(INDEX('All Data'!$AF:$AF,MATCH($D11&"",'All Data'!$A:$A,0)),"-") | L11: ==IFERROR(INDEX('All Data'!$AA:$AA,MATCH($D11&"",'All Data'!$A:$A,0)),"-") | M11: ==IFERROR(INDEX('All Data'!$AK:$AK,MATCH($D11&"",'All Data'!$A:$A,0)),"-") | N11: ==IFERROR(INDEX('All Data'!$AP:$AP,MATCH($D11&"",'All Data'!$A:$A,0)),"-")
A12: 05 | B12: Weber | C12: Tract 2008 | D12: 49057200800 | E12: ==IFERROR(INDEX('All Data'!$D:$D,MATCH($D12&"",'All Data'!$A:$A,0)),"-") | F12: ==IFERROR(INDEX('All Data'!$E:$E,MATCH($D12&"",'All Data'!$A:$A,0)),"-") | G12: ==IFERROR(INDEX('All Data'!$F:$F,MATCH($D12&"",'All Data'!$A:$A,0)),"-") | H12: ==IFERROR(INDEX('All Data'!$G:$G,MATCH($D12&"",'All Data'!$A:$A,0)),"-") | I12: ==IFERROR(INDEX('All Data'!$I:$I,MATCH($D12&"",'All Data'!$A:$A,0)),"-") | J12: ==IFERROR(INDEX('All Data'!$J:$J,MATCH($D12&"",'All Data'!$A:$A,0)),"-") | K12: ==IFERROR(INDEX('All Data'!$AF:$AF,MATCH($D12&"",'All Data'!$A:$A,0)),"-") | L12: ==IFERROR(INDEX('All Data'!$AA:$AA,MATCH($D12&"",'All Data'!$A:$A,0)),"-") | M12: ==IFERROR(INDEX('All Data'!$AK:$AK,MATCH($D12&"",'All Data'!$A:$A,0)),"-") | N12: ==IFERROR(INDEX('All Data'!$AP:$AP,MATCH($D12&"",'All Data'!$A:$A,0)),"-")
A13: 06 | B13: Weber | C13: Tract 2009 | D13: 49057200900 | E13: ==IFERROR(INDEX('All Data'!$D:$D,MATCH($D13&"",'All Data'!$A:$A,0)),"-") | F13: ==IFERROR(INDEX('All Data'!$E:$E,MATCH($D13&"",'All Data'!$A:$A,0)),"-") | G13: ==IFERROR(INDEX('All Data'!$F:$F,MATCH($D13&"",'All Data'!$A:$A,0)),"-") | H13: ==IFERROR(INDEX('All Data'!$G:$G,MATCH($D13&"",'All Data'!$A:$A,0)),"-") | I13: ==IFERROR(INDEX('All Data'!$I:$I,MATCH($D13&"",'All Data'!$A:$A,0)),"-") | J13: ==IFERROR(INDEX('All Data'!$J:$J,MATCH($D13&"",'All Data'!$A:$A,0)),"-") | K13: ==IFERROR(INDEX('All Data'!$AF:$AF,MATCH($D13&"",'All Data'!$A:$A,0)),"-") | L13: ==IFERROR(INDEX('All Data'!$AA:$AA,MATCH($D13&"",'All Data'!$A:$A,0)),"-") | M13: ==IFERROR(INDEX('All Data'!$AK:$AK,MATCH($D13&"",'All Data'!$A:$A,0)),"-") | N13: ==IFERROR(INDEX('All Data'!$AP:$AP,MATCH($D13&"",'All Data'!$A:$A,0)),"-")
A14: 07 | B14: Weber | C14: Tract 2011 | D14: 49057201100 | E14: ==IFERROR(INDEX('All Data'!$D:$D,MATCH($D14&"",'All Data'!$A:$A,0)),"-") | F14: ==IFERROR(INDEX('All Data'!$E:$E,MATCH($D14&"",'All Data'!$A:$A,0)),"-") | G14: ==IFERROR(INDEX('All Data'!$F:$F,MATCH($D14&"",'All Data'!$A:$A,0)),"-") | H14: ==IFERROR(INDEX('All Data'!$G:$G,MATCH($D14&"",'All Data'!$A:$A,0)),"-") | I14: ==IFERROR(INDEX('All Data'!$I:$I,MATCH($D14&"",'All Data'!$A:$A,0)),"-") | J14: ==IFERROR(INDEX('All Data'!$J:$J,MATCH($D14&"",'All Data'!$A:$A,0)),"-") | K14: ==IFERROR(INDEX('All Data'!$AF:$AF,MATCH($D14&"",'All Data'!$A:$A,0)),"-") | L14: ==IFERROR(INDEX('All Data'!$AA:$AA,MATCH($D14&"",'All Data'!$A:$A,0)),"-") | M14: ==IFERROR(INDEX('All Data'!$AK:$AK,MATCH($D14&"",'All Data'!$A:$A,0)),"-") | N14: ==IFERROR(INDEX('All Data'!$AP:$AP,MATCH($D14&"",'All Data'!$A:$A,0)),"-")
A15: 08 | B15: Weber | C15: Tract 2012 | D15: 49057201200 | E15: ==IFERROR(INDEX('All Data'!$D:$D,MATCH($D15&"",'All Data'!$A:$A,0)),"-") | F15: ==IFERROR(INDEX('All Data'!$E:$E,MATCH($D15&"",'All Data'!$A:$A,0)),"-") | G15: ==IFERROR(INDEX('All Data'!$F:$F,MATCH($D15&"",'All Data'!$A:$A,0)),"-") | H15: ==IFERROR(INDEX('All Data'!$G:$G,MATCH($D15&"",'All Data'!$A:$A,0)),"-") | I15: ==IFERROR(INDEX('All Data'!$I:$I,MATCH($D15&"",'All Data'!$A:$A,0)),"-") | J15: ==IFERROR(INDEX('All Data'!$J:$J,MATCH($D15&"",'All Data'!$A:$A,0)),"-") | K15: ==IFERROR(INDEX('All Data'!$AF:$AF,MATCH($D15&"",'All Data'!$A:$A,0)),"-") | L15: ==IFERROR(INDEX('All Data'!$AA:$AA,MATCH($D15&"",'All Data'!$A:$A,0)),"-") | M15: ==IFERROR(INDEX('All Data'!$AK:$AK,MATCH($D15&"",'All Data'!$A:$A,0)),"-") | N15: ==IFERROR(INDEX('All Data'!$AP:$AP,MATCH($D15&"",'All Data'!$A:$A,0)),"-")
A16: 09 | B16: Weber | C16: Tract 2013.01 | D16: 49057201301 | E16: ==IFERROR(INDEX('All Data'!$D:$D,MATCH($D16&"",'All Data'!$A:$A,0)),"-") | F16: ==IFERROR(INDEX('All Data'!$E:$E,MATCH($D16&"",'All Data'!$A:$A,0)),"-") | G16: ==IFERROR(INDEX('All Data'!$F:$F,MATCH($D16&"",'All Data'!$A:$A,0)),"-") | H16: ==IFERROR(INDEX('All Data'!$G:$G,MATCH($D16&"",'All Data'!$A:$A,0)),"-") | I16: ==IFERROR(INDEX('All Data'!$I:$I,MATCH($D16&"",'All Data'!$A:$A,0)),"-") | J16: ==IFERROR(INDEX('All Data'!$J:$J,MATCH($D16&"",'All Data'!$A:$A,0)),"-") | K16: ==IFERROR(INDEX('All Data'!$AF:$AF,MATCH($D16&"",'All Data'!$A:$A,0)),"-") | L16: ==IFERROR(INDEX('All Data'!$AA:$AA,MATCH($D16&"",'All Data'!$A:$A,0)),"-") | M16: ==IFERROR(INDEX('All Data'!$AK:$AK,MATCH($D16&"",'All Data'!$A:$A,0)),"-") | N16: ==IFERROR(INDEX('All Data'!$AP:$AP,MATCH($D16&"",'All Data'!$A:$A,0)),"-")
A17: 10 | B17: Weber | C17: Tract 2013.02 | D17: 49057201302 | E17: ==IFERROR(INDEX('All Data'!$D:$D,MATCH($D17&"",'All Data'!$A:$A,0)),"-") | F17: ==IFERROR(INDEX('All Data'!$E:$E,MATCH($D17&"",'All Data'!$A:$A,0)),"-") | G17: ==IFERROR(INDEX('All Data'!$F:$F,MATCH($D17&"",'All Data'!$A:$A,0)),"-") | H17: ==IFERROR(INDEX('All Data'!$G:$G,MATCH($D17&"",'All Data'!$A:$A,0)),"-") | I17: ==IFERROR(INDEX('All Data'!$I:$I,MATCH($D17&"",'All Data'!$A:$A,0)),"-") | J17: ==IFERROR(INDEX('All Data'!$J:$J,MATCH($D17&"",'All Data'!$A:$A,0)),"-") | K17: ==IFERROR(INDEX('All Data'!$AF:$AF,MATCH($D17&"",'All Data'!$A:$A,0)),"-") | L17: ==IFERROR(INDEX('All Data'!$AA:$AA,MATCH($D17&"",'All Data'!$A:$A,0)),"-") | M17: ==IFERROR(INDEX('All Data'!$AK:$AK,MATCH($D17&"",'All Data'!$A:$A,0)),"-") | N17: ==IFERROR(INDEX('All Data'!$AP:$AP,MATCH($D17&"",'All Data'!$A:$A,0)),"-")
A18: 11 | B18: Weber | C18: Tract 2016 | D18: 49057201600 | E18: ==IFERROR(INDEX('All Data'!$D:$D,MATCH($D18&"",'All Data'!$A:$A,0)),"-") | F18: ==IFERROR(INDEX('All Data'!$E:$E,MATCH($D18&"",'All Data'!$A:$A,0)),"-") | G18: ==IFERROR(INDEX('All Data'!$F:$F,MATCH($D18&"",'All Data'!$A:$A,0)),"-") | H18: ==IFERROR(INDEX('All Data'!$G:$G,MATCH($D18&"",'All Data'!$A:$A,0)),"-") | I18: ==IFERROR(INDEX('All Data'!$I:$I,MATCH($D18&"",'All Data'!$A:$A,0)),"-") | J18: ==IFERROR(INDEX('All Data'!$J:$J,MATCH($D18&"",'All Data'!$A:$A,0)),"-") | K18: ==IFERROR(INDEX('All Data'!$AF:$AF,MATCH($D18&"",'All Data'!$A:$A,0)),"-") | L18: ==IFERROR(INDEX('All Data'!$AA:$AA,MATCH($D18&"",'All Data'!$A:$A,0)),"-") | M18: ==IFERROR(INDEX('All Data'!$AK:$AK,MATCH($D18&"",'All Data'!$A:$A,0)),"-") | N18: ==IFERROR(INDEX('All Data'!$AP:$AP,MATCH($D18&"",'All Data'!$A:$A,0)),"-")
A19: 12 | B19: Weber | C19: Tract 2018 | D19: 49057201800 | E19: ==IFERROR(INDEX('All Data'!$D:$D,MATCH($D19&"",'All Data'!$A:$A,0)),"-") | F19: ==IFERROR(INDEX('All Data'!$E:$E,MATCH($D19&"",'All Data'!$A:$A,0)),"-") | G19: ==IFERROR(INDEX('All Data'!$F:$F,MATCH($D19&"",'All Data'!$A:$A,0)),"-") | H19: ==IFERROR(INDEX('All Data'!$G:$G,MATCH($D19&"",'All Data'!$A:$A,0)),"-") | I19: ==IFERROR(INDEX('All Data'!$I:$I,MATCH($D19&"",'All Data'!$A:$A,0)),"-") | J19: ==IFERROR(INDEX('All Data'!$J:$J,MATCH($D19&"",'All Data'!$A:$A,0)),"-") | K19: ==IFERROR(INDEX('All Data'!$AF:$AF,MATCH($D19&"",'All Data'!$A:$A,0)),"-") | L19: ==IFERROR(INDEX('All Data'!$AA:$AA,MATCH($D19&"",'All Data'!$A:$A,0)),"-") | M19: ==IFERROR(INDEX('All Data'!$AK:$AK,MATCH($D19&"",'All Data'!$A:$A,0)),"-") | N19: ==IFERROR(INDEX('All Data'!$AP:$AP,MATCH($D19&"",'All Data'!$A:$A,0)),"-")
... A23: 16 | B23: Weber | C23: Tract 2108 | D23: 49057210800 | E23: ==IFERROR(INDEX('All Data'!$D:$D,MATCH($D23&"",'All Data'!$A:$A,0)),"-") | F23: ==IFERROR(INDEX('All Data'!$E:$E,MATCH($D23&"",'All Data'!$A:$A,0)),"-") | G23: ==IFERROR(INDEX('All Data'!$F:$F,MATCH($D23&"",'All Data'!$A:$A,0)),"-") | H23: ==IFERROR(INDEX('All Data'!$G:$G,MATCH($D23&"",'All Data'!$A:$A,0)),"-") | I23: ==IFERROR(INDEX('All Data'!$I:$I,MATCH($D23&"",'All Data'!$A:$A,0)),"-") | J23: ==IFERROR(INDEX('All Data'!$J:$J,MATCH($D23&"",'All Data'!$A:$A,0)),"-") | K23: ==IFERROR(INDEX('All Data'!$AF:$AF,MATCH($D23&"",'All Data'!$A:$A,0)),"-") | L23: ==IFERROR(INDEX('All Data'!$AA:$AA,MATCH($D23&"",'All Data'!$A:$A,0)),"-") | M23: ==IFERROR(INDEX('All Data'!$AK:$AK,MATCH($D23&"",'All Data'!$A:$A,0)),"-") | N23: ==IFERROR(INDEX('All Data'!$AP:$AP,MATCH($D23&"",'All Data'!$A:$A,0)),"-")
A24: Davis County — 8 Eligible Tracts
A25: 01 | B25: Davis | C25: Tract 1252.01 | D25: 49011125201 | E25: ==IFERROR(INDEX('All Data'!$D:$D,MATCH($D25&"",'All Data'!$A:$A,0)),"-") | F25: ==IFERROR(INDEX('All Data'!$E:$E,MATCH($D25&"",'All Data'!$A:$A,0)),"-") | G25: ==IFERROR(INDEX('All Data'!$F:$F,MATCH($D25&"",'All Data'!$A:$A,0)),"-") | H25: ==IFERROR(INDEX('All Data'!$G:$G,MATCH($D25&"",'All Data'!$A:$A,0)),"-") | I25: ==IFERROR(INDEX('All Data'!$I:$I,MATCH($D25&"",'All Data'!$A:$A,0)),"-") | J25: ==IFERROR(INDEX('All Data'!$J:$J,MATCH($D25&"",'All Data'!$A:$A,0)),"-") | K25: ==IFERROR(INDEX('All Data'!$AF:$AF,MATCH($D25&"",'All Data'!$A:$A,0)),"-") | L25: ==IFERROR(INDEX('All Data'!$AA:$AA,MATCH($D25&"",'All Data'!$A:$A,0)),"-") | M25: ==IFERROR(INDEX('All Data'!$AK:$AK,MATCH($D25&"",'All Data'!$A:$A,0)),"-") | N25: ==IFERROR(INDEX('All Data'!$AP:$AP,MATCH($D25&"",'All Data'!$A:$A,0)),"-")
A26: 02 | B26: Davis | C26: Tract 1253.01 | D26: 49011125301 | E26: ==IFERROR(INDEX('All Data'!$D:$D,MATCH($D26&"",'All Data'!$A:$A,0)),"-") | F26: ==IFERROR(INDEX('All Data'!$E:$E,MATCH($D26&"",'All Data'!$A:$A,0)),"-") | G26: ==IFERROR(INDEX('All Data'!$F:$F,MATCH($D26&"",'All Data'!$A:$A,0)),"-") | H26: ==IFERROR(INDEX('All Data'!$G:$G,MATCH($D26&"",'All Data'!$A:$A,0)),"-") | I26: ==IFERROR(INDEX('All Data'!$I:$I,MATCH($D26&"",'All Data'!$A:$A,0)),"-") | J26: ==IFERROR(INDEX('All Data'!$J:$J,MATCH($D26&"",'All Data'!$A:$A,0)),"-") | K26: ==IFERROR(INDEX('All Data'!$AF:$AF,MATCH($D26&"",'All Data'!$A:$A,0)),"-") | L26: ==IFERROR(INDEX('All Data'!$AA:$AA,MATCH($D26&"",'All Data'!$A:$A,0)),"-") | M26: ==IFERROR(INDEX('All Data'!$AK:$AK,MATCH($D26&"",'All Data'!$A:$A,0)),"-") | N26: ==IFERROR(INDEX('All Data'!$AP:$AP,MATCH($D26&"",'All Data'!$A:$A,0)),"-")
A27: 03 | B27: Davis | C27: Tract 1256 | D27: 49011125600 | E27: ==IFERROR(INDEX('All Data'!$D:$D,MATCH($D27&"",'All Data'!$A:$A,0)),"-") | F27: ==IFERROR(INDEX('All Data'!$E:$E,MATCH($D27&"",'All Data'!$A:$A,0)),"-") | G27: ==IFERROR(INDEX('All Data'!$F:$F,MATCH($D27&"",'All Data'!$A:$A,0)),"-") | H27: ==IFERROR(INDEX('All Data'!$G:$G,MATCH($D27&"",'All Data'!$A:$A,0)),"-") | I27: ==IFERROR(INDEX('All Data'!$I:$I,MATCH($D27&"",'All Data'!$A:$A,0)),"-") | J27: ==IFERROR(INDEX('All Data'!$J:$J,MATCH($D27&"",'All Data'!$A:$A,0)),"-") | K27: ==IFERROR(INDEX('All Data'!$AF:$AF,MATCH($D27&"",'All Data'!$A:$A,0)),"-") | L27: ==IFERROR(INDEX('All Data'!$AA:$AA,MATCH($D27&"",'All Data'!$A:$A,0)),"-") | M27: ==IFERROR(INDEX('All Data'!$AK:$AK,MATCH($D27&"",'All Data'!$A:$A,0)),"-") | N27: ==IFERROR(INDEX('All Data'!$AP:$AP,MATCH($D27&"",'All Data'!$A:$A,0)),"-")
A28: 04 | B28: Davis | C28: Tract 1257.01 | D28: 49011125701 | E28: ==IFERROR(INDEX('All Data'!$D:$D,MATCH($D28&"",'All Data'!$A:$A,0)),"-") | F28: ==IFERROR(INDEX('All Data'!$E:$E,MATCH($D28&"",'All Data'!$A:$A,0)),"-") | G28: ==IFERROR(INDEX('All Data'!$F:$F,MATCH($D28&"",'All Data'!$A:$A,0)),"-") | H28: ==IFERROR(INDEX('All Data'!$G:$G,MATCH($D28&"",'All Data'!$A:$A,0)),"-") | I28: ==IFERROR(INDEX('All Data'!$I:$I,MATCH($D28&"",'All Data'!$A:$A,0)),"-") | J28: ==IFERROR(INDEX('All Data'!$J:$J,MATCH($D28&"",'All Data'!$A:$A,0)),"-") | K28: ==IFERROR(INDEX('All Data'!$AF:$AF,MATCH($D28&"",'All Data'!$A:$A,0)),"-") | L28: ==IFERROR(INDEX('All Data'!$AA:$AA,MATCH($D28&"",'All Data'!$A:$A,0)),"-") | M28: ==IFERROR(INDEX('All Data'!$AK:$AK,MATCH($D28&"",'All Data'!$A:$A,0)),"-") | N28: ==IFERROR(INDEX('All Data'!$AP:$AP,MATCH($D28&"",'All Data'!$A:$A,0)),"-")
A29: 05 | B29: Davis | C29: Tract 1257.02 | D29: 49011125702 | E29: ==IFERROR(INDEX('All Data'!$D:$D,MATCH($D29&"",'All Data'!$A:$A,0)),"-") | F29: ==IFERROR(INDEX('All Data'!$E:$E,MATCH($D29&"",'All Data'!$A:$A,0)),"-") | G29: ==IFERROR(INDEX('All Data'!$F:$F,MATCH($D29&"",'All Data'!$A:$A,0)),"-") | H29: ==IFERROR(INDEX('All Data'!$G:$G,MATCH($D29&"",'All Data'!$A:$A,0)),"-") | I29: ==IFERROR(INDEX('All Data'!$I:$I,MATCH($D29&"",'All Data'!$A:$A,0)),"-") | J29: ==IFERROR(INDEX('All Data'!$J:$J,MATCH($D29&"",'All Data'!$A:$A,0)),"-") | K29: ==IFERROR(INDEX('All Data'!$AF:$AF,MATCH($D29&"",'All Data'!$A:$A,0)),"-") | L29: ==IFERROR(INDEX('All Data'!$AA:$AA,MATCH($D29&"",'All Data'!$A:$A,0)),"-") | M29: ==IFERROR(INDEX('All Data'!$AK:$AK,MATCH($D29&"",'All Data'!$A:$A,0)),"-") | N29: ==IFERROR(INDEX('All Data'!$AP:$AP,MATCH($D29&"",'All Data'!$A:$A,0)),"-")
A30: 06 | B30: Davis | C30: Tract 1258.01 | D30: 49011125801 | E30: ==IFERROR(INDEX('All Data'!$D:$D,MATCH($D30&"",'All Data'!$A:$A,0)),"-") | F30: ==IFERROR(INDEX('All Data'!$E:$E,MATCH($D30&"",'All Data'!$A:$A,0)),"-") | G30: ==IFERROR(INDEX('All Data'!$F:$F,MATCH($D30&"",'All Data'!$A:$A,0)),"-") | H30: ==IFERROR(INDEX('All Data'!$G:$G,MATCH($D30&"",'All Data'!$A:$A,0)),"-") | I30: ==IFERROR(INDEX('All Data'!$I:$I,MATCH($D30&"",'All Data'!$A:$A,0)),"-") | J30: ==IFERROR(INDEX('All Data'!$J:$J,MATCH($D30&"",'All Data'!$A:$A,0)),"-") | K30: ==IFERROR(INDEX('All Data'!$AF:$AF,MATCH($D30&"",'All Data'!$A:$A,0)),"-") | L30: ==IFERROR(INDEX('All Data'!$AA:$AA,MATCH($D30&"",'All Data'!$A:$A,0)),"-") | M30: ==IFERROR(INDEX('All Data'!$AK:$AK,MATCH($D30&"",'All Data'!$A:$A,0)),"-") | N30: ==IFERROR(INDEX('All Data'!$AP:$AP,MATCH($D30&"",'All Data'!$A:$A,0)),"-")
A31: 07 | B31: Davis | C31: Tract 1258.10 | D31: 49011125810 | E31: ==IFERROR(INDEX('All Data'!$D:$D,MATCH($D31&"",'All Data'!$A:$A,0)),"-") | F31: ==IFERROR(INDEX('All Data'!$E:$E,MATCH($D31&"",'All Data'!$A:$A,0)),"-") | G31: ==IFERROR(INDEX('All Data'!$F:$F,MATCH($D31&"",'All Data'!$A:$A,0)),"-") | H31: ==IFERROR(INDEX('All Data'!$G:$G,MATCH($D31&"",'All Data'!$A:$A,0)),"-") | I31: ==IFERROR(INDEX('All Data'!$I:$I,MATCH($D31&"",'All Data'!$A:$A,0)),"-") | J31: ==IFERROR(INDEX('All Data'!$J:$J,MATCH($D31&"",'All Data'!$A:$A,0)),"-") | K31: ==IFERROR(INDEX('All Data'!$AF:$AF,MATCH($D31&"",'All Data'!$A:$A,0)),"-") | L31: ==IFERROR(INDEX('All Data'!$AA:$AA,MATCH($D31&"",'All Data'!$A:$A,0)),"-") | M31: ==IFERROR(INDEX('All Data'!$AK:$AK,MATCH($D31&"",'All Data'!$A:$A,0)),"-") | N31: ==IFERROR(INDEX('All Data'!$AP:$AP,MATCH($D31&"",'All Data'!$A:$A,0)),"-")
A32: 08 | B32: Davis | C32: Tract 1267 | D32: 49011126700 | E32: ==IFERROR(INDEX('All Data'!$D:$D,MATCH($D32&"",'All Data'!$A:$A,0)),"-") | F32: ==IFERROR(INDEX('All Data'!$E:$E,MATCH($D32&"",'All Data'!$A:$A,0)),"-") | G32: ==IFERROR(INDEX('All Data'!$F:$F,MATCH($D32&"",'All Data'!$A:$A,0)),"-") | H32: ==IFERROR(INDEX('All Data'!$G:$G,MATCH($D32&"",'All Data'!$A:$A,0)),"-") | I32: ==IFERROR(INDEX('All Data'!$I:$I,MATCH($D32&"",'All Data'!$A:$A,0)),"-") | J32: ==IFERROR(INDEX('All Data'!$J:$J,MATCH($D32&"",'All Data'!$A:$A,0)),"-") | K32: ==IFERROR(INDEX('All Data'!$AF:$AF,MATCH($D32&"",'All Data'!$A:$A,0)),"-") | L32: ==IFERROR(INDEX('All Data'!$AA:$AA,MATCH($D32&"",'All Data'!$A:$A,0)),"-") | M32: ==IFERROR(INDEX('All Data'!$AK:$AK,MATCH($D32&"",'All Data'!$A:$A,0)),"-") | N32: ==IFERROR(INDEX('All Data'!$AP:$AP,MATCH($D32&"",'All Data'!$A:$A,0)),"-")
A33: Salt Lake County — 49 Eligible Tracts
A34: 01 | B34: Salt Lake | C34: Tract 1003.06 | D34: 49035100306 | E34: ==IFERROR(INDEX('All Data'!$D:$D,MATCH($D34&"",'All Data'!$A:$A,0)),"-") | F34: ==IFERROR(INDEX('All Data'!$E:$E,MATCH($D34&"",'All Data'!$A:$A,0)),"-") | G34: ==IFERROR(INDEX('All Data'!$F:$F,MATCH($D34&"",'All Data'!$A:$A,0)),"-") | H34: ==IFERROR(INDEX('All Data'!$G:$G,MATCH($D34&"",'All Data'!$A:$A,0)),"-") | I34: ==IFERROR(INDEX('All Data'!$I:$I,MATCH($D34&"",'All Data'!$A:$A,0)),"-") | J34: ==IFERROR(INDEX('All Data'!$J:$J,MATCH($D34&"",'All Data'!$A:$A,0)),"-") | K34: ==IFERROR(INDEX('All Data'!$AF:$AF,MATCH($D34&"",'All Data'!$A:$A,0)),"-") | L34: ==IFERROR(INDEX('All Data'!$AA:$AA,MATCH($D34&"",'All Data'!$A:$A,0)),"-") | M34: ==IFERROR(INDEX('All Data'!$AK:$AK,MATCH($D34&"",'All Data'!$A:$A,0)),"-") | N34: ==IFERROR(INDEX('All Data'!$AP:$AP,MATCH($D34&"",'All Data'!$A:$A,0)),"-")
A35: 02 | B35: Salt Lake | C35: Tract 1003.08 | D35: 49035100308 | E35: ==IFERROR(INDEX('All Data'!$D:$D,MATCH($D35&"",'All Data'!$A:$A,0)),"-") | F35: ==IFERROR(INDEX('All Data'!$E:$E,MATCH($D35&"",'All Data'!$A:$A,0)),"-") | G35: ==IFERROR(INDEX('All Data'!$F:$F,MATCH($D35&"",'All Data'!$A:$A,0)),"-") | H35: ==IFERROR(INDEX('All Data'!$G:$G,MATCH($D35&"",'All Data'!$A:$A,0)),"-") | I35: ==IFERROR(INDEX('All Data'!$I:$I,MATCH($D35&"",'All Data'!$A:$A,0)),"-") | J35: ==IFERROR(INDEX('All Data'!$J:$J,MATCH($D35&"",'All Data'!$A:$A,0)),"-") | K35: ==IFERROR(INDEX('All Data'!$AF:$AF,MATCH($D35&"",'All Data'!$A:$A,0)),"-") | L35: ==IFERROR(INDEX('All Data'!$AA:$AA,MATCH($D35&"",'All Data'!$A:$A,0)),"-") | M35: ==IFERROR(INDEX('All Data'!$AK:$AK,MATCH($D35&"",'All Data'!$A:$A,0)),"-") | N35: ==IFERROR(INDEX('All Data'!$AP:$AP,MATCH($D35&"",'All Data'!$A:$A,0)),"-")
A36: 03 | B36: Salt Lake | C36: Tract 1005 | D36: 49035100500 | E36: ==IFERROR(INDEX('All Data'!$D:$D,MATCH($D36&"",'All Data'!$A:$A,0)),"-") | F36: ==IFERROR(INDEX('All Data'!$E:$E,MATCH($D36&"",'All Data'!$A:$A,0)),"-") | G36: ==IFERROR(INDEX('All Data'!$F:$F,MATCH($D36&"",'All Data'!$A:$A,0)),"-") | H36: ==IFERROR(INDEX('All Data'!$G:$G,MATCH($D36&"",'All Data'!$A:$A,0)),"-") | I36: ==IFERROR(INDEX('All Data'!$I:$I,MATCH($D36&"",'All Data'!$A:$A,0)),"-") | J36: ==IFERROR(INDEX('All Data'!$J:$J,MATCH($D36&"",'All Data'!$A:$A,0)),"-") | K36: ==IFERROR(INDEX('All Data'!$AF:$AF,MATCH($D36&"",'All Data'!$A:$A,0)),"-") | L36: ==IFERROR(INDEX('All Data'!$AA:$AA,MATCH($D36&"",'All Data'!$A:$A,0)),"-") | M36: ==IFERROR(INDEX('All Data'!$AK:$AK,MATCH($D36&"",'All Data'!$A:$A,0)),"-") | N36: ==IFERROR(INDEX('All Data'!$AP:$AP,MATCH($D36&"",'All Data'!$A:$A,0)),"-")
A37: 04 | B37: Salt Lake | C37: Tract 1006 | D37: 49035100600 | E37: ==IFERROR(INDEX('All Data'!$D:$D,MATCH($D37&"",'All Data'!$A:$A,0)),"-") | F37: ==IFERROR(INDEX('All Data'!$E:$E,MATCH($D37&"",'All Data'!$A:$A,0)),"-") | G37: ==IFERROR(INDEX('All Data'!$F:$F,MATCH($D37&"",'All Data'!$A:$A,0)),"-") | H37: ==IFERROR(INDEX('All Data'!$G:$G,MATCH($D37&"",'All Data'!$A:$A,0)),"-") | I37: ==IFERROR(INDEX('All Data'!$I:$I,MATCH($D37&"",'All Data'!$A:$A,0)),"-") | J37: ==IFERROR(INDEX('All Data'!$J:$J,MATCH($D37&"",'All Data'!$A:$A,0)),"-") | K37: ==IFERROR(INDEX('All Data'!$AF:$AF,MATCH($D37&"",'All Data'!$A:$A,0)),"-") | L37: ==IFERROR(INDEX('All Data'!$AA:$AA,MATCH($D37&"",'All Data'!$A:$A,0)),"-") | M37: ==IFERROR(INDEX('All Data'!$AK:$AK,MATCH($D37&"",'All Data'!$A:$A,0)),"-") | N37: ==IFERROR(INDEX('All Data'!$AP:$AP,MATCH($D37&"",'All Data'!$A:$A,0)),"-")
A38: 05 | B38: Salt Lake | C38: Tract 1008 | D38: 49035100800 | E38: ==IFERROR(INDEX('All Data'!$D:$D,MATCH($D38&"",'All Data'!$A:$A,0)),"-") | F38: ==IFERROR(INDEX('All Data'!$E:$E,MATCH($D38&"",'All Data'!$A:$A,0)),"-") | G38: ==IFERROR(INDEX('All Data'!$F:$F,MATCH($D38&"",'All Data'!$A:$A,0)),"-") | H38: ==IFERROR(INDEX('All Data'!$G:$G,MATCH($D38&"",'All Data'!$A:$A,0)),"-") | I38: ==IFERROR(INDEX('All Data'!$I:$I,MATCH($D38&"",'All Data'!$A:$A,0)),"-") | J38: ==IFERROR(INDEX('All Data'!$J:$J,MATCH($D38&"",'All Data'!$A:$A,0)),"-") | K38: ==IFERROR(INDEX('All Data'!$AF:$AF,MATCH($D38&"",'All Data'!$A:$A,0)),"-") | L38: ==IFERROR(INDEX('All Data'!$AA:$AA,MATCH($D38&"",'All Data'!$A:$A,0)),"-") | M38: ==IFERROR(INDEX('All Data'!$AK:$AK,MATCH($D38&"",'All Data'!$A:$A,0)),"-") | N38: ==IFERROR(INDEX('All Data'!$AP:$AP,MATCH($D38&"",'All Data'!$A:$A,0)),"-")
A39: 06 | B39: Salt Lake | C39: Tract 1014.01 | D39: 49035101401 | E39: ==IFERROR(INDEX('All Data'!$D:$D,MATCH($D39&"",'All Data'!$A:$A,0)),"-") | F39: ==IFERROR(INDEX('All Data'!$E:$E,MATCH($D39&"",'All Data'!$A:$A,0)),"-") | G39: ==IFERROR(INDEX('All Data'!$F:$F,MATCH($D39&"",'All Data'!$A:$A,0)),"-") | H39: ==IFERROR(INDEX('All Data'!$G:$G,MATCH($D39&"",'All Data'!$A:$A,0)),"-") | I39: ==IFERROR(INDEX('All Data'!$I:$I,MATCH($D39&"",'All Data'!$A:$A,0)),"-") | J39: ==IFERROR(INDEX('All Data'!$J:$J,MATCH($D39&"",'All Data'!$A:$A,0)),"-") | K39: ==IFERROR(INDEX('All Data'!$AF:$AF,MATCH($D39&"",'All Data'!$A:$A,0)),"-") | L39: ==IFERROR(INDEX('All Data'!$AA:$AA,MATCH($D39&"",'All Data'!$A:$A,0)),"-") | M39: ==IFERROR(INDEX('All Data'!$AK:$AK,MATCH($D39&"",'All Data'!$A:$A,0)),"-") | N39: ==IFERROR(INDEX('All Data'!$AP:$AP,MATCH($D39&"",'All Data'!$A:$A,0)),"-")
A40: 07 | B40: Salt Lake | C40: Tract 1014.02 | D40: 49035101402 | E40: ==IFERROR(INDEX('All Data'!$D:$D,MATCH($D40&"",'All Data'!$A:$A,0)),"-") | F40: ==IFERROR(INDEX('All Data'!$E:$E,MATCH($D40&"",'All Data'!$A:$A,0)),"-") | G40: ==IFERROR(INDEX('All Data'!$F:$F,MATCH($D40&"",'All Data'!$A:$A,0)),"-") | H40: ==IFERROR(INDEX('All Data'!$G:$G,MATCH($D40&"",'All Data'!$A:$A,0)),"-") | I40: ==IFERROR(INDEX('All Data'!$I:$I,MATCH($D40&"",'All Data'!$A:$A,0)),"-") | J40: ==IFERROR(INDEX('All Data'!$J:$J,MATCH($D40&"",'All Data'!$A:$A,0)),"-") | K40: ==IFERROR(INDEX('All Data'!$AF:$AF,MATCH($D40&"",'All Data'!$A:$A,0)),"-") | L40: ==IFERROR(INDEX('All Data'!$AA:$AA,MATCH($D40&"",'All Data'!$A:$A,0)),"-") | M40: ==IFERROR(INDEX('All Data'!$AK:$AK,MATCH($D40&"",'All Data'!$A:$A,0)),"-") | N40: ==IFERROR(INDEX('All Data'!$AP:$AP,MATCH($D40&"",'All Data'!$A:$A,0)),"-")
A41: 08 | B41: Salt Lake | C41: Tract 1015 | D41: 49035101500 | E41: ==IFERROR(INDEX('All Data'!$D:$D,MATCH($D41&"",'All Data'!$A:$A,0)),"-") | F41: ==IFERROR(INDEX('All Data'!$E:$E,MATCH($D41&"",'All Data'!$A:$A,0)),"-") | G41: ==IFERROR(INDEX('All Data'!$F:$F,MATCH($D41&"",'All Data'!$A:$A,0)),"-") | H41: ==IFERROR(INDEX('All Data'!$G:$G,MATCH($D41&"",'All Data'!$A:$A,0)),"-") | I41: ==IFERROR(INDEX('All Data'!$I:$I,MATCH($D41&"",'All Data'!$A:$A,0)),"-") | J41: ==IFERROR(INDEX('All Data'!$J:$J,MATCH($D41&"",'All Data'!$A:$A,0)),"-") | K41: ==IFERROR(INDEX('All Data'!$AF:$AF,MATCH($D41&"",'All Data'!$A:$A,0)),"-") | L41: ==IFERROR(INDEX('All Data'!$AA:$AA,MATCH($D41&"",'All Data'!$A:$A,0)),"-") | M41: ==IFERROR(INDEX('All Data'!$AK:$AK,MATCH($D41&"",'All Data'!$A:$A,0)),"-") | N41: ==IFERROR(INDEX('All Data'!$AP:$AP,MATCH($D41&"",'All Data'!$A:$A,0)),"-")
A42: 09 | B42: Salt Lake | C42: Tract 1016 | D42: 49035101600 | E42: ==IFERROR(INDEX('All Data'!$D:$D,MATCH($D42&"",'All Data'!$A:$A,0)),"-") | F42: ==IFERROR(INDEX('All Data'!$E:$E,MATCH($D42&"",'All Data'!$A:$A,0)),"-") | G42: ==IFERROR(INDEX('All Data'!$F:$F,MATCH($D42&"",'All Data'!$A:$A,0)),"-") | H42: ==IFERROR(INDEX('All Data'!$G:$G,MATCH($D42&"",'All Data'!$A:$A,0)),"-") | I42: ==IFERROR(INDEX('All Data'!$I:$I,MATCH($D42&"",'All Data'!$A:$A,0)),"-") | J42: ==IFERROR(INDEX('All Data'!$J:$J,MATCH($D42&"",'All Data'!$A:$A,0)),"-") | K42: ==IFERROR(INDEX('All Data'!$AF:$AF,MATCH($D42&"",'All Data'!$A:$A,0)),"-") | L42: ==IFERROR(INDEX('All Data'!$AA:$AA,MATCH($D42&"",'All Data'!$A:$A,0)),"-") | M42: ==IFERROR(INDEX('All Data'!$AK:$AK,MATCH($D42&"",'All Data'!$A:$A,0)),"-") | N42: ==IFERROR(INDEX('All Data'!$AP:$AP,MATCH($D42&"",'All Data'!$A:$A,0)),"-")
A43: 10 | B43: Salt Lake | C43: Tract 1017 | D43: 49035101700 | E43: ==IFERROR(INDEX('All Data'!$D:$D,MATCH($D43&"",'All Data'!$A:$A,0)),"-") | F43: ==IFERROR(INDEX('All Data'!$E:$E,MATCH($D43&"",'All Data'!$A:$A,0)),"-") | G43: ==IFERROR(INDEX('All Data'!$F:$F,MATCH($D43&"",'All Data'!$A:$A,0)),"-") | H43: ==IFERROR(INDEX('All Data'!$G:$G,MATCH($D43&"",'All Data'!$A:$A,0)),"-") | I43: ==IFERROR(INDEX('All Data'!$I:$I,MATCH($D43&"",'All Data'!$A:$A,0)),"-") | J43: ==IFERROR(INDEX('All Data'!$J:$J,MATCH($D43&"",'All Data'!$A:$A,0)),"-") | K43: ==IFERROR(INDEX('All Data'!$AF:$AF,MATCH($D43&"",'All Data'!$A:$A,0)),"-") | L43: ==IFERROR(INDEX('All Data'!$AA:$AA,MATCH($D43&"",'All Data'!$A:$A,0)),"-") | M43: ==IFERROR(INDEX('All Data'!$AK:$AK,MATCH($D43&"",'All Data'!$A:$A,0)),"-") | N43: ==IFERROR(INDEX('All Data'!$AP:$AP,MATCH($D43&"",'All Data'!$A:$A,0)),"-")
A44: 11 | B44: Salt Lake | C44: Tract 1018 | D44: 49035101800 | E44: ==IFERROR(INDEX('All Data'!$D:$D,MATCH($D44&"",'All Data'!$A:$A,0)),"-") | F44: ==IFERROR(INDEX('All Data'!$E:$E,MATCH($D44&"",'All Data'!$A:$A,0)),"-") | G44: ==IFERROR(INDEX('All Data'!$F:$F,MATCH($D44&"",'All Data'!$A:$A,0)),"-") | H44: ==IFERROR(INDEX('All Data'!$G:$G,MATCH($D44&"",'All Data'!$A:$A,0)),"-") | I44: ==IFERROR(INDEX('All Data'!$I:$I,MATCH($D44&"",'All Data'!$A:$A,0)),"-") | J44: ==IFERROR(INDEX('All Data'!$J:$J,MATCH($D44&"",'All Data'!$A:$A,0)),"-") | K44: ==IFERROR(INDEX('All Data'!$AF:$AF,MATCH($D44&"",'All Data'!$A:$A,0)),"-") | L44: ==IFERROR(INDEX('All Data'!$AA:$AA,MATCH($D44&"",'All Data'!$A:$A,0)),"-") | M44: ==IFERROR(INDEX('All Data'!$AK:$AK,MATCH($D44&"",'All Data'!$A:$A,0)),"-") | N44: ==IFERROR(INDEX('All Data'!$AP:$AP,MATCH($D44&"",'All Data'!$A:$A,0)),"-")
A45: 12 | B45: Salt Lake | C45: Tract 1019 | D45: 49035101900 | E45: ==IFERROR(INDEX('All Data'!$D:$D,MATCH($D45&"",'All Data'!$A:$A,0)),"-") | F45: ==IFERROR(INDEX('All Data'!$E:$E,MATCH($D45&"",'All Data'!$A:$A,0)),"-") | G45: ==IFERROR(INDEX('All Data'!$F:$F,MATCH($D45&"",'All Data'!$A:$A,0)),"-") | H45: ==IFERROR(INDEX('All Data'!$G:$G,MATCH($D45&"",'All Data'!$A:$A,0)),"-") | I45: ==IFERROR(INDEX('All Data'!$I:$I,MATCH($D45&"",'All Data'!$A:$A,0)),"-") | J45: ==IFERROR(INDEX('All Data'!$J:$J,MATCH($D45&"",'All Data'!$A:$A,0)),"-") | K45: ==IFERROR(INDEX('All Data'!$AF:$AF,MATCH($D45&"",'All Data'!$A:$A,0)),"-") | L45: ==IFERROR(INDEX('All Data'!$AA:$AA,MATCH($D45&"",'All Data'!$A:$A,0)),"-") | M45: ==IFERROR(INDEX('All Data'!$AK:$AK,MATCH($D45&"",'All Data'!$A:$A,0)),"-") | N45: ==IFERROR(INDEX('All Data'!$AP:$AP,MATCH($D45&"",'All Data'!$A:$A,0)),"-")
... A82: 49 | B82: Salt Lake | C82: Tract 1147 | D82: 49035114700 | E82: ==IFERROR(INDEX('All Data'!$D:$D,MATCH($D82&"",'All Data'!$A:$A,0)),"-") | F82: ==IFERROR(INDEX('All Data'!$E:$E,MATCH($D82&"",'All Data'!$A:$A,0)),"-") | G82: ==IFERROR(INDEX('All Data'!$F:$F,MATCH($D82&"",'All Data'!$A:$A,0)),"-") | H82: ==IFERROR(INDEX('All Data'!$G:$G,MATCH($D82&"",'All Data'!$A:$A,0)),"-") | I82: ==IFERROR(INDEX('All Data'!$I:$I,MATCH($D82&"",'All Data'!$A:$A,0)),"-") | J82: ==IFERROR(INDEX('All Data'!$J:$J,MATCH($D82&"",'All Data'!$A:$A,0)),"-") | K82: ==IFERROR(INDEX('All Data'!$AF:$AF,MATCH($D82&"",'All Data'!$A:$A,0)),"-") | L82: ==IFERROR(INDEX('All Data'!$AA:$AA,MATCH($D82&"",'All Data'!$A:$A,0)),"-") | M82: ==IFERROR(INDEX('All Data'!$AK:$AK,MATCH($D82&"",'All Data'!$A:$A,0)),"-") | N82: ==IFERROR(INDEX('All Data'!$AP:$AP,MATCH($D82&"",'All Data'!$A:$A,0)),"-")
A83: Tooele County — 3 Eligible Tracts
A84: 01 | B84: Tooele | C84: Tract 1306 | D84: 49045130600 | E84: ==IFERROR(INDEX('All Data'!$D:$D,MATCH($D84&"",'All Data'!$A:$A,0)),"-") | F84: ==IFERROR(INDEX('All Data'!$E:$E,MATCH($D84&"",'All Data'!$A:$A,0)),"-") | G84: ==IFERROR(INDEX('All Data'!$F:$F,MATCH($D84&"",'All Data'!$A:$A,0)),"-") | H84: ==IFERROR(INDEX('All Data'!$G:$G,MATCH($D84&"",'All Data'!$A:$A,0)),"-") | I84: ==IFERROR(INDEX('All Data'!$I:$I,MATCH($D84&"",'All Data'!$A:$A,0)),"-") | J84: ==IFERROR(INDEX('All Data'!$J:$J,MATCH($D84&"",'All Data'!$A:$A,0)),"-") | K84: ==IFERROR(INDEX('All Data'!$AF:$AF,MATCH($D84&"",'All Data'!$A:$A,0)),"-") | L84: ==IFERROR(INDEX('All Data'!$AA:$AA,MATCH($D84&"",'All Data'!$A:$A,0)),"-") | M84: ==IFERROR(INDEX('All Data'!$AK:$AK,MATCH($D84&"",'All Data'!$A:$A,0)),"-") | N84: ==IFERROR(INDEX('All Data'!$AP:$AP,MATCH($D84&"",'All Data'!$A:$A,0)),"-")
A85: 02 | B85: Tooele | C85: Tract 1310.03 | D85: 49045131003 | E85: ==IFERROR(INDEX('All Data'!$D:$D,MATCH($D85&"",'All Data'!$A:$A,0)),"-") | F85: ==IFERROR(INDEX('All Data'!$E:$E,MATCH($D85&"",'All Data'!$A:$A,0)),"-") | G85: ==IFERROR(INDEX('All Data'!$F:$F,MATCH($D85&"",'All Data'!$A:$A,0)),"-") | H85: ==IFERROR(INDEX('All Data'!$G:$G,MATCH($D85&"",'All Data'!$A:$A,0)),"-") | I85: ==IFERROR(INDEX('All Data'!$I:$I,MATCH($D85&"",'All Data'!$A:$A,0)),"-") | J85: ==IFERROR(INDEX('All Data'!$J:$J,MATCH($D85&"",'All Data'!$A:$A,0)),"-") | K85: ==IFERROR(INDEX('All Data'!$AF:$AF,MATCH($D85&"",'All Data'!$A:$A,0)),"-") | L85: ==IFERROR(INDEX('All Data'!$AA:$AA,MATCH($D85&"",'All Data'!$A:$A,0)),"-") | M85: ==IFERROR(INDEX('All Data'!$AK:$AK,MATCH($D85&"",'All Data'!$A:$A,0)),"-") | N85: ==IFERROR(INDEX('All Data'!$AP:$AP,MATCH($D85&"",'All Data'!$A:$A,0)),"-")
A86: 03 | B86: Tooele | C86: Tract 1311.02 | D86: 49045131102 | E86: ==IFERROR(INDEX('All Data'!$D:$D,MATCH($D86&"",'All Data'!$A:$A,0)),"-") | F86: ==IFERROR(INDEX('All Data'!$E:$E,MATCH($D86&"",'All Data'!$A:$A,0)),"-") | G86: ==IFERROR(INDEX('All Data'!$F:$F,MATCH($D86&"",'All Data'!$A:$A,0)),"-") | H86: ==IFERROR(INDEX('All Data'!$G:$G,MATCH($D86&"",'All Data'!$A:$A,0)),"-") | I86: ==IFERROR(INDEX('All Data'!$I:$I,MATCH($D86&"",'All Data'!$A:$A,0)),"-") | J86: ==IFERROR(INDEX('All Data'!$J:$J,MATCH($D86&"",'All Data'!$A:$A,0)),"-") | K86: ==IFERROR(INDEX('All Data'!$AF:$AF,MATCH($D86&"",'All Data'!$A:$A,0)),"-") | L86: ==IFERROR(INDEX('All Data'!$AA:$AA,MATCH($D86&"",'All Data'!$A:$A,0)),"-") | M86: ==IFERROR(INDEX('All Data'!$AK:$AK,MATCH($D86&"",'All Data'!$A:$A,0)),"-") | N86: ==IFERROR(INDEX('All Data'!$AP:$AP,MATCH($D86&"",'All Data'!$A:$A,0)),"-")
A87: Utah County — 30 Eligible Tracts
A88: 01 | B88: Utah | C88: Tract 5.11 | D88: 49049000511 | E88: ==IFERROR(INDEX('All Data'!$D:$D,MATCH($D88&"",'All Data'!$A:$A,0)),"-") | F88: ==IFERROR(INDEX('All Data'!$E:$E,MATCH($D88&"",'All Data'!$A:$A,0)),"-") | G88: ==IFERROR(INDEX('All Data'!$F:$F,MATCH($D88&"",'All Data'!$A:$A,0)),"-") | H88: ==IFERROR(INDEX('All Data'!$G:$G,MATCH($D88&"",'All Data'!$A:$A,0)),"-") | I88: ==IFERROR(INDEX('All Data'!$I:$I,MATCH($D88&"",'All Data'!$A:$A,0)),"-") | J88: ==IFERROR(INDEX('All Data'!$J:$J,MATCH($D88&"",'All Data'!$A:$A,0)),"-") | K88: ==IFERROR(INDEX('All Data'!$AF:$AF,MATCH($D88&"",'All Data'!$A:$A,0)),"-") | L88: ==IFERROR(INDEX('All Data'!$AA:$AA,MATCH($D88&"",'All Data'!$A:$A,0)),"-") | M88: ==IFERROR(INDEX('All Data'!$AK:$AK,MATCH($D88&"",'All Data'!$A:$A,0)),"-") | N88: ==IFERROR(INDEX('All Data'!$AP:$AP,MATCH($D88&"",'All Data'!$A:$A,0)),"-")
A89: 02 | B89: Utah | C89: Tract 8.01 | D89: 49049000801 | E89: ==IFERROR(INDEX('All Data'!$D:$D,MATCH($D89&"",'All Data'!$A:$A,0)),"-") | F89: ==IFERROR(INDEX('All Data'!$E:$E,MATCH($D89&"",'All Data'!$A:$A,0)),"-") | G89: ==IFERROR(INDEX('All Data'!$F:$F,MATCH($D89&"",'All Data'!$A:$A,0)),"-") | H89: ==IFERROR(INDEX('All Data'!$G:$G,MATCH($D89&"",'All Data'!$A:$A,0)),"-") | I89: ==IFERROR(INDEX('All Data'!$I:$I,MATCH($D89&"",'All Data'!$A:$A,0)),"-") | J89: ==IFERROR(INDEX('All Data'!$J:$J,MATCH($D89&"",'All Data'!$A:$A,0)),"-") | K89: ==IFERROR(INDEX('All Data'!$AF:$AF,MATCH($D89&"",'All Data'!$A:$A,0)),"-") | L89: ==IFERROR(INDEX('All Data'!$AA:$AA,MATCH($D89&"",'All Data'!$A:$A,0)),"-") | M89: ==IFERROR(INDEX('All Data'!$AK:$AK,MATCH($D89&"",'All Data'!$A:$A,0)),"-") | N89: ==IFERROR(INDEX('All Data'!$AP:$AP,MATCH($D89&"",'All Data'!$A:$A,0)),"-")
A90: 03 | B90: Utah | C90: Tract 8.03 | D90: 49049000803 | E90: ==IFERROR(INDEX('All Data'!$D:$D,MATCH($D90&"",'All Data'!$A:$A,0)),"-") | F90: ==IFERROR(INDEX('All Data'!$E:$E,MATCH($D90&"",'All Data'!$A:$A,0)),"-") | G90: ==IFERROR(INDEX('All Data'!$F:$F,MATCH($D90&"",'All Data'!$A:$A,0)),"-") | H90: ==IFERROR(INDEX('All Data'!$G:$G,MATCH($D90&"",'All Data'!$A:$A,0)),"-") | I90: ==IFERROR(INDEX('All Data'!$I:$I,MATCH($D90&"",'All Data'!$A:$A,0)),"-") | J90: ==IFERROR(INDEX('All Data'!$J:$J,MATCH($D90&"",'All Data'!$A:$A,0)),"-") | K90: ==IFERROR(INDEX('All Data'!$AF:$AF,MATCH($D90&"",'All Data'!$A:$A,0)),"-") | L90: ==IFERROR(INDEX('All Data'!$AA:$AA,MATCH($D90&"",'All Data'!$A:$A,0)),"-") | M90: ==IFERROR(INDEX('All Data'!$AK:$AK,MATCH($D90&"",'All Data'!$A:$A,0)),"-") | N90: ==IFERROR(INDEX('All Data'!$AP:$AP,MATCH($D90&"",'All Data'!$A:$A,0)),"-")
A91: 04 | B91: Utah | C91: Tract 8.04 | D91: 49049000804 | E91: ==IFERROR(INDEX('All Data'!$D:$D,MATCH($D91&"",'All Data'!$A:$A,0)),"-") | F91: ==IFERROR(INDEX('All Data'!$E:$E,MATCH($D91&"",'All Data'!$A:$A,0)),"-") | G91: ==IFERROR(INDEX('All Data'!$F:$F,MATCH($D91&"",'All Data'!$A:$A,0)),"-") | H91: ==IFERROR(INDEX('All Data'!$G:$G,MATCH($D91&"",'All Data'!$A:$A,0)),"-") | I91: ==IFERROR(INDEX('All Data'!$I:$I,MATCH($D91&"",'All Data'!$A:$A,0)),"-") | J91: ==IFERROR(INDEX('All Data'!$J:$J,MATCH($D91&"",'All Data'!$A:$A,0)),"-") | K91: ==IFERROR(INDEX('All Data'!$AF:$AF,MATCH($D91&"",'All Data'!$A:$A,0)),"-") | L91: ==IFERROR(INDEX('All Data'!$AA:$AA,MATCH($D91&"",'All Data'!$A:$A,0)),"-") | M91: ==IFERROR(INDEX('All Data'!$AK:$AK,MATCH($D91&"",'All Data'!$A:$A,0)),"-") | N91: ==IFERROR(INDEX('All Data'!$AP:$AP,MATCH($D91&"",'All Data'!$A:$A,0)),"-")
A92: 05 | B92: Utah | C92: Tract 9.01 | D92: 49049000901 | E92: ==IFERROR(INDEX('All Data'!$D:$D,MATCH($D92&"",'All Data'!$A:$A,0)),"-") | F92: ==IFERROR(INDEX('All Data'!$E:$E,MATCH($D92&"",'All Data'!$A:$A,0)),"-") | G92: ==IFERROR(INDEX('All Data'!$F:$F,MATCH($D92&"",'All Data'!$A:$A,0)),"-") | H92: ==IFERROR(INDEX('All Data'!$G:$G,MATCH($D92&"",'All Data'!$A:$A,0)),"-") | I92: ==IFERROR(INDEX('All Data'!$I:$I,MATCH($D92&"",'All Data'!$A:$A,0)),"-") | J92: ==IFERROR(INDEX('All Data'!$J:$J,MATCH($D92&"",'All Data'!$A:$A,0)),"-") | K92: ==IFERROR(INDEX('All Data'!$AF:$AF,MATCH($D92&"",'All Data'!$A:$A,0)),"-") | L92: ==IFERROR(INDEX('All Data'!$AA:$AA,MATCH($D92&"",'All Data'!$A:$A,0)),"-") | M92: ==IFERROR(INDEX('All Data'!$AK:$AK,MATCH($D92&"",'All Data'!$A:$A,0)),"-") | N92: ==IFERROR(INDEX('All Data'!$AP:$AP,MATCH($D92&"",'All Data'!$A:$A,0)),"-")
A93: 06 | B93: Utah | C93: Tract 11.03 | D93: 49049001103 | E93: ==IFERROR(INDEX('All Data'!$D:$D,MATCH($D93&"",'All Data'!$A:$A,0)),"-") | F93: ==IFERROR(INDEX('All Data'!$E:$E,MATCH($D93&"",'All Data'!$A:$A,0)),"-") | G93: ==IFERROR(INDEX('All Data'!$F:$F,MATCH($D93&"",'All Data'!$A:$A,0)),"-") | H93: ==IFERROR(INDEX('All Data'!$G:$G,MATCH($D93&"",'All Data'!$A:$A,0)),"-") | I93: ==IFERROR(INDEX('All Data'!$I:$I,MATCH($D93&"",'All Data'!$A:$A,0)),"-") | J93: ==IFERROR(INDEX('All Data'!$J:$J,MATCH($D93&"",'All Data'!$A:$A,0)),"-") | K93: ==IFERROR(INDEX('All Data'!$AF:$AF,MATCH($D93&"",'All Data'!$A:$A,0)),"-") | L93: ==IFERROR(INDEX('All Data'!$AA:$AA,MATCH($D93&"",'All Data'!$A:$A,0)),"-") | M93: ==IFERROR(INDEX('All Data'!$AK:$AK,MATCH($D93&"",'All Data'!$A:$A,0)),"-") | N93: ==IFERROR(INDEX('All Data'!$AP:$AP,MATCH($D93&"",'All Data'!$A:$A,0)),"-")
A94: 07 | B94: Utah | C94: Tract 11.08 | D94: 49049001108 | E94: ==IFERROR(INDEX('All Data'!$D:$D,MATCH($D94&"",'All Data'!$A:$A,0)),"-") | F94: ==IFERROR(INDEX('All Data'!$E:$E,MATCH($D94&"",'All Data'!$A:$A,0)),"-") | G94: ==IFERROR(INDEX('All Data'!$F:$F,MATCH($D94&"",'All Data'!$A:$A,0)),"-") | H94: ==IFERROR(INDEX('All Data'!$G:$G,MATCH($D94&"",'All Data'!$A:$A,0)),"-") | I94: ==IFERROR(INDEX('All Data'!$I:$I,MATCH($D94&"",'All Data'!$A:$A,0)),"-") | J94: ==IFERROR(INDEX('All Data'!$J:$J,MATCH($D94&"",'All Data'!$A:$A,0)),"-") | K94: ==IFERROR(INDEX('All Data'!$AF:$AF,MATCH($D94&"",'All Data'!$A:$A,0)),"-") | L94: ==IFERROR(INDEX('All Data'!$AA:$AA,MATCH($D94&"",'All Data'!$A:$A,0)),"-") | M94: ==IFERROR(INDEX('All Data'!$AK:$AK,MATCH($D94&"",'All Data'!$A:$A,0)),"-") | N94: ==IFERROR(INDEX('All Data'!$AP:$AP,MATCH($D94&"",'All Data'!$A:$A,0)),"-")
A95: 08 | B95: Utah | C95: Tract 14.01 | D95: 49049001401 | E95: ==IFERROR(INDEX('All Data'!$D:$D,MATCH($D95&"",'All Data'!$A:$A,0)),"-") | F95: ==IFERROR(INDEX('All Data'!$E:$E,MATCH($D95&"",'All Data'!$A:$A,0)),"-") | G95: ==IFERROR(INDEX('All Data'!$F:$F,MATCH($D95&"",'All Data'!$A:$A,0)),"-") | H95: ==IFERROR(INDEX('All Data'!$G:$G,MATCH($D95&"",'All Data'!$A:$A,0)),"-") | I95: ==IFERROR(INDEX('All Data'!$I:$I,MATCH($D95&"",'All Data'!$A:$A,0)),"-") | J95: ==IFERROR(INDEX('All Data'!$J:$J,MATCH($D95&"",'All Data'!$A:$A,0)),"-") | K95: ==IFERROR(INDEX('All Data'!$AF:$AF,MATCH($D95&"",'All Data'!$A:$A,0)),"-") | L95: ==IFERROR(INDEX('All Data'!$AA:$AA,MATCH($D95&"",'All Data'!$A:$A,0)),"-") | M95: ==IFERROR(INDEX('All Data'!$AK:$AK,MATCH($D95&"",'All Data'!$A:$A,0)),"-") | N95: ==IFERROR(INDEX('All Data'!$AP:$AP,MATCH($D95&"",'All Data'!$A:$A,0)),"-")
A96: 09 | B96: Utah | C96: Tract 14.03 | D96: 49049001403 | E96: ==IFERROR(INDEX('All Data'!$D:$D,MATCH($D96&"",'All Data'!$A:$A,0)),"-") | F96: ==IFERROR(INDEX('All Data'!$E:$E,MATCH($D96&"",'All Data'!$A:$A,0)),"-") | G96: ==IFERROR(INDEX('All Data'!$F:$F,MATCH($D96&"",'All Data'!$A:$A,0)),"-") | H96: ==IFERROR(INDEX('All Data'!$G:$G,MATCH($D96&"",'All Data'!$A:$A,0)),"-") | I96: ==IFERROR(INDEX('All Data'!$I:$I,MATCH($D96&"",'All Data'!$A:$A,0)),"-") | J96: ==IFERROR(INDEX('All Data'!$J:$J,MATCH($D96&"",'All Data'!$A:$A,0)),"-") | K96: ==IFERROR(INDEX('All Data'!$AF:$AF,MATCH($D96&"",'All Data'!$A:$A,0)),"-") | L96: ==IFERROR(INDEX('All Data'!$AA:$AA,MATCH($D96&"",'All Data'!$A:$A,0)),"-") | M96: ==IFERROR(INDEX('All Data'!$AK:$AK,MATCH($D96&"",'All Data'!$A:$A,0)),"-") | N96: ==IFERROR(INDEX('All Data'!$AP:$AP,MATCH($D96&"",'All Data'!$A:$A,0)),"-")
A97: 10 | B97: Utah | C97: Tract 14.04 | D97: 49049001404 | E97: ==IFERROR(INDEX('All Data'!$D:$D,MATCH($D97&"",'All Data'!$A:$A,0)),"-") | F97: ==IFERROR(INDEX('All Data'!$E:$E,MATCH($D97&"",'All Data'!$A:$A,0)),"-") | G97: ==IFERROR(INDEX('All Data'!$F:$F,MATCH($D97&"",'All Data'!$A:$A,0)),"-") | H97: ==IFERROR(INDEX('All Data'!$G:$G,MATCH($D97&"",'All Data'!$A:$A,0)),"-") | I97: ==IFERROR(INDEX('All Data'!$I:$I,MATCH($D97&"",'All Data'!$A:$A,0)),"-") | J97: ==IFERROR(INDEX('All Data'!$J:$J,MATCH($D97&"",'All Data'!$A:$A,0)),"-") | K97: ==IFERROR(INDEX('All Data'!$AF:$AF,MATCH($D97&"",'All Data'!$A:$A,0)),"-") | L97: ==IFERROR(INDEX('All Data'!$AA:$AA,MATCH($D97&"",'All Data'!$A:$A,0)),"-") | M97: ==IFERROR(INDEX('All Data'!$AK:$AK,MATCH($D97&"",'All Data'!$A:$A,0)),"-") | N97: ==IFERROR(INDEX('All Data'!$AP:$AP,MATCH($D97&"",'All Data'!$A:$A,0)),"-")
A98: 11 | B98: Utah | C98: Tract 16.01 | D98: 49049001601 | E98: ==IFERROR(INDEX('All Data'!$D:$D,MATCH($D98&"",'All Data'!$A:$A,0)),"-") | F98: ==IFERROR(INDEX('All Data'!$E:$E,MATCH($D98&"",'All Data'!$A:$A,0)),"-") | G98: ==IFERROR(INDEX('All Data'!$F:$F,MATCH($D98&"",'All Data'!$A:$A,0)),"-") | H98: ==IFERROR(INDEX('All Data'!$G:$G,MATCH($D98&"",'All Data'!$A:$A,0)),"-") | I98: ==IFERROR(INDEX('All Data'!$I:$I,MATCH($D98&"",'All Data'!$A:$A,0)),"-") | J98: ==IFERROR(INDEX('All Data'!$J:$J,MATCH($D98&"",'All Data'!$A:$A,0)),"-") | K98: ==IFERROR(INDEX('All Data'!$AF:$AF,MATCH($D98&"",'All Data'!$A:$A,0)),"-") | L98: ==IFERROR(INDEX('All Data'!$AA:$AA,MATCH($D98&"",'All Data'!$A:$A,0)),"-") | M98: ==IFERROR(INDEX('All Data'!$AK:$AK,MATCH($D98&"",'All Data'!$A:$A,0)),"-") | N98: ==IFERROR(INDEX('All Data'!$AP:$AP,MATCH($D98&"",'All Data'!$A:$A,0)),"-")
A99: 12 | B99: Utah | C99: Tract 16.02 | D99: 49049001602 | E99: ==IFERROR(INDEX('All Data'!$D:$D,MATCH($D99&"",'All Data'!$A:$A,0)),"-") | F99: ==IFERROR(INDEX('All Data'!$E:$E,MATCH($D99&"",'All Data'!$A:$A,0)),"-") | G99: ==IFERROR(INDEX('All Data'!$F:$F,MATCH($D99&"",'All Data'!$A:$A,0)),"-") | H99: ==IFERROR(INDEX('All Data'!$G:$G,MATCH($D99&"",'All Data'!$A:$A,0)),"-") | I99: ==IFERROR(INDEX('All Data'!$I:$I,MATCH($D99&"",'All Data'!$A:$A,0)),"-") | J99: ==IFERROR(INDEX('All Data'!$J:$J,MATCH($D99&"",'All Data'!$A:$A,0)),"-") | K99: ==IFERROR(INDEX('All Data'!$AF:$AF,MATCH($D99&"",'All Data'!$A:$A,0)),"-") | L99: ==IFERROR(INDEX('All Data'!$AA:$AA,MATCH($D99&"",'All Data'!$A:$A,0)),"-") | M99: ==IFERROR(INDEX('All Data'!$AK:$AK,MATCH($D99&"",'All Data'!$A:$A,0)),"-") | N99: ==IFERROR(INDEX('All Data'!$AP:$AP,MATCH($D99&"",'All Data'!$A:$A,0)),"-")
... A117: 30 | B117: Utah | C117: Tract 9805 | D117: 49049980500 | E117: ==IFERROR(INDEX('All Data'!$D:$D,MATCH($D117&"",'All Data'!$A:$A,0)),"-") | F117: ==IFERROR(INDEX('All Data'!$E:$E,MATCH($D117&"",'All Data'!$A:$A,0)),"-") | G117: ==IFERROR(INDEX('All Data'!$F:$F,MATCH($D117&"",'All Data'!$A:$A,0)),"-") | H117: ==IFERROR(INDEX('All Data'!$G:$G,MATCH($D117&"",'All Data'!$A:$A,0)),"-") | I117: ==IFERROR(INDEX('All Data'!$I:$I,MATCH($D117&"",'All Data'!$A:$A,0)),"-") | J117: ==IFERROR(INDEX('All Data'!$J:$J,MATCH($D117&"",'All Data'!$A:$A,0)),"-") | K117: ==IFERROR(INDEX('All Data'!$AF:$AF,MATCH($D117&"",'All Data'!$A:$A,0)),"-") | L117: ==IFERROR(INDEX('All Data'!$AA:$AA,MATCH($D117&"",'All Data'!$A:$A,0)),"-") | M117: ==IFERROR(INDEX('All Data'!$AK:$AK,MATCH($D117&"",'All Data'!$A:$A,0)),"-") | N117: ==IFERROR(INDEX('All Data'!$AP:$AP,MATCH($D117&"",'All Data'!$A:$A,0)),"-")

Sheet Box Elder County
A1: Box Elder County — OZ 2.0 Candidate Tracts — Detail
A2: WFRC & MAG Region | Generated June 01, 2026
A4: =="01 — "&IFERROR(INDEX('All Data'!$C:$C,MATCH($H$4&"",'All Data'!$A:$A,0)),"")&" | GEOID "&$H$4&" | "&TEXT(IFERROR(INDEX('All Data'!$F:$F,MATCH($H$4&"",'All Data'!$A:$A,0)),0),"0")&" ac | "&IFERROR(INDEX('All Data'!$AP:$AP,MATCH($H$4&"",'All Data'!$A:$A,0)),"—") | H4: 49003960601
B5: TRACT PROFILE | D5: CENTERS & DISTRICTS | F5: HOUSING & DEMOGRAPHICS
B6: Population | C6: ==IFERROR(INDEX('All Data'!$D:$D,MATCH($H$4&"",'All Data'!$A:$A,0)),"-") | D6: WC MUorC % Total | E6: ==IFERROR(INDEX('All Data'!$J:$J,MATCH($H$4&"",'All Data'!$A:$A,0)),"-") | F6: Total Units | G6: ==IFERROR(INDEX('All Data'!$R:$R,MATCH($H$4&"",'All Data'!$A:$A,0)),"-")
B7: Households | C7: ==IFERROR(INDEX('All Data'!$E:$E,MATCH($H$4&"",'All Data'!$A:$A,0)),"-") | D7: Metropolitan Center | E7: ==IFERROR(INDEX('All Data'!$K:$K,MATCH($H$4&"",'All Data'!$A:$A,0)),"-") | F7: Residential Acres | G7: ==IFERROR(INDEX('All Data'!$S:$S,MATCH($H$4&"",'All Data'!$A:$A,0)),"-")
B8: Total Acres | C8: ==IFERROR(INDEX('All Data'!$F:$F,MATCH($H$4&"",'All Data'!$A:$A,0)),"-") | D8: Urban Center | E8: ==IFERROR(INDEX('All Data'!$L:$L,MATCH($H$4&"",'All Data'!$A:$A,0)),"-") | F8: SFD Acres | G8: ==IFERROR(INDEX('All Data'!$T:$T,MATCH($H$4&"",'All Data'!$A:$A,0)),"-")
B9: Developable Acres | C9: ==IFERROR(INDEX('All Data'!$G:$G,MATCH($H$4&"",'All Data'!$A:$A,0)),"-") | D9: City Center | E9: ==IFERROR(INDEX('All Data'!$M:$M,MATCH($H$4&"",'All Data'!$A:$A,0)),"-") | F9: MF / SFA Acres | G9: ==IFERROR(INDEX('All Data'!$U:$U,MATCH($H$4&"",'All Data'!$A:$A,0)),"-")
B10: OZ 1.0 Acres | C10: ==IFERROR(INDEX('All Data'!$H:$H,MATCH($H$4&"",'All Data'!$A:$A,0)),"-") | D10: Neighborhood Center | E10: ==IFERROR(INDEX('All Data'!$N:$N,MATCH($H$4&"",'All Data'!$A:$A,0)),"-") | F10: Poverty Rate | G10: ==IFERROR(INDEX('All Data'!$AL:$AL,MATCH($H$4&"",'All Data'!$A:$A,0)),"-")
B11: OZ 1.0 % of Tract | C11: ==IFERROR(INDEX('All Data'!$I:$I,MATCH($H$4&"",'All Data'!$A:$A,0)),"-") | D11: Employment District | E11: ==IFERROR(INDEX('All Data'!$O:$O,MATCH($H$4&"",'All Data'!$A:$A,0)),"-") | F11: Unemployment Rate | G11: ==IFERROR(INDEX('All Data'!$AM:$AM,MATCH($H$4&"",'All Data'!$A:$A,0)),"-")
D12: Industrial District | E12: ==IFERROR(INDEX('All Data'!$P:$P,MATCH($H$4&"",'All Data'!$A:$A,0)),"-") | F12: Median Family Income | G12: ==IFERROR(INDEX('All Data'!$AN:$AN,MATCH($H$4&"",'All Data'!$A:$A,0)),"-")
D13: Retail District | E13: ==IFERROR(INDEX('All Data'!$Q:$Q,MATCH($H$4&"",'All Data'!$A:$A,0)),"-")
B14: TRANSIT ACCESS | D14: AUTO ACCESS | F14: PROJECTED GROWTH 2027-37
B15: Rail / BRT Stops | C15: ==IFERROR(INDEX('All Data'!$V:$V,MATCH($H$4&"",'All Data'!$A:$A,0)),"-") | D15: Freeway Exits | E15: ==IFERROR(INDEX('All Data'!$AB:$AB,MATCH($H$4&"",'All Data'!$A:$A,0)),"-") | F15: Households Added | G15: ==IFERROR(INDEX('All Data'!$AG:$AG,MATCH($H$4&"",'All Data'!$A:$A,0)),"-")
B16: SAP Acres | C16: ==IFERROR(INDEX('All Data'!$W:$W,MATCH($H$4&"",'All Data'!$A:$A,0)),"-") | D16: Exit Distance (mi) | E16: ==IFERROR(INDEX('All Data'!$AC:$AC,MATCH($H$4&"",'All Data'!$A:$A,0)),"-") | F16: Population Added | G16: ==IFERROR(INDEX('All Data'!$AH:$AH,MATCH($H$4&"",'All Data'!$A:$A,0)),"-")
B17: SAP % of Tract | C17: ==IFERROR(INDEX('All Data'!$X:$X,MATCH($H$4&"",'All Data'!$A:$A,0)),"-") | D17: ATO Jobs (Auto) | E17: ==IFERROR(INDEX('All Data'!$AD:$AD,MATCH($H$4&"",'All Data'!$A:$A,0)),"-") | F17: Jobs Added | G17: ==IFERROR(INDEX('All Data'!$AI:$AI,MATCH($H$4&"",'All Data'!$A:$A,0)),"-")
B18: ATO Jobs (Transit) | C18: ==IFERROR(INDEX('All Data'!$Y:$Y,MATCH($H$4&"",'All Data'!$A:$A,0)),"-") | D18: ATO Households (Auto) | E18: ==IFERROR(INDEX('All Data'!$AE:$AE,MATCH($H$4&"",'All Data'!$A:$A,0)),"-") | F18: ERU Added | G18: ==IFERROR(INDEX('All Data'!$AJ:$AJ,MATCH($H$4&"",'All Data'!$A:$A,0)),"-")
B19: ATO Households (Transit) | C19: ==IFERROR(INDEX('All Data'!$Z:$Z,MATCH($H$4&"",'All Data'!$A:$A,0)),"-") | F19: ERU per Acre | G19: ==IFERROR(INDEX('All Data'!$AK:$AK,MATCH($H$4&"",'All Data'!$A:$A,0)),"-")
B20: SAP Planned HH/ac | C20: ==IFERROR(INDEX('All Data'!$AA:$AA,MATCH($H$4&"",'All Data'!$A:$A,0)),"-")
B22: INCOME | D22: POVERTY RATE | F22: UNEMPLOYMENT
C23: ==IFERROR(INDEX('All Data'!$AN:$AN,MATCH($H$4&"",'All Data'!$A:$A,0)),"-") | E23: ==IFERROR(INDEX('All Data'!$AL:$AL,MATCH($H$4&"",'All Data'!$A:$A,0)),"-") | G23: ==IFERROR(INDEX('All Data'!$AM:$AM,MATCH($H$4&"",'All Data'!$A:$A,0)),"-")
B24: =="Investment Likelihood: "&IFERROR(INDEX('All Data'!$AP:$AP,MATCH($H$4&"",'All Data'!$A:$A,0)),"—")
B25: Access to Opportunities (ATO) Composite Score /100 | F25: ==IFERROR(INDEX('All Data'!$AF:$AF,MATCH($H$4&"",'All Data'!$A:$A,0)),"-")
A29: =="02 — "&IFERROR(INDEX('All Data'!$C:$C,MATCH($H$29&"",'All Data'!$A:$A,0)),"")&" | GEOID "&$H$29&" | "&TEXT(IFERROR(INDEX('All Data'!$F:$F,MATCH($H$29&"",'All Data'!$A:$A,0)),0),"0")&" ac | "&IFERROR(INDEX('All Data'!$AP:$AP,MATCH($H$29&"",'All Data'!$A:$A,0)),"—") | H29: 49003960702
B30: TRACT PROFILE | D30: CENTERS & DISTRICTS | F30: HOUSING & DEMOGRAPHICS
B31: Population | C31: ==IFERROR(INDEX('All Data'!$D:$D,MATCH($H$29&"",'All Data'!$A:$A,0)),"-") | D31: WC MUorC % Total | E31: ==IFERROR(INDEX('All Data'!$J:$J,MATCH($H$29&"",'All Data'!$A:$A,0)),"-") | F31: Total Units | G31: ==IFERROR(INDEX('All Data'!$R:$R,MATCH($H$29&"",'All Data'!$A:$A,0)),"-")
B32: Households | C32: ==IFERROR(INDEX('All Data'!$E:$E,MATCH($H$29&"",'All Data'!$A:$A,0)),"-") | D32: Metropolitan Center | E32: ==IFERROR(INDEX('All Data'!$K:$K,MATCH($H$29&"",'All Data'!$A:$A,0)),"-") | F32: Residential Acres | G32: ==IFERROR(INDEX('All Data'!$S:$S,MATCH($H$29&"",'All Data'!$A:$A,0)),"-")
B33: Total Acres | C33: ==IFERROR(INDEX('All Data'!$F:$F,MATCH($H$29&"",'All Data'!$A:$A,0)),"-") | D33: Urban Center | E33: ==IFERROR(INDEX('All Data'!$L:$L,MATCH($H$29&"",'All Data'!$A:$A,0)),"-") | F33: SFD Acres | G33: ==IFERROR(INDEX('All Data'!$T:$T,MATCH($H$29&"",'All Data'!$A:$A,0)),"-")
B34: Developable Acres | C34: ==IFERROR(INDEX('All Data'!$G:$G,MATCH($H$29&"",'All Data'!$A:$A,0)),"-") | D34: City Center | E34: ==IFERROR(INDEX('All Data'!$M:$M,MATCH($H$29&"",'All Data'!$A:$A,0)),"-") | F34: MF / SFA Acres | G34: ==IFERROR(INDEX('All Data'!$U:$U,MATCH($H$29&"",'All Data'!$A:$A,0)),"-")
B35: OZ 1.0 Acres | C35: ==IFERROR(INDEX('All Data'!$H:$H,MATCH($H$29&"",'All Data'!$A:$A,0)),"-") | D35: Neighborhood Center | E35: ==IFERROR(INDEX('All Data'!$N:$N,MATCH($H$29&"",'All Data'!$A:$A,0)),"-") | F35: Poverty Rate | G35: ==IFERROR(INDEX('All Data'!$AL:$AL,MATCH($H$29&"",'All Data'!$A:$A,0)),"-")
B36: OZ 1.0 % of Tract | C36: ==IFERROR(INDEX('All Data'!$I:$I,MATCH($H$29&"",'All Data'!$A:$A,0)),"-") | D36: Employment District | E36: ==IFERROR(INDEX('All Data'!$O:$O,MATCH($H$29&"",'All Data'!$A:$A,0)),"-") | F36: Unemployment Rate | G36: ==IFERROR(INDEX('All Data'!$AM:$AM,MATCH($H$29&"",'All Data'!$A:$A,0)),"-")
D37: Industrial District | E37: ==IFERROR(INDEX('All Data'!$P:$P,MATCH($H$29&"",'All Data'!$A:$A,0)),"-") | F37: Median Family Income | G37: ==IFERROR(INDEX('All Data'!$AN:$AN,MATCH($H$29&"",'All Data'!$A:$A,0)),"-")
D38: Retail District | E38: ==IFERROR(INDEX('All Data'!$Q:$Q,MATCH($H$29&"",'All Data'!$A:$A,0)),"-")
B39: TRANSIT ACCESS | D39: AUTO ACCESS | F39: PROJECTED GROWTH 2027-37
B40: Rail / BRT Stops | C40: ==IFERROR(INDEX('All Data'!$V:$V,MATCH($H$29&"",'All Data'!$A:$A,0)),"-") | D40: Freeway Exits | E40: ==IFERROR(INDEX('All Data'!$AB:$AB,MATCH($H$29&"",'All Data'!$A:$A,0)),"-") | F40: Households Added | G40: ==IFERROR(INDEX('All Data'!$AG:$AG,MATCH($H$29&"",'All Data'!$A:$A,0)),"-")
B41: SAP Acres | C41: ==IFERROR(INDEX('All Data'!$W:$W,MATCH($H$29&"",'All Data'!$A:$A,0)),"-") | D41: Exit Distance (mi) | E41: ==IFERROR(INDEX('All Data'!$AC:$AC,MATCH($H$29&"",'All Data'!$A:$A,0)),"-") | F41: Population Added | G41: ==IFERROR(INDEX('All Data'!$AH:$AH,MATCH($H$29&"",'All Data'!$A:$A,0)),"-")
B42: SAP % of Tract | C42: ==IFERROR(INDEX('All Data'!$X:$X,MATCH($H$29&"",'All Data'!$A:$A,0)),"-") | D42: ATO Jobs (Auto) | E42: ==IFERROR(INDEX('All Data'!$AD:$AD,MATCH($H$29&"",'All Data'!$A:$A,0)),"-") | F42: Jobs Added | G42: ==IFERROR(INDEX('All Data'!$AI:$AI,MATCH($H$29&"",'All Data'!$A:$A,0)),"-")
B43: ATO Jobs (Transit) | C43: ==IFERROR(INDEX('All Data'!$Y:$Y,MATCH($H$29&"",'All Data'!$A:$A,0)),"-") | D43: ATO Households (Auto) | E43: ==IFERROR(INDEX('All Data'!$AE:$AE,MATCH($H$29&"",'All Data'!$A:$A,0)),"-") | F43: ERU Added | G43: ==IFERROR(INDEX('All Data'!$AJ:$AJ,MATCH($H$29&"",'All Data'!$A:$A,0)),"-")
B44: ATO Households (Transit) | C44: ==IFERROR(INDEX('All Data'!$Z:$Z,MATCH($H$29&"",'All Data'!$A:$A,0)),"-") | F44: ERU per Acre | G44: ==IFERROR(INDEX('All Data'!$AK:$AK,MATCH($H$29&"",'All Data'!$A:$A,0)),"-")
B45: SAP Planned HH/ac | C45: ==IFERROR(INDEX('All Data'!$AA:$AA,MATCH($H$29&"",'All Data'!$A:$A,0)),"-")
B47: INCOME | D47: POVERTY RATE | F47: UNEMPLOYMENT
C48: ==IFERROR(INDEX('All Data'!$AN:$AN,MATCH($H$29&"",'All Data'!$A:$A,0)),"-") | E48: ==IFERROR(INDEX('All Data'!$AL:$AL,MATCH($H$29&"",'All Data'!$A:$A,0)),"-") | G48: ==IFERROR(INDEX('All Data'!$AM:$AM,MATCH($H$29&"",'All Data'!$A:$A,0)),"-")
B49: =="Investment Likelihood: "&IFERROR(INDEX('All Data'!$AP:$AP,MATCH($H$29&"",'All Data'!$A:$A,0)),"—")
B50: Access to Opportunities (ATO) Composite Score /100 | F50: ==IFERROR(INDEX('All Data'!$AF:$AF,MATCH($H$29&"",'All Data'!$A:$A,0)),"-")

Sheet Weber County
A1: Weber County — OZ 2.0 Candidate Tracts — Detail
A2: WFRC & MAG Region | Generated June 01, 2026
A4: =="01 — "&IFERROR(INDEX('All Data'!$C:$C,MATCH($H$4&"",'All Data'!$A:$A,0)),"")&" | GEOID "&$H$4&" | "&TEXT(IFERROR(INDEX('All Data'!$F:$F,MATCH($H$4&"",'All Data'!$A:$A,0)),0),"0")&" ac | "&IFERROR(INDEX('All Data'!$AP:$AP,MATCH($H$4&"",'All Data'!$A:$A,0)),"—") | H4: 49057200202
B5: TRACT PROFILE | D5: CENTERS & DISTRICTS | F5: HOUSING & DEMOGRAPHICS
B6: Population | C6: ==IFERROR(INDEX('All Data'!$D:$D,MATCH($H$4&"",'All Data'!$A:$A,0)),"-") | D6: WC MUorC % Total | E6: ==IFERROR(INDEX('All Data'!$J:$J,MATCH($H$4&"",'All Data'!$A:$A,0)),"-") | F6: Total Units | G6: ==IFERROR(INDEX('All Data'!$R:$R,MATCH($H$4&"",'All Data'!$A:$A,0)),"-")
B7: Households | C7: ==IFERROR(INDEX('All Data'!$E:$E,MATCH($H$4&"",'All Data'!$A:$A,0)),"-") | D7: Metropolitan Center | E7: ==IFERROR(INDEX('All Data'!$K:$K,MATCH($H$4&"",'All Data'!$A:$A,0)),"-") | F7: Residential Acres | G7: ==IFERROR(INDEX('All Data'!$S:$S,MATCH($H$4&"",'All Data'!$A:$A,0)),"-")
B8: Total Acres | C8: ==IFERROR(INDEX('All Data'!$F:$F,MATCH($H$4&"",'All Data'!$A:$A,0)),"-") | D8: Urban Center | E8: ==IFERROR(INDEX('All Data'!$L:$L,MATCH($H$4&"",'All Data'!$A:$A,0)),"-") | F8: SFD Acres | G8: ==IFERROR(INDEX('All Data'!$T:$T,MATCH($H$4&"",'All Data'!$A:$A,0)),"-")
B9: Developable Acres | C9: ==IFERROR(INDEX('All Data'!$G:$G,MATCH($H$4&"",'All Data'!$A:$A,0)),"-") | D9: City Center | E9: ==IFERROR(INDEX('All Data'!$M:$M,MATCH($H$4&"",'All Data'!$A:$A,0)),"-") | F9: MF / SFA Acres | G9: ==IFERROR(INDEX('All Data'!$U:$U,MATCH($H$4&"",'All Data'!$A:$A,0)),"-")
B10: OZ 1.0 Acres | C10: ==IFERROR(INDEX('All Data'!$H:$H,MATCH($H$4&"",'All Data'!$A:$A,0)),"-") | D10: Neighborhood Center | E10: ==IFERROR(INDEX('All Data'!$N:$N,MATCH($H$4&"",'All Data'!$A:$A,0)),"-") | F10: Poverty Rate | G10: ==IFERROR(INDEX('All Data'!$AL:$AL,MATCH($H$4&"",'All Data'!$A:$A,0)),"-")
B11: OZ 1.0 % of Tract | C11: ==IFERROR(INDEX('All Data'!$I:$I,MATCH($H$4&"",'All Data'!$A:$A,0)),"-") | D11: Employment District | E11: ==IFERROR(INDEX('All Data'!$O:$O,MATCH($H$4&"",'All Data'!$A:$A,0)),"-") | F11: Unemployment Rate | G11: ==IFERROR(INDEX('All Data'!$AM:$AM,MATCH($H$4&"",'All Data'!$A:$A,0)),"-")
D12: Industrial District | E12: ==IFERROR(INDEX('All Data'!$P:$P,MATCH($H$4&"",'All Data'!$A:$A,0)),"-") | F12: Median Family Income | G12: ==IFERROR(INDEX('All Data'!$AN:$AN,MATCH($H$4&"",'All Data'!$A:$A,0)),"-")
D13: Retail District | E13: ==IFERROR(INDEX('All Data'!$Q:$Q,MATCH($H$4&"",'All Data'!$A:$A,0)),"-")
B14: TRANSIT ACCESS | D14: AUTO ACCESS | F14: PROJECTED GROWTH 2027-37
B15: Rail / BRT Stops | C15: ==IFERROR(INDEX('All Data'!$V:$V,MATCH($H$4&"",'All Data'!$A:$A,0)),"-") | D15: Freeway Exits | E15: ==IFERROR(INDEX('All Data'!$AB:$AB,MATCH($H$4&"",'All Data'!$A:$A,0)),"-") | F15: Households Added | G15: ==IFERROR(INDEX('All Data'!$AG:$AG,MATCH($H$4&"",'All Data'!$A:$A,0)),"-")
B16: SAP Acres | C16: ==IFERROR(INDEX('All Data'!$W:$W,MATCH($H$4&"",'All Data'!$A:$A,0)),"-") | D16: Exit Distance (mi) | E16: ==IFERROR(INDEX('All Data'!$AC:$AC,MATCH($H$4&"",'All Data'!$A:$A,0)),"-") | F16: Population Added | G16: ==IFERROR(INDEX('All Data'!$AH:$AH,MATCH($H$4&"",'All Data'!$A:$A,0)),"-")
B17: SAP % of Tract | C17: ==IFERROR(INDEX('All Data'!$X:$X,MATCH($H$4&"",'All Data'!$A:$A,0)),"-") | D17: ATO Jobs (Auto) | E17: ==IFERROR(INDEX('All Data'!$AD:$AD,MATCH($H$4&"",'All Data'!$A:$A,0)),"-") | F17: Jobs Added | G17: ==IFERROR(INDEX('All Data'!$AI:$AI,MATCH($H$4&"",'All Data'!$A:$A,0)),"-")
B18: ATO Jobs (Transit) | C18: ==IFERROR(INDEX('All Data'!$Y:$Y,MATCH($H$4&"",'All Data'!$A:$A,0)),"-") | D18: ATO Households (Auto) | E18: ==IFERROR(INDEX('All Data'!$AE:$AE,MATCH($H$4&"",'All Data'!$A:$A,0)),"-") | F18: ERU Added | G18: ==IFERROR(INDEX('All Data'!$AJ:$AJ,MATCH($H$4&"",'All Data'!$A:$A,0)),"-")
B19: ATO Households (Transit) | C19: ==IFERROR(INDEX('All Data'!$Z:$Z,MATCH($H$4&"",'All Data'!$A:$A,0)),"-") | F19: ERU per Acre | G19: ==IFERROR(INDEX('All Data'!$AK:$AK,MATCH($H$4&"",'All Data'!$A:$A,0)),"-")
B20: SAP Planned HH/ac | C20: ==IFERROR(INDEX('All Data'!$AA:$AA,MATCH($H$4&"",'All Data'!$A:$A,0)),"-")
B22: INCOME | D22: POVERTY RATE | F22: UNEMPLOYMENT
C23: ==IFERROR(INDEX('All Data'!$AN:$AN,MATCH($H$4&"",'All Data'!$A:$A,0)),"-") | E23: ==IFERROR(INDEX('All Data'!$AL:$AL,MATCH($H$4&"",'All Data'!$A:$A,0)),"-") | G23: ==IFERROR(INDEX('All Data'!$AM:$AM,MATCH($H$4&"",'All Data'!$A:$A,0)),"-")
B24: =="Investment Likelihood: "&IFERROR(INDEX('All Data'!$AP:$AP,MATCH($H$4&"",'All Data'!$A:$A,0)),"—")
B25: Access to Opportunities (ATO) Composite Score /100 | F25: ==IFERROR(INDEX('All Data'!$AF:$AF,MATCH($H$4&"",'All Data'!$A:$A,0)),"-")
A29: =="02 — "&IFERROR(INDEX('All Data'!$C:$C,MATCH($H$29&"",'All Data'!$A:$A,0)),"")&" | GEOID "&$H$29&" | "&TEXT(IFERROR(INDEX('All Data'!$F:$F,MATCH($H$29&"",'All Data'!$A:$A,0)),0),"0")&" ac | "&IFERROR(INDEX('All Data'!$AP:$AP,MATCH($H$29&"",'All Data'!$A:$A,0)),"—") | H29: 49057200302
B30: TRACT PROFILE | D30: CENTERS & DISTRICTS | F30: HOUSING & DEMOGRAPHICS
B31: Population | C31: ==IFERROR(INDEX('All Data'!$D:$D,MATCH($H$29&"",'All Data'!$A:$A,0)),"-") | D31: WC MUorC % Total | E31: ==IFERROR(INDEX('All Data'!$J:$J,MATCH($H$29&"",'All Data'!$A:$A,0)),"-") | F31: Total Units | G31: ==IFERROR(INDEX('All Data'!$R:$R,MATCH($H$29&"",'All Data'!$A:$A,0)),"-")
B32: Households | C32: ==IFERROR(INDEX('All Data'!$E:$E,MATCH($H$29&"",'All Data'!$A:$A,0)),"-") | D32: Metropolitan Center | E32: ==IFERROR(INDEX('All Data'!$K:$K,MATCH($H$29&"",'All Data'!$A:$A,0)),"-") | F32: Residential Acres | G32: ==IFERROR(INDEX('All Data'!$S:$S,MATCH($H$29&"",'All Data'!$A:$A,0)),"-")
B33: Total Acres | C33: ==IFERROR(INDEX('All Data'!$F:$F,MATCH($H$29&"",'All Data'!$A:$A,0)),"-") | D33: Urban Center | E33: ==IFERROR(INDEX('All Data'!$L:$L,MATCH($H$29&"",'All Data'!$A:$A,0)),"-") | F33: SFD Acres | G33: ==IFERROR(INDEX('All Data'!$T:$T,MATCH($H$29&"",'All Data'!$A:$A,0)),"-")
B34: Developable Acres | C34: ==IFERROR(INDEX('All Data'!$G:$G,MATCH($H$29&"",'All Data'!$A:$A,0)),"-") | D34: City Center | E34: ==IFERROR(INDEX('All Data'!$M:$M,MATCH($H$29&"",'All Data'!$A:$A,0)),"-") | F34: MF / SFA Acres | G34: ==IFERROR(INDEX('All Data'!$U:$U,MATCH($H$29&"",'All Data'!$A:$A,0)),"-")
B35: OZ 1.0 Acres | C35: ==IFERROR(INDEX('All Data'!$H:$H,MATCH($H$29&"",'All Data'!$A:$A,0)),"-") | D35: Neighborhood Center | E35: ==IFERROR(INDEX('All Data'!$N:$N,MATCH($H$29&"",'All Data'!$A:$A,0)),"-") | F35: Poverty Rate | G35: ==IFERROR(INDEX('All Data'!$AL:$AL,MATCH($H$29&"",'All Data'!$A:$A,0)),"-")
B36: OZ 1.0 % of Tract | C36: ==IFERROR(INDEX('All Data'!$I:$I,MATCH($H$29&"",'All Data'!$A:$A,0)),"-") | D36: Employment District | E36: ==IFERROR(INDEX('All Data'!$O:$O,MATCH($H$29&"",'All Data'!$A:$A,0)),"-") | F36: Unemployment Rate | G36: ==IFERROR(INDEX('All Data'!$AM:$AM,MATCH($H$29&"",'All Data'!$A:$A,0)),"-")
D37: Industrial District | E37: ==IFERROR(INDEX('All Data'!$P:$P,MATCH($H$29&"",'All Data'!$A:$A,0)),"-") | F37: Median Family Income | G37: ==IFERROR(INDEX('All Data'!$AN:$AN,MATCH($H$29&"",'All Data'!$A:$A,0)),"-")
D38: Retail District | E38: ==IFERROR(INDEX('All Data'!$Q:$Q,MATCH($H$29&"",'All Data'!$A:$A,0)),"-")
B39: TRANSIT ACCESS | D39: AUTO ACCESS | F39: PROJECTED GROWTH 2027-37
B40: Rail / BRT Stops | C40: ==IFERROR(INDEX('All Data'!$V:$V,MATCH($H$29&"",'All Data'!$A:$A,0)),"-") | D40: Freeway Exits | E40: ==IFERROR(INDEX('All Data'!$AB:$AB,MATCH($H$29&"",'All Data'!$A:$A,0)),"-") | F40: Households Added | G40: ==IFERROR(INDEX('All Data'!$AG:$AG,MATCH($H$29&"",'All Data'!$A:$A,0)),"-")
B41: SAP Acres | C41: ==IFERROR(INDEX('All Data'!$W:$W,MATCH($H$29&"",'All Data'!$A:$A,0)),"-") | D41: Exit Distance (mi) | E41: ==IFERROR(INDEX('All Data'!$AC:$AC,MATCH($H$29&"",'All Data'!$A:$A,0)),"-") | F41: Population Added | G41: ==IFERROR(INDEX('All Data'!$AH:$AH,MATCH($H$29&"",'All Data'!$A:$A,0)),"-")
B42: SAP % of Tract | C42: ==IFERROR(INDEX('All Data'!$X:$X,MATCH($H$29&"",'All Data'!$A:$A,0)),"-") | D42: ATO Jobs (Auto) | E42: ==IFERROR(INDEX('All Data'!$AD:$AD,MATCH($H$29&"",'All Data'!$A:$A,0)),"-") | F42: Jobs Added | G42: ==IFERROR(INDEX('All Data'!$AI:$AI,MATCH($H$29&"",'All Data'!$A:$A,0)),"-")
B43: ATO Jobs (Transit) | C43: ==IFERROR(INDEX('All Data'!$Y:$Y,MATCH($H$29&"",'All Data'!$A:$A,0)),"-") | D43: ATO Households (Auto) | E43: ==IFERROR(INDEX('All Data'!$AE:$AE,MATCH($H$29&"",'All Data'!$A:$A,0)),"-") | F43: ERU Added | G43: ==IFERROR(INDEX('All Data'!$AJ:$AJ,MATCH($H$29&"",'All Data'!$A:$A,0)),"-")
B44: ATO Households (Transit) | C44: ==IFERROR(INDEX('All Data'!$Z:$Z,MATCH($H$29&"",'All Data'!$A:$A,0)),"-") | F44: ERU per Acre | G44: ==IFERROR(INDEX('All Data'!$AK:$AK,MATCH($H$29&"",'All Data'!$A:$A,0)),"-")
B45: SAP Planned HH/ac | C45: ==IFERROR(INDEX('All Data'!$AA:$AA,MATCH($H$29&"",'All Data'!$A:$A,0)),"-")
B47: INCOME | D47: POVERTY RATE | F47: UNEMPLOYMENT
C48: ==IFERROR(INDEX('All Data'!$AN:$AN,MATCH($H$29&"",'All Data'!$A:$A,0)),"-") | E48: ==IFERROR(INDEX('All Data'!$AL:$AL,MATCH($H$29&"",'All Data'!$A:$A,0)),"-") | G48: ==IFERROR(INDEX('All Data'!$AM:$AM,MATCH($H$29&"",'All Data'!$A:$A,0)),"-")
B49: =="Investment Likelihood: "&IFERROR(INDEX('All Data'!$AP:$AP,MATCH($H$29&"",'All Data'!$A:$A,0)),"—")
B50: Access to Opportunities (ATO) Composite Score /100 | F50: ==IFERROR(INDEX('All Data'!$AF:$AF,MATCH($H$29&"",'All Data'!$A:$A,0)),"-")
A54: =="03 — "&IFERROR(INDEX('All Data'!$C:$C,MATCH($H$54&"",'All Data'!$A:$A,0)),"")&" | GEOID "&$H$54&" | "&TEXT(IFERROR(INDEX('All Data'!$F:$F,MATCH($H$54&"",'All Data'!$A:$A,0)),0),"0")&" ac | "&IFERROR(INDEX('All Data'!$AP:$AP,MATCH($H$54&"",'All Data'!$A:$A,0)),"—") | H54: 49057200400
B55: TRACT PROFILE | D55: CENTERS & DISTRICTS | F55: HOUSING & DEMOGRAPHICS
B56: Population | C56: ==IFERROR(INDEX('All Data'!$D:$D,MATCH($H$54&"",'All Data'!$A:$A,0)),"-") | D56: WC MUorC % Total | E56: ==IFERROR(INDEX('All Data'!$J:$J,MATCH($H$54&"",'All Data'!$A:$A,0)),"-") | F56: Total Units | G56: ==IFERROR(INDEX('All Data'!$R:$R,MATCH($H$54&"",'All Data'!$A:$A,0)),"-")
B57: Households | C57: ==IFERROR(INDEX('All Data'!$E:$E,MATCH($H$54&"",'All Data'!$A:$A,0)),"-") | D57: Metropolitan Center | E57: ==IFERROR(INDEX('All Data'!$K:$K,MATCH($H$54&"",'All Data'!$A:$A,0)),"-") | F57: Residential Acres | G57: ==IFERROR(INDEX('All Data'!$S:$S,MATCH($H$54&"",'All Data'!$A:$A,0)),"-")
B58: Total Acres | C58: ==IFERROR(INDEX('All Data'!$F:$F,MATCH($H$54&"",'All Data'!$A:$A,0)),"-") | D58: Urban Center | E58: ==IFERROR(INDEX('All Data'!$L:$L,MATCH($H$54&"",'All Data'!$A:$A,0)),"-") | F58: SFD Acres | G58: ==IFERROR(INDEX('All Data'!$T:$T,MATCH($H$54&"",'All Data'!$A:$A,0)),"-")
B59: Developable Acres | C59: ==IFERROR(INDEX('All Data'!$G:$G,MATCH($H$54&"",'All Data'!$A:$A,0)),"-") | D59: City Center | E59: ==IFERROR(INDEX('All Data'!$M:$M,MATCH($H$54&"",'All Data'!$A:$A,0)),"-") | F59: MF / SFA Acres | G59: ==IFERROR(INDEX('All Data'!$U:$U,MATCH($H$54&"",'All Data'!$A:$A,0)),"-")
B60: OZ 1.0 Acres | C60: ==IFERROR(INDEX('All Data'!$H:$H,MATCH($H$54&"",'All Data'!$A:$A,0)),"-") | D60: Neighborhood Center | E60: ==IFERROR(INDEX('All Data'!$N:$N,MATCH($H$54&"",'All Data'!$A:$A,0)),"-") | F60: Poverty Rate | G60: ==IFERROR(INDEX('All Data'!$AL:$AL,MATCH($H$54&"",'All Data'!$A:$A,0)),"-")
B61: OZ 1.0 % of Tract | C61: ==IFERROR(INDEX('All Data'!$I:$I,MATCH($H$54&"",'All Data'!$A:$A,0)),"-") | D61: Employment District | E61: ==IFERROR(INDEX('All Data'!$O:$O,MATCH($H$54&"",'All Data'!$A:$A,0)),"-") | F61: Unemployment Rate | G61: ==IFERROR(INDEX('All Data'!$AM:$AM,MATCH($H$54&"",'All Data'!$A:$A,0)),"-")
D62: Industrial District | E62: ==IFERROR(INDEX('All Data'!$P:$P,MATCH($H$54&"",'All Data'!$A:$A,0)),"-") | F62: Median Family Income | G62: ==IFERROR(INDEX('All Data'!$AN:$AN,MATCH($H$54&"",'All Data'!$A:$A,0)),"-")
D63: Retail District | E63: ==IFERROR(INDEX('All Data'!$Q:$Q,MATCH($H$54&"",'All Data'!$A:$A,0)),"-")
B64: TRANSIT ACCESS | D64: AUTO ACCESS | F64: PROJECTED GROWTH 2027-37
B65: Rail / BRT Stops | C65: ==IFERROR(INDEX('All Data'!$V:$V,MATCH($H$54&"",'All Data'!$A:$A,0)),"-") | D65: Freeway Exits | E65: ==IFERROR(INDEX('All Data'!$AB:$AB,MATCH($H$54&"",'All Data'!$A:$A,0)),"-") | F65: Households Added | G65: ==IFERROR(INDEX('All Data'!$AG:$AG,MATCH($H$54&"",'All Data'!$A:$A,0)),"-")
B66: SAP Acres | C66: ==IFERROR(INDEX('All Data'!$W:$W,MATCH($H$54&"",'All Data'!$A:$A,0)),"-") | D66: Exit Distance (mi) | E66: ==IFERROR(INDEX('All Data'!$AC:$AC,MATCH($H$54&"",'All Data'!$A:$A,0)),"-") | F66: Population Added | G66: ==IFERROR(INDEX('All Data'!$AH:$AH,MATCH($H$54&"",'All Data'!$A:$A,0)),"-")
B67: SAP % of Tract | C67: ==IFERROR(INDEX('All Data'!$X:$X,MATCH($H$54&"",'All Data'!$A:$A,0)),"-") | D67: ATO Jobs (Auto) | E67: ==IFERROR(INDEX('All Data'!$AD:$AD,MATCH($H$54&"",'All Data'!$A:$A,0)),"-") | F67: Jobs Added | G67: ==IFERROR(INDEX('All Data'!$AI:$AI,MATCH($H$54&"",'All Data'!$A:$A,0)),"-")
B68: ATO Jobs (Transit) | C68: ==IFERROR(INDEX('All Data'!$Y:$Y,MATCH($H$54&"",'All Data'!$A:$A,0)),"-") | D68: ATO Households (Auto) | E68: ==IFERROR(INDEX('All Data'!$AE:$AE,MATCH($H$54&"",'All Data'!$A:$A,0)),"-") | F68: ERU Added | G68: ==IFERROR(INDEX('All Data'!$AJ:$AJ,MATCH($H$54&"",'All Data'!$A:$A,0)),"-")
B69: ATO Households (Transit) | C69: ==IFERROR(INDEX('All Data'!$Z:$Z,MATCH($H$54&"",'All Data'!$A:$A,0)),"-") | F69: ERU per Acre | G69: ==IFERROR(INDEX('All Data'!$AK:$AK,MATCH($H$54&"",'All Data'!$A:$A,0)),"-")
B70: SAP Planned HH/ac | C70: ==IFERROR(INDEX('All Data'!$AA:$AA,MATCH($H$54&"",'All Data'!$A:$A,0)),"-")
B72: INCOME | D72: POVERTY RATE | F72: UNEMPLOYMENT
C73: ==IFERROR(INDEX('All Data'!$AN:$AN,MATCH($H$54&"",'All Data'!$A:$A,0)),"-") | E73: ==IFERROR(INDEX('All Data'!$AL:$AL,MATCH($H$54&"",'All Data'!$A:$A,0)),"-") | G73: ==IFERROR(INDEX('All Data'!$AM:$AM,MATCH($H$54&"",'All Data'!$A:$A,0)),"-")
B74: =="Investment Likelihood: "&IFERROR(INDEX('All Data'!$AP:$AP,MATCH($H$54&"",'All Data'!$A:$A,0)),"—")
B75: Access to Opportunities (ATO) Composite Score /100 | F75: ==IFERROR(INDEX('All Data'!$AF:$AF,MATCH($H$54&"",'All Data'!$A:$A,0)),"-")
A79: =="04 — "&IFERROR(INDEX('All Data'!$C:$C,MATCH($H$79&"",'All Data'!$A:$A,0)),"")&" | GEOID "&$H$79&" | "&TEXT(IFERROR(INDEX('All Data'!$F:$F,MATCH($H$79&"",'All Data'!$A:$A,0)),0),"0")&" ac | "&IFERROR(INDEX('All Data'!$AP:$AP,MATCH($H$79&"",'All Data'!$A:$A,0)),"—") | H79: 49057200500
B80: TRACT PROFILE | D80: CENTERS & DISTRICTS | F80: HOUSING & DEMOGRAPHICS
B81: Population | C81: ==IFERROR(INDEX('All Data'!$D:$D,MATCH($H$79&"",'All Data'!$A:$A,0)),"-") | D81: WC MUorC % Total | E81: ==IFERROR(INDEX('All Data'!$J:$J,MATCH($H$79&"",'All Data'!$A:$A,0)),"-") | F81: Total Units | G81: ==IFERROR(INDEX('All Data'!$R:$R,MATCH($H$79&"",'All Data'!$A:$A,0)),"-")
B82: Households | C82: ==IFERROR(INDEX('All Data'!$E:$E,MATCH($H$79&"",'All Data'!$A:$A,0)),"-") | D82: Metropolitan Center | E82: ==IFERROR(INDEX('All Data'!$K:$K,MATCH($H$79&"",'All Data'!$A:$A,0)),"-") | F82: Residential Acres | G82: ==IFERROR(INDEX('All Data'!$S:$S,MATCH($H$79&"",'All Data'!$A:$A,0)),"-")
B83: Total Acres | C83: ==IFERROR(INDEX('All Data'!$F:$F,MATCH($H$79&"",'All Data'!$A:$A,0)),"-") | D83: Urban Center | E83: ==IFERROR(INDEX('All Data'!$L:$L,MATCH($H$79&"",'All Data'!$A:$A,0)),"-") | F83: SFD Acres | G83: ==IFERROR(INDEX('All Data'!$T:$T,MATCH($H$79&"",'All Data'!$A:$A,0)),"-")
B84: Developable Acres | C84: ==IFERROR(INDEX('All Data'!$G:$G,MATCH($H$79&"",'All Data'!$A:$A,0)),"-") | D84: City Center | E84: ==IFERROR(INDEX('All Data'!$M:$M,MATCH($H$79&"",'All Data'!$A:$A,0)),"-") | F84: MF / SFA Acres | G84: ==IFERROR(INDEX('All Data'!$U:$U,MATCH($H$79&"",'All Data'!$A:$A,0)),"-")
B85: OZ 1.0 Acres | C85: ==IFERROR(INDEX('All Data'!$H:$H,MATCH($H$79&"",'All Data'!$A:$A,0)),"-") | D85: Neighborhood Center | E85: ==IFERROR(INDEX('All Data'!$N:$N,MATCH($H$79&"",'All Data'!$A:$A,0)),"-") | F85: Poverty Rate | G85: ==IFERROR(INDEX('All Data'!$AL:$AL,MATCH($H$79&"",'All Data'!$A:$A,0)),"-")
B86: OZ 1.0 % of Tract | C86: ==IFERROR(INDEX('All Data'!$I:$I,MATCH($H$79&"",'All Data'!$A:$A,0)),"-") | D86: Employment District | E86: ==IFERROR(INDEX('All Data'!$O:$O,MATCH($H$79&"",'All Data'!$A:$A,0)),"-") | F86: Unemployment Rate | G86: ==IFERROR(INDEX('All Data'!$AM:$AM,MATCH($H$79&"",'All Data'!$A:$A,0)),"-")
D87: Industrial District | E87: ==IFERROR(INDEX('All Data'!$P:$P,MATCH($H$79&"",'All Data'!$A:$A,0)),"-") | F87: Median Family Income | G87: ==IFERROR(INDEX('All Data'!$AN:$AN,MATCH($H$79&"",'All Data'!$A:$A,0)),"-")
D88: Retail District | E88: ==IFERROR(INDEX('All Data'!$Q:$Q,MATCH($H$79&"",'All Data'!$A:$A,0)),"-")
B89: TRANSIT ACCESS | D89: AUTO ACCESS | F89: PROJECTED GROWTH 2027-37
B90: Rail / BRT Stops | C90: ==IFERROR(INDEX('All Data'!$V:$V,MATCH($H$79&"",'All Data'!$A:$A,0)),"-") | D90: Freeway Exits | E90: ==IFERROR(INDEX('All Data'!$AB:$AB,MATCH($H$79&"",'All Data'!$A:$A,0)),"-") | F90: Households Added | G90: ==IFERROR(INDEX('All Data'!$AG:$AG,MATCH($H$79&"",'All Data'!$A:$A,0)),"-")
B91: SAP Acres | C91: ==IFERROR(INDEX('All Data'!$W:$W,MATCH($H$79&"",'All Data'!$A:$A,0)),"-") | D91: Exit Distance (mi) | E91: ==IFERROR(INDEX('All Data'!$AC:$AC,MATCH($H$79&"",'All Data'!$A:$A,0)),"-") | F91: Population Added | G91: ==IFERROR(INDEX('All Data'!$AH:$AH,MATCH($H$79&"",'All Data'!$A:$A,0)),"-")
B92: SAP % of Tract | C92: ==IFERROR(INDEX('All Data'!$X:$X,MATCH($H$79&"",'All Data'!$A:$A,0)),"-") | D92: ATO Jobs (Auto) | E92: ==IFERROR(INDEX('All Data'!$AD:$AD,MATCH($H$79&"",'All Data'!$A:$A,0)),"-") | F92: Jobs Added | G92: ==IFERROR(INDEX('All Data'!$AI:$AI,MATCH($H$79&"",'All Data'!$A:$A,0)),"-")
B93: ATO Jobs (Transit) | C93: ==IFERROR(INDEX('All Data'!$Y:$Y,MATCH($H$79&"",'All Data'!$A:$A,0)),"-") | D93: ATO Households (Auto) | E93: ==IFERROR(INDEX('All Data'!$AE:$AE,MATCH($H$79&"",'All Data'!$A:$A,0)),"-") | F93: ERU Added | G93: ==IFERROR(INDEX('All Data'!$AJ:$AJ,MATCH($H$79&"",'All Data'!$A:$A,0)),"-")
B94: ATO Households (Transit) | C94: ==IFERROR(INDEX('All Data'!$Z:$Z,MATCH($H$79&"",'All Data'!$A:$A,0)),"-") | F94: ERU per Acre | G94: ==IFERROR(INDEX('All Data'!$AK:$AK,MATCH($H$79&"",'All Data'!$A:$A,0)),"-")
B95: SAP Planned HH/ac | C95: ==IFERROR(INDEX('All Data'!$AA:$AA,MATCH($H$79&"",'All Data'!$A:$A,0)),"-")
B97: INCOME | D97: POVERTY RATE | F97: UNEMPLOYMENT
C98: ==IFERROR(INDEX('All Data'!$AN:$AN,MATCH($H$79&"",'All Data'!$A:$A,0)),"-") | E98: ==IFERROR(INDEX('All Data'!$AL:$AL,MATCH($H$79&"",'All Data'!$A:$A,0)),"-") | G98: ==IFERROR(INDEX('All Data'!$AM:$AM,MATCH($H$79&"",'All Data'!$A:$A,0)),"-")
B99: =="Investment Likelihood: "&IFERROR(INDEX('All Data'!$AP:$AP,MATCH($H$79&"",'All Data'!$A:$A,0)),"—")
B100: Access to Opportunities (ATO) Composite Score /100 | F100: ==IFERROR(INDEX('All Data'!$AF:$AF,MATCH($H$79&"",'All Data'!$A:$A,0)),"-")
A104: =="05 — "&IFERROR(INDEX('All Data'!$C:$C,MATCH($H$104&"",'All Data'!$A:$A,0)),"")&" | GEOID "&$H$104&" | "&TEXT(IFERROR(INDEX('All Data'!$F:$F,MATCH($H$104&"",'All Data'!$A:$A,0)),0),"0")&" ac | "&IFERROR(INDEX('All Data'!$AP:$AP,MATCH($H$104&"",'All Data'!$A:$A,0)),"—") | H104: 49057200800
B105: TRACT PROFILE | D105: CENTERS & DISTRICTS | F105: HOUSING & DEMOGRAPHICS
B106: Population | C106: ==IFERROR(INDEX('All Data'!$D:$D,MATCH($H$104&"",'All Data'!$A:$A,0)),"-") | D106: WC MUorC % Total | E106: ==IFERROR(INDEX('All Data'!$J:$J,MATCH($H$104&"",'All Data'!$A:$A,0)),"-") | F106: Total Units | G106: ==IFERROR(INDEX('All Data'!$R:$R,MATCH($H$104&"",'All Data'!$A:$A,0)),"-")
B107: Households | C107: ==IFERROR(INDEX('All Data'!$E:$E,MATCH($H$104&"",'All Data'!$A:$A,0)),"-") | D107: Metropolitan Center | E107: ==IFERROR(INDEX('All Data'!$K:$K,MATCH($H$104&"",'All Data'!$A:$A,0)),"-") | F107: Residential Acres | G107: ==IFERROR(INDEX('All Data'!$S:$S,MATCH($H$104&"",'All Data'!$A:$A,0)),"-")
B108: Total Acres | C108: ==IFERROR(INDEX('All Data'!$F:$F,MATCH($H$104&"",'All Data'!$A:$A,0)),"-") | D108: Urban Center | E108: ==IFERROR(INDEX('All Data'!$L:$L,MATCH($H$104&"",'All Data'!$A:$A,0)),"-") | F108: SFD Acres | G108: ==IFERROR(INDEX('All Data'!$T:$T,MATCH($H$104&"",'All Data'!$A:$A,0)),"-")
B109: Developable Acres | C109: ==IFERROR(INDEX('All Data'!$G:$G,MATCH($H$104&"",'All Data'!$A:$A,0)),"-") | D109: City Center | E109: ==IFERROR(INDEX('All Data'!$M:$M,MATCH($H$104&"",'All Data'!$A:$A,0)),"-") | F109: MF / SFA Acres | G109: ==IFERROR(INDEX('All Data'!$U:$U,MATCH($H$104&"",'All Data'!$A:$A,0)),"-")
B110: OZ 1.0 Acres | C110: ==IFERROR(INDEX('All Data'!$H:$H,MATCH($H$104&"",'All Data'!$A:$A,0)),"-") | D110: Neighborhood Center | E110: ==IFERROR(INDEX('All Data'!$N:$N,MATCH($H$104&"",'All Data'!$A:$A,0)),"-") | F110: Poverty Rate | G110: ==IFERROR(INDEX('All Data'!$AL:$AL,MATCH($H$104&"",'All Data'!$A:$A,0)),"-")
B111: OZ 1.0 % of Tract | C111: ==IFERROR(INDEX('All Data'!$I:$I,MATCH($H$104&"",'All Data'!$A:$A,0)),"-") | D111: Employment District | E111: ==IFERROR(INDEX('All Data'!$O:$O,MATCH($H$104&"",'All Data'!$A:$A,0)),"-") | F111: Unemployment Rate | G111: ==IFERROR(INDEX('All Data'!$AM:$AM,MATCH($H$104&"",'All Data'!$A:$A,0)),"-")
D112: Industrial District | E112: ==IFERROR(INDEX('All Data'!$P:$P,MATCH($H$104&"",'All Data'!$A:$A,0)),"-") | F112: Median Family Income | G112: ==IFERROR(INDEX('All Data'!$AN:$AN,MATCH($H$104&"",'All Data'!$A:$A,0)),"-")
D113: Retail District | E113: ==IFERROR(INDEX('All Data'!$Q:$Q,MATCH($H$104&"",'All Data'!$A:$A,0)),"-")
B114: TRANSIT ACCESS | D114: AUTO ACCESS | F114: PROJECTED GROWTH 2027-37
B115: Rail / BRT Stops | C115: ==IFERROR(INDEX('All Data'!$V:$V,MATCH($H$104&"",'All Data'!$A:$A,0)),"-") | D115: Freeway Exits | E115: ==IFERROR(INDEX('All Data'!$AB:$AB,MATCH($H$104&"",'All Data'!$A:$A,0)),"-") | F115: Households Added | G115: ==IFERROR(INDEX('All Data'!$AG:$AG,MATCH($H$104&"",'All Data'!$A:$A,0)),"-")
B116: SAP Acres | C116: ==IFERROR(INDEX('All Data'!$W:$W,MATCH($H$104&"",'All Data'!$A:$A,0)),"-") | D116: Exit Distance (mi) | E116: ==IFERROR(INDEX('All Data'!$AC:$AC,MATCH($H$104&"",'All Data'!$A:$A,0)),"-") | F116: Population Added | G116: ==IFERROR(INDEX('All Data'!$AH:$AH,MATCH($H$104&"",'All Data'!$A:$A,0)),"-")
B117: SAP % of Tract | C117: ==IFERROR(INDEX('All Data'!$X:$X,MATCH($H$104&"",'All Data'!$A:$A,0)),"-") | D117: ATO Jobs (Auto) | E117: ==IFERROR(INDEX('All Data'!$AD:$AD,MATCH($H$104&"",'All Data'!$A:$A,0)),"-") | F117: Jobs Added | G117: ==IFERROR(INDEX('All Data'!$AI:$AI,MATCH($H$104&"",'All Data'!$A:$A,0)),"-")
...

Sheet Davis County
A1: Davis County — OZ 2.0 Candidate Tracts — Detail
A2: WFRC & MAG Region | Generated June 01, 2026
A4: =="01 — "&IFERROR(INDEX('All Data'!$C:$C,MATCH($H$4&"",'All Data'!$A:$A,0)),"")&" | GEOID "&$H$4&" | "&TEXT(IFERROR(INDEX('All Data'!$F:$F,MATCH($H$4&"",'All Data'!$A:$A,0)),0),"0")&" ac | "&IFERROR(INDEX('All Data'!$AP:$AP,MATCH($H$4&"",'All Data'!$A:$A,0)),"—") | H4: 49011125201
B5: TRACT PROFILE | D5: CENTERS & DISTRICTS | F5: HOUSING & DEMOGRAPHICS
B6: Population | C6: ==IFERROR(INDEX('All Data'!$D:$D,MATCH($H$4&"",'All Data'!$A:$A,0)),"-") | D6: WC MUorC % Total | E6: ==IFERROR(INDEX('All Data'!$J:$J,MATCH($H$4&"",'All Data'!$A:$A,0)),"-") | F6: Total Units | G6: ==IFERROR(INDEX('All Data'!$R:$R,MATCH($H$4&"",'All Data'!$A:$A,0)),"-")
B7: Households | C7: ==IFERROR(INDEX('All Data'!$E:$E,MATCH($H$4&"",'All Data'!$A:$A,0)),"-") | D7: Metropolitan Center | E7: ==IFERROR(INDEX('All Data'!$K:$K,MATCH($H$4&"",'All Data'!$A:$A,0)),"-") | F7: Residential Acres | G7: ==IFERROR(INDEX('All Data'!$S:$S,MATCH($H$4&"",'All Data'!$A:$A,0)),"-")
B8: Total Acres | C8: ==IFERROR(INDEX('All Data'!$F:$F,MATCH($H$4&"",'All Data'!$A:$A,0)),"-") | D8: Urban Center | E8: ==IFERROR(INDEX('All Data'!$L:$L,MATCH($H$4&"",'All Data'!$A:$A,0)),"-") | F8: SFD Acres | G8: ==IFERROR(INDEX('All Data'!$T:$T,MATCH($H$4&"",'All Data'!$A:$A,0)),"-")
B9: Developable Acres | C9: ==IFERROR(INDEX('All Data'!$G:$G,MATCH($H$4&"",'All Data'!$A:$A,0)),"-") | D9: City Center | E9: ==IFERROR(INDEX('All Data'!$M:$M,MATCH($H$4&"",'All Data'!$A:$A,0)),"-") | F9: MF / SFA Acres | G9: ==IFERROR(INDEX('All Data'!$U:$U,MATCH($H$4&"",'All Data'!$A:$A,0)),"-")
B10: OZ 1.0 Acres | C10: ==IFERROR(INDEX('All Data'!$H:$H,MATCH($H$4&"",'All Data'!$A:$A,0)),"-") | D10: Neighborhood Center | E10: ==IFERROR(INDEX('All Data'!$N:$N,MATCH($H$4&"",'All Data'!$A:$A,0)),"-") | F10: Poverty Rate | G10: ==IFERROR(INDEX('All Data'!$AL:$AL,MATCH($H$4&"",'All Data'!$A:$A,0)),"-")
B11: OZ 1.0 % of Tract | C11: ==IFERROR(INDEX('All Data'!$I:$I,MATCH($H$4&"",'All Data'!$A:$A,0)),"-") | D11: Employment District | E11: ==IFERROR(INDEX('All Data'!$O:$O,MATCH($H$4&"",'All Data'!$A:$A,0)),"-") | F11: Unemployment Rate | G11: ==IFERROR(INDEX('All Data'!$AM:$AM,MATCH($H$4&"",'All Data'!$A:$A,0)),"-")
D12: Industrial District | E12: ==IFERROR(INDEX('All Data'!$P:$P,MATCH($H$4&"",'All Data'!$A:$A,0)),"-") | F12: Median Family Income | G12: ==IFERROR(INDEX('All Data'!$AN:$AN,MATCH($H$4&"",'All Data'!$A:$A,0)),"-")
D13: Retail District | E13: ==IFERROR(INDEX('All Data'!$Q:$Q,MATCH($H$4&"",'All Data'!$A:$A,0)),"-")
B14: TRANSIT ACCESS | D14: AUTO ACCESS | F14: PROJECTED GROWTH 2027-37
B15: Rail / BRT Stops | C15: ==IFERROR(INDEX('All Data'!$V:$V,MATCH($H$4&"",'All Data'!$A:$A,0)),"-") | D15: Freeway Exits | E15: ==IFERROR(INDEX('All Data'!$AB:$AB,MATCH($H$4&"",'All Data'!$A:$A,0)),"-") | F15: Households Added | G15: ==IFERROR(INDEX('All Data'!$AG:$AG,MATCH($H$4&"",'All Data'!$A:$A,0)),"-")
B16: SAP Acres | C16: ==IFERROR(INDEX('All Data'!$W:$W,MATCH($H$4&"",'All Data'!$A:$A,0)),"-") | D16: Exit Distance (mi) | E16: ==IFERROR(INDEX('All Data'!$AC:$AC,MATCH($H$4&"",'All Data'!$A:$A,0)),"-") | F16: Population Added | G16: ==IFERROR(INDEX('All Data'!$AH:$AH,MATCH($H$4&"",'All Data'!$A:$A,0)),"-")
B17: SAP % of Tract | C17: ==IFERROR(INDEX('All Data'!$X:$X,MATCH($H$4&"",'All Data'!$A:$A,0)),"-") | D17: ATO Jobs (Auto) | E17: ==IFERROR(INDEX('All Data'!$AD:$AD,MATCH($H$4&"",'All Data'!$A:$A,0)),"-") | F17: Jobs Added | G17: ==IFERROR(INDEX('All Data'!$AI:$AI,MATCH($H$4&"",'All Data'!$A:$A,0)),"-")
B18: ATO Jobs (Transit) | C18: ==IFERROR(INDEX('All Data'!$Y:$Y,MATCH($H$4&"",'All Data'!$A:$A,0)),"-") | D18: ATO Households (Auto) | E18: ==IFERROR(INDEX('All Data'!$AE:$AE,MATCH($H$4&"",'All Data'!$A:$A,0)),"-") | F18: ERU Added | G18: ==IFERROR(INDEX('All Data'!$AJ:$AJ,MATCH($H$4&"",'All Data'!$A:$A,0)),"-")
B19: ATO Households (Transit) | C19: ==IFERROR(INDEX('All Data'!$Z:$Z,MATCH($H$4&"",'All Data'!$A:$A,0)),"-") | F19: ERU per Acre | G19: ==IFERROR(INDEX('All Data'!$AK:$AK,MATCH($H$4&"",'All Data'!$A:$A,0)),"-")
B20: SAP Planned HH/ac | C20: ==IFERROR(INDEX('All Data'!$AA:$AA,MATCH($H$4&"",'All Data'!$A:$A,0)),"-")
B22: INCOME | D22: POVERTY RATE | F22: UNEMPLOYMENT
C23: ==IFERROR(INDEX('All Data'!$AN:$AN,MATCH($H$4&"",'All Data'!$A:$A,0)),"-") | E23: ==IFERROR(INDEX('All Data'!$AL:$AL,MATCH($H$4&"",'All Data'!$A:$A,0)),"-") | G23: ==IFERROR(INDEX('All Data'!$AM:$AM,MATCH($H$4&"",'All Data'!$A:$A,0)),"-")
B24: =="Investment Likelihood: "&IFERROR(INDEX('All Data'!$AP:$AP,MATCH($H$4&"",'All Data'!$A:$A,0)),"—")
B25: Access to Opportunities (ATO) Composite Score /100 | F25: ==IFERROR(INDEX('All Data'!$AF:$AF,MATCH($H$4&"",'All Data'!$A:$A,0)),"-")
A29: =="02 — "&IFERROR(INDEX('All Data'!$C:$C,MATCH($H$29&"",'All Data'!$A:$A,0)),"")&" | GEOID "&$H$29&" | "&TEXT(IFERROR(INDEX('All Data'!$F:$F,MATCH($H$29&"",'All Data'!$A:$A,0)),0),"0")&" ac | "&IFERROR(INDEX('All Data'!$AP:$AP,MATCH($H$29&"",'All Data'!$A:$A,0)),"—") | H29: 49011125301
B30: TRACT PROFILE | D30: CENTERS & DISTRICTS | F30: HOUSING & DEMOGRAPHICS
B31: Population | C31: ==IFERROR(INDEX('All Data'!$D:$D,MATCH($H$29&"",'All Data'!$A:$A,0)),"-") | D31: WC MUorC % Total | E31: ==IFERROR(INDEX('All Data'!$J:$J,MATCH($H$29&"",'All Data'!$A:$A,0)),"-") | F31: Total Units | G31: ==IFERROR(INDEX('All Data'!$R:$R,MATCH($H$29&"",'All Data'!$A:$A,0)),"-")
B32: Households | C32: ==IFERROR(INDEX('All Data'!$E:$E,MATCH($H$29&"",'All Data'!$A:$A,0)),"-") | D32: Metropolitan Center | E32: ==IFERROR(INDEX('All Data'!$K:$K,MATCH($H$29&"",'All Data'!$A:$A,0)),"-") | F32: Residential Acres | G32: ==IFERROR(INDEX('All Data'!$S:$S,MATCH($H$29&"",'All Data'!$A:$A,0)),"-")
B33: Total Acres | C33: ==IFERROR(INDEX('All Data'!$F:$F,MATCH($H$29&"",'All Data'!$A:$A,0)),"-") | D33: Urban Center | E33: ==IFERROR(INDEX('All Data'!$L:$L,MATCH($H$29&"",'All Data'!$A:$A,0)),"-") | F33: SFD Acres | G33: ==IFERROR(INDEX('All Data'!$T:$T,MATCH($H$29&"",'All Data'!$A:$A,0)),"-")
B34: Developable Acres | C34: ==IFERROR(INDEX('All Data'!$G:$G,MATCH($H$29&"",'All Data'!$A:$A,0)),"-") | D34: City Center | E34: ==IFERROR(INDEX('All Data'!$M:$M,MATCH($H$29&"",'All Data'!$A:$A,0)),"-") | F34: MF / SFA Acres | G34: ==IFERROR(INDEX('All Data'!$U:$U,MATCH($H$29&"",'All Data'!$A:$A,0)),"-")
B35: OZ 1.0 Acres | C35: ==IFERROR(INDEX('All Data'!$H:$H,MATCH($H$29&"",'All Data'!$A:$A,0)),"-") | D35: Neighborhood Center | E35: ==IFERROR(INDEX('All Data'!$N:$N,MATCH($H$29&"",'All Data'!$A:$A,0)),"-") | F35: Poverty Rate | G35: ==IFERROR(INDEX('All Data'!$AL:$AL,MATCH($H$29&"",'All Data'!$A:$A,0)),"-")
B36: OZ 1.0 % of Tract | C36: ==IFERROR(INDEX('All Data'!$I:$I,MATCH($H$29&"",'All Data'!$A:$A,0)),"-") | D36: Employment District | E36: ==IFERROR(INDEX('All Data'!$O:$O,MATCH($H$29&"",'All Data'!$A:$A,0)),"-") | F36: Unemployment Rate | G36: ==IFERROR(INDEX('All Data'!$AM:$AM,MATCH($H$29&"",'All Data'!$A:$A,0)),"-")
D37: Industrial District | E37: ==IFERROR(INDEX('All Data'!$P:$P,MATCH($H$29&"",'All Data'!$A:$A,0)),"-") | F37: Median Family Income | G37: ==IFERROR(INDEX('All Data'!$AN:$AN,MATCH($H$29&"",'All Data'!$A:$A,0)),"-")
D38: Retail District | E38: ==IFERROR(INDEX('All Data'!$Q:$Q,MATCH($H$29&"",'All Data'!$A:$A,0)),"-")
B39: TRANSIT ACCESS | D39: AUTO ACCESS | F39: PROJECTED GROWTH 2027-37
B40: Rail / BRT Stops | C40: ==IFERROR(INDEX('All Data'!$V:$V,MATCH($H$29&"",'All Data'!$A:$A,0)),"-") | D40: Freeway Exits | E40: ==IFERROR(INDEX('All Data'!$AB:$AB,MATCH($H$29&"",'All Data'!$A:$A,0)),"-") | F40: Households Added | G40: ==IFERROR(INDEX('All Data'!$AG:$AG,MATCH($H$29&"",'All Data'!$A:$A,0)),"-")
B41: SAP Acres | C41: ==IFERROR(INDEX('All Data'!$W:$W,MATCH($H$29&"",'All Data'!$A:$A,0)),"-") | D41: Exit Distance (mi) | E41: ==IFERROR(INDEX('All Data'!$AC:$AC,MATCH($H$29&"",'All Data'!$A:$A,0)),"-") | F41: Population Added | G41: ==IFERROR(INDEX('All Data'!$AH:$AH,MATCH($H$29&"",'All Data'!$A:$A,0)),"-")
B42: SAP % of Tract | C42: ==IFERROR(INDEX('All Data'!$X:$X,MATCH($H$29&"",'All Data'!$A:$A,0)),"-") | D42: ATO Jobs (Auto) | E42: ==IFERROR(INDEX('All Data'!$AD:$AD,MATCH($H$29&"",'All Data'!$A:$A,0)),"-") | F42: Jobs Added | G42: ==IFERROR(INDEX('All Data'!$AI:$AI,MATCH($H$29&"",'All Data'!$A:$A,0)),"-")
B43: ATO Jobs (Transit) | C43: ==IFERROR(INDEX('All Data'!$Y:$Y,MATCH($H$29&"",'All Data'!$A:$A,0)),"-") | D43: ATO Households (Auto) | E43: ==IFERROR(INDEX('All Data'!$AE:$AE,MATCH($H$29&"",'All Data'!$A:$A,0)),"-") | F43: ERU Added | G43: ==IFERROR(INDEX('All Data'!$AJ:$AJ,MATCH($H$29&"",'All Data'!$A:$A,0)),"-")
B44: ATO Households (Transit) | C44: ==IFERROR(INDEX('All Data'!$Z:$Z,MATCH($H$29&"",'All Data'!$A:$A,0)),"-") | F44: ERU per Acre | G44: ==IFERROR(INDEX('All Data'!$AK:$AK,MATCH($H$29&"",'All Data'!$A:$A,0)),"-")
B45: SAP Planned HH/ac | C45: ==IFERROR(INDEX('All Data'!$AA:$AA,MATCH($H$29&"",'All Data'!$A:$A,0)),"-")
B47: INCOME | D47: POVERTY RATE | F47: UNEMPLOYMENT
C48: ==IFERROR(INDEX('All Data'!$AN:$AN,MATCH($H$29&"",'All Data'!$A:$A,0)),"-") | E48: ==IFERROR(INDEX('All Data'!$AL:$AL,MATCH($H$29&"",'All Data'!$A:$A,0)),"-") | G48: ==IFERROR(INDEX('All Data'!$AM:$AM,MATCH($H$29&"",'All Data'!$A:$A,0)),"-")
B49: =="Investment Likelihood: "&IFERROR(INDEX('All Data'!$AP:$AP,MATCH($H$29&"",'All Data'!$A:$A,0)),"—")
B50: Access to Opportunities (ATO) Composite Score /100 | F50: ==IFERROR(INDEX('All Data'!$AF:$AF,MATCH($H$29&"",'All Data'!$A:$A,0)),"-")
A54: =="03 — "&IFERROR(INDEX('All Data'!$C:$C,MATCH($H$54&"",'All Data'!$A:$A,0)),"")&" | GEOID "&$H$54&" | "&TEXT(IFERROR(INDEX('All Data'!$F:$F,MATCH($H$54&"",'All Data'!$A:$A,0)),0),"0")&" ac | "&IFERROR(INDEX('All Data'!$AP:$AP,MATCH($H$54&"",'All Data'!$A:$A,0)),"—") | H54: 49011125600
B55: TRACT PROFILE | D55: CENTERS & DISTRICTS | F55: HOUSING & DEMOGRAPHICS
B56: Population | C56: ==IFERROR(INDEX('All Data'!$D:$D,MATCH($H$54&"",'All Data'!$A:$A,0)),"-") | D56: WC MUorC % Total | E56: ==IFERROR(INDEX('All Data'!$J:$J,MATCH($H$54&"",'All Data'!$A:$A,0)),"-") | F56: Total Units | G56: ==IFERROR(INDEX('All Data'!$R:$R,MATCH($H$54&"",'All Data'!$A:$A,0)),"-")
B57: Households | C57: ==IFERROR(INDEX('All Data'!$E:$E,MATCH($H$54&"",'All Data'!$A:$A,0)),"-") | D57: Metropolitan Center | E57: ==IFERROR(INDEX('All Data'!$K:$K,MATCH($H$54&"",'All Data'!$A:$A,0)),"-") | F57: Residential Acres | G57: ==IFERROR(INDEX('All Data'!$S:$S,MATCH($H$54&"",'All Data'!$A:$A,0)),"-")
B58: Total Acres | C58: ==IFERROR(INDEX('All Data'!$F:$F,MATCH($H$54&"",'All Data'!$A:$A,0)),"-") | D58: Urban Center | E58: ==IFERROR(INDEX('All Data'!$L:$L,MATCH($H$54&"",'All Data'!$A:$A,0)),"-") | F58: SFD Acres | G58: ==IFERROR(INDEX('All Data'!$T:$T,MATCH($H$54&"",'All Data'!$A:$A,0)),"-")
B59: Developable Acres | C59: ==IFERROR(INDEX('All Data'!$G:$G,MATCH($H$54&"",'All Data'!$A:$A,0)),"-") | D59: City Center | E59: ==IFERROR(INDEX('All Data'!$M:$M,MATCH($H$54&"",'All Data'!$A:$A,0)),"-") | F59: MF / SFA Acres | G59: ==IFERROR(INDEX('All Data'!$U:$U,MATCH($H$54&"",'All Data'!$A:$A,0)),"-")
B60: OZ 1.0 Acres | C60: ==IFERROR(INDEX('All Data'!$H:$H,MATCH($H$54&"",'All Data'!$A:$A,0)),"-") | D60: Neighborhood Center | E60: ==IFERROR(INDEX('All Data'!$N:$N,MATCH($H$54&"",'All Data'!$A:$A,0)),"-") | F60: Poverty Rate | G60: ==IFERROR(INDEX('All Data'!$AL:$AL,MATCH($H$54&"",'All Data'!$A:$A,0)),"-")
B61: OZ 1.0 % of Tract | C61: ==IFERROR(INDEX('All Data'!$I:$I,MATCH($H$54&"",'All Data'!$A:$A,0)),"-") | D61: Employment District | E61: ==IFERROR(INDEX('All Data'!$O:$O,MATCH($H$54&"",'All Data'!$A:$A,0)),"-") | F61: Unemployment Rate | G61: ==IFERROR(INDEX('All Data'!$AM:$AM,MATCH($H$54&"",'All Data'!$A:$A,0)),"-")
D62: Industrial District | E62: ==IFERROR(INDEX('All Data'!$P:$P,MATCH($H$54&"",'All Data'!$A:$A,0)),"-") | F62: Median Family Income | G62: ==IFERROR(INDEX('All Data'!$AN:$AN,MATCH($H$54&"",'All Data'!$A:$A,0)),"-")
D63: Retail District | E63: ==IFERROR(INDEX('All Data'!$Q:$Q,MATCH($H$54&"",'All Data'!$A:$A,0)),"-")
B64: TRANSIT ACCESS | D64: AUTO ACCESS | F64: PROJECTED GROWTH 2027-37
B65: Rail / BRT Stops | C65: ==IFERROR(INDEX('All Data'!$V:$V,MATCH($H$54&"",'All Data'!$A:$A,0)),"-") | D65: Freeway Exits | E65: ==IFERROR(INDEX('All Data'!$AB:$AB,MATCH($H$54&"",'All Data'!$A:$A,0)),"-") | F65: Households Added | G65: ==IFERROR(INDEX('All Data'!$AG:$AG,MATCH($H$54&"",'All Data'!$A:$A,0)),"-")
B66: SAP Acres | C66: ==IFERROR(INDEX('All Data'!$W:$W,MATCH($H$54&"",'All Data'!$A:$A,0)),"-") | D66: Exit Distance (mi) | E66: ==IFERROR(INDEX('All Data'!$AC:$AC,MATCH($H$54&"",'All Data'!$A:$A,0)),"-") | F66: Population Added | G66: ==IFERROR(INDEX('All Data'!$AH:$AH,MATCH($H$54&"",'All Data'!$A:$A,0)),"-")
B67: SAP % of Tract | C67: ==IFERROR(INDEX('All Data'!$X:$X,MATCH($H$54&"",'All Data'!$A:$A,0)),"-") | D67: ATO Jobs (Auto) | E67: ==IFERROR(INDEX('All Data'!$AD:$AD,MATCH($H$54&"",'All Data'!$A:$A,0)),"-") | F67: Jobs Added | G67: ==IFERROR(INDEX('All Data'!$AI:$AI,MATCH($H$54&"",'All Data'!$A:$A,0)),"-")
B68: ATO Jobs (Transit) | C68: ==IFERROR(INDEX('All Data'!$Y:$Y,MATCH($H$54&"",'All Data'!$A:$A,0)),"-") | D68: ATO Households (Auto) | E68: ==IFERROR(INDEX('All Data'!$AE:$AE,MATCH($H$54&"",'All Data'!$A:$A,0)),"-") | F68: ERU Added | G68: ==IFERROR(INDEX('All Data'!$AJ:$AJ,MATCH($H$54&"",'All Data'!$A:$A,0)),"-")
B69: ATO Households (Transit) | C69: ==IFERROR(INDEX('All Data'!$Z:$Z,MATCH($H$54&"",'All Data'!$A:$A,0)),"-") | F69: ERU per Acre | G69: ==IFERROR(INDEX('All Data'!$AK:$AK,MATCH($H$54&"",'All Data'!$A:$A,0)),"-")
B70: SAP Planned HH/ac | C70: ==IFERROR(INDEX('All Data'!$AA:$AA,MATCH($H$54&"",'All Data'!$A:$A,0)),"-")
B72: INCOME | D72: POVERTY RATE | F72: UNEMPLOYMENT
C73: ==IFERROR(INDEX('All Data'!$AN:$AN,MATCH($H$54&"",'All Data'!$A:$A,0)),"-") | E73: ==IFERROR(INDEX('All Data'!$AL:$AL,MATCH($H$54&"",'All Data'!$A:$A,0)),"-") | G73: ==IFERROR(INDEX('All Data'!$AM:$AM,MATCH($H$54&"",'All Data'!$A:$A,0)),"-")
B74: =="Investment Likelihood: "&IFERROR(INDEX('All Data'!$AP:$AP,MATCH($H$54&"",'All Data'!$A:$A,0)),"—")
B75: Access to Opportunities (ATO) Composite Score /100 | F75: ==IFERROR(INDEX('All Data'!$AF:$AF,MATCH($H$54&"",'All Data'!$A:$A,0)),"-")
A79: =="04 — "&IFERROR(INDEX('All Data'!$C:$C,MATCH($H$79&"",'All Data'!$A:$A,0)),"")&" | GEOID "&$H$79&" | "&TEXT(IFERROR(INDEX('All Data'!$F:$F,MATCH($H$79&"",'All Data'!$A:$A,0)),0),"0")&" ac | "&IFERROR(INDEX('All Data'!$AP:$AP,MATCH($H$79&"",'All Data'!$A:$A,0)),"—") | H79: 49011125701
B80: TRACT PROFILE | D80: CENTERS & DISTRICTS | F80: HOUSING & DEMOGRAPHICS
B81: Population | C81: ==IFERROR(INDEX('All Data'!$D:$D,MATCH($H$79&"",'All Data'!$A:$A,0)),"-") | D81: WC MUorC % Total | E81: ==IFERROR(INDEX('All Data'!$J:$J,MATCH($H$79&"",'All Data'!$A:$A,0)),"-") | F81: Total Units | G81: ==IFERROR(INDEX('All Data'!$R:$R,MATCH($H$79&"",'All Data'!$A:$A,0)),"-")
B82: Households | C82: ==IFERROR(INDEX('All Data'!$E:$E,MATCH($H$79&"",'All Data'!$A:$A,0)),"-") | D82: Metropolitan Center | E82: ==IFERROR(INDEX('All Data'!$K:$K,MATCH($H$79&"",'All Data'!$A:$A,0)),"-") | F82: Residential Acres | G82: ==IFERROR(INDEX('All Data'!$S:$S,MATCH($H$79&"",'All Data'!$A:$A,0)),"-")
B83: Total Acres | C83: ==IFERROR(INDEX('All Data'!$F:$F,MATCH($H$79&"",'All Data'!$A:$A,0)),"-") | D83: Urban Center | E83: ==IFERROR(INDEX('All Data'!$L:$L,MATCH($H$79&"",'All Data'!$A:$A,0)),"-") | F83: SFD Acres | G83: ==IFERROR(INDEX('All Data'!$T:$T,MATCH($H$79&"",'All Data'!$A:$A,0)),"-")
B84: Developable Acres | C84: ==IFERROR(INDEX('All Data'!$G:$G,MATCH($H$79&"",'All Data'!$A:$A,0)),"-") | D84: City Center | E84: ==IFERROR(INDEX('All Data'!$M:$M,MATCH($H$79&"",'All Data'!$A:$A,0)),"-") | F84: MF / SFA Acres | G84: ==IFERROR(INDEX('All Data'!$U:$U,MATCH($H$79&"",'All Data'!$A:$A,0)),"-")
B85: OZ 1.0 Acres | C85: ==IFERROR(INDEX('All Data'!$H:$H,MATCH($H$79&"",'All Data'!$A:$A,0)),"-") | D85: Neighborhood Center | E85: ==IFERROR(INDEX('All Data'!$N:$N,MATCH($H$79&"",'All Data'!$A:$A,0)),"-") | F85: Poverty Rate | G85: ==IFERROR(INDEX('All Data'!$AL:$AL,MATCH($H$79&"",'All Data'!$A:$A,0)),"-")
B86: OZ 1.0 % of Tract | C86: ==IFERROR(INDEX('All Data'!$I:$I,MATCH($H$79&"",'All Data'!$A:$A,0)),"-") | D86: Employment District | E86: ==IFERROR(INDEX('All Data'!$O:$O,MATCH($H$79&"",'All Data'!$A:$A,0)),"-") | F86: Unemployment Rate | G86: ==IFERROR(INDEX('All Data'!$AM:$AM,MATCH($H$79&"",'All Data'!$A:$A,0)),"-")
D87: Industrial District | E87: ==IFERROR(INDEX('All Data'!$P:$P,MATCH($H$79&"",'All Data'!$A:$A,0)),"-") | F87: Median Family Income | G87: ==IFERROR(INDEX('All Data'!$AN:$AN,MATCH($H$79&"",'All Data'!$A:$A,0)),"-")
D88: Retail District | E88: ==IFERROR(INDEX('All Data'!$Q:$Q,MATCH($H$79&"",'All Data'!$A:$A,0)),"-")
B89: TRANSIT ACCESS | D89: AUTO ACCESS | F89: PROJECTED GROWTH 2027-37
B90: Rail / BRT Stops | C90: ==IFERROR(INDEX('All Data'!$V:$V,MATCH($H$79&"",'All Data'!$A:$A,0)),"-") | D90: Freeway Exits | E90: ==IFERROR(INDEX('All Data'!$AB:$AB,MATCH($H$79&"",'All Data'!$A:$A,0)),"-") | F90: Households Added | G90: ==IFERROR(INDEX('All Data'!$AG:$AG,MATCH($H$79&"",'All Data'!$A:$A,0)),"-")
B91: SAP Acres | C91: ==IFERROR(INDEX('All Data'!$W:$W,MATCH($H$79&"",'All Data'!$A:$A,0)),"-") | D91: Exit Distance (mi) | E91: ==IFERROR(INDEX('All Data'!$AC:$AC,MATCH($H$79&"",'All Data'!$A:$A,0)),"-") | F91: Population Added | G91: ==IFERROR(INDEX('All Data'!$AH:$AH,MATCH($H$79&"",'All Data'!$A:$A,0)),"-")
B92: SAP % of Tract | C92: ==IFERROR(INDEX('All Data'!$X:$X,MATCH($H$79&"",'All Data'!$A:$A,0)),"-") | D92: ATO Jobs (Auto) | E92: ==IFERROR(INDEX('All Data'!$AD:$AD,MATCH($H$79&"",'All Data'!$A:$A,0)),"-") | F92: Jobs Added | G92: ==IFERROR(INDEX('All Data'!$AI:$AI,MATCH($H$79&"",'All Data'!$A:$A,0)),"-")
B93: ATO Jobs (Transit) | C93: ==IFERROR(INDEX('All Data'!$Y:$Y,MATCH($H$79&"",'All Data'!$A:$A,0)),"-") | D93: ATO Households (Auto) | E93: ==IFERROR(INDEX('All Data'!$AE:$AE,MATCH($H$79&"",'All Data'!$A:$A,0)),"-") | F93: ERU Added | G93: ==IFERROR(INDEX('All Data'!$AJ:$AJ,MATCH($H$79&"",'All Data'!$A:$A,0)),"-")
B94: ATO Households (Transit) | C94: ==IFERROR(INDEX('All Data'!$Z:$Z,MATCH($H$79&"",'All Data'!$A:$A,0)),"-") | F94: ERU per Acre | G94: ==IFERROR(INDEX('All Data'!$AK:$AK,MATCH($H$79&"",'All Data'!$A:$A,0)),"-")
B95: SAP Planned HH/ac | C95: ==IFERROR(INDEX('All Data'!$AA:$AA,MATCH($H$79&"",'All Data'!$A:$A,0)),"-")
B97: INCOME | D97: POVERTY RATE | F97: UNEMPLOYMENT
C98: ==IFERROR(INDEX('All Data'!$AN:$AN,MATCH($H$79&"",'All Data'!$A:$A,0)),"-") | E98: ==IFERROR(INDEX('All Data'!$AL:$AL,MATCH($H$79&"",'All Data'!$A:$A,0)),"-") | G98: ==IFERROR(INDEX('All Data'!$AM:$AM,MATCH($H$79&"",'All Data'!$A:$A,0)),"-")
B99: =="Investment Likelihood: "&IFERROR(INDEX('All Data'!$AP:$AP,MATCH($H$79&"",'All Data'!$A:$A,0)),"—")
B100: Access to Opportunities (ATO) Composite Score /100 | F100: ==IFERROR(INDEX('All Data'!$AF:$AF,MATCH($H$79&"",'All Data'!$A:$A,0)),"-")
A104: =="05 — "&IFERROR(INDEX('All Data'!$C:$C,MATCH($H$104&"",'All Data'!$A:$A,0)),"")&" | GEOID "&$H$104&" | "&TEXT(IFERROR(INDEX('All Data'!$F:$F,MATCH($H$104&"",'All Data'!$A:$A,0)),0),"0")&" ac | "&IFERROR(INDEX('All Data'!$AP:$AP,MATCH($H$104&"",'All Data'!$A:$A,0)),"—") | H104: 49011125702
B105: TRACT PROFILE | D105: CENTERS & DISTRICTS | F105: HOUSING & DEMOGRAPHICS
B106: Population | C106: ==IFERROR(INDEX('All Data'!$D:$D,MATCH($H$104&"",'All Data'!$A:$A,0)),"-") | D106: WC MUorC % Total | E106: ==IFERROR(INDEX('All Data'!$J:$J,MATCH($H$104&"",'All Data'!$A:$A,0)),"-") | F106: Total Units | G106: ==IFERROR(INDEX('All Data'!$R:$R,MATCH($H$104&"",'All Data'!$A:$A,0)),"-")
B107: Households | C107: ==IFERROR(INDEX('All Data'!$E:$E,MATCH($H$104&"",'All Data'!$A:$A,0)),"-") | D107: Metropolitan Center | E107: ==IFERROR(INDEX('All Data'!$K:$K,MATCH($H$104&"",'All Data'!$A:$A,0)),"-") | F107: Residential Acres | G107: ==IFERROR(INDEX('All Data'!$S:$S,MATCH($H$104&"",'All Data'!$A:$A,0)),"-")
B108: Total Acres | C108: ==IFERROR(INDEX('All Data'!$F:$F,MATCH($H$104&"",'All Data'!$A:$A,0)),"-") | D108: Urban Center | E108: ==IFERROR(INDEX('All Data'!$L:$L,MATCH($H$104&"",'All Data'!$A:$A,0)),"-") | F108: SFD Acres | G108: ==IFERROR(INDEX('All Data'!$T:$T,MATCH($H$104&"",'All Data'!$A:$A,0)),"-")
B109: Developable Acres | C109: ==IFERROR(INDEX('All Data'!$G:$G,MATCH($H$104&"",'All Data'!$A:$A,0)),"-") | D109: City Center | E109: ==IFERROR(INDEX('All Data'!$M:$M,MATCH($H$104&"",'All Data'!$A:$A,0)),"-") | F109: MF / SFA Acres | G109: ==IFERROR(INDEX('All Data'!$U:$U,MATCH($H$104&"",'All Data'!$A:$A,0)),"-")
B110: OZ 1.0 Acres | C110: ==IFERROR(INDEX('All Data'!$H:$H,MATCH($H$104&"",'All Data'!$A:$A,0)),"-") | D110: Neighborhood Center | E110: ==IFERROR(INDEX('All Data'!$N:$N,MATCH($H$104&"",'All Data'!$A:$A,0)),"-") | F110: Poverty Rate | G110: ==IFERROR(INDEX('All Data'!$AL:$AL,MATCH($H$104&"",'All Data'!$A:$A,0)),"-")
B111: OZ 1.0 % of Tract | C111: ==IFERROR(INDEX('All Data'!$I:$I,MATCH($H$104&"",'All Data'!$A:$A,0)),"-") | D111: Employment District | E111: ==IFERROR(INDEX('All Data'!$O:$O,MATCH($H$104&"",'All Data'!$A:$A,0)),"-") | F111: Unemployment Rate | G111: ==IFERROR(INDEX('All Data'!$AM:$AM,MATCH($H$104&"",'All Data'!$A:$A,0)),"-")
D112: Industrial District | E112: ==IFERROR(INDEX('All Data'!$P:$P,MATCH($H$104&"",'All Data'!$A:$A,0)),"-") | F112: Median Family Income | G112: ==IFERROR(INDEX('All Data'!$AN:$AN,MATCH($H$104&"",'All Data'!$A:$A,0)),"-")
D113: Retail District | E113: ==IFERROR(INDEX('All Data'!$Q:$Q,MATCH($H$104&"",'All Data'!$A:$A,0)),"-")
B114: TRANSIT ACCESS | D114: AUTO ACCESS | F114: PROJECTED GROWTH 2027-37
B115: Rail / BRT Stops | C115: ==IFERROR(INDEX('All Data'!$V:$V,MATCH($H$104&"",'All Data'!$A:$A,0)),"-") | D115: Freeway Exits | E115: ==IFERROR(INDEX('All Data'!$AB:$AB,MATCH($H$104&"",'All Data'!$A:$A,0)),"-") | F115: Households Added | G115: ==IFERROR(INDEX('All Data'!$AG:$AG,MATCH($H$104&"",'All Data'!$A:$A,0)),"-")
B116: SAP Acres | C116: ==IFERROR(INDEX('All Data'!$W:$W,MATCH($H$104&"",'All Data'!$A:$A,0)),"-") | D116: Exit Distance (mi) | E116: ==IFERROR(INDEX('All Data'!$AC:$AC,MATCH($H$104&"",'All Data'!$A:$A,0)),"-") | F116: Population Added | G116: ==IFERROR(INDEX('All Data'!$AH:$AH,MATCH($H$104&"",'All Data'!$A:$A,0)),"-")
B117: SAP % of Tract | C117: ==IFERROR(INDEX('All Data'!$X:$X,MATCH($H$104&"",'All Data'!$A:$A,0)),"-") | D117: ATO Jobs (Auto) | E117: ==IFERROR(INDEX('All Data'!$AD:$AD,MATCH($H$104&"",'All Data'!$A:$A,0)),"-") | F117: Jobs Added | G117: ==IFERROR(INDEX('All Data'!$AI:$AI,MATCH($H$104&"",'All Data'!$A:$A,0)),"-")
...

Sheet Salt Lake County
A1: Salt Lake County — OZ 2.0 Candidate Tracts — Detail
A2: WFRC & MAG Region | Generated June 01, 2026
A4: =="01 — "&IFERROR(INDEX('All Data'!$C:$C,MATCH($H$4&"",'All Data'!$A:$A,0)),"")&" | GEOID "&$H$4&" | "&TEXT(IFERROR(INDEX('All Data'!$F:$F,MATCH($H$4&"",'All Data'!$A:$A,0)),0),"0")&" ac | "&IFERROR(INDEX('All Data'!$AP:$AP,MATCH($H$4&"",'All Data'!$A:$A,0)),"—") | H4: 49035100306
B5: TRACT PROFILE | D5: CENTERS & DISTRICTS | F5: HOUSING & DEMOGRAPHICS
B6: Population | C6: ==IFERROR(INDEX('All Data'!$D:$D,MATCH($H$4&"",'All Data'!$A:$A,0)),"-") | D6: WC MUorC % Total | E6: ==IFERROR(INDEX('All Data'!$J:$J,MATCH($H$4&"",'All Data'!$A:$A,0)),"-") | F6: Total Units | G6: ==IFERROR(INDEX('All Data'!$R:$R,MATCH($H$4&"",'All Data'!$A:$A,0)),"-")
B7: Households | C7: ==IFERROR(INDEX('All Data'!$E:$E,MATCH($H$4&"",'All Data'!$A:$A,0)),"-") | D7: Metropolitan Center | E7: ==IFERROR(INDEX('All Data'!$K:$K,MATCH($H$4&"",'All Data'!$A:$A,0)),"-") | F7: Residential Acres | G7: ==IFERROR(INDEX('All Data'!$S:$S,MATCH($H$4&"",'All Data'!$A:$A,0)),"-")
B8: Total Acres | C8: ==IFERROR(INDEX('All Data'!$F:$F,MATCH($H$4&"",'All Data'!$A:$A,0)),"-") | D8: Urban Center | E8: ==IFERROR(INDEX('All Data'!$L:$L,MATCH($H$4&"",'All Data'!$A:$A,0)),"-") | F8: SFD Acres | G8: ==IFERROR(INDEX('All Data'!$T:$T,MATCH($H$4&"",'All Data'!$A:$A,0)),"-")
B9: Developable Acres | C9: ==IFERROR(INDEX('All Data'!$G:$G,MATCH($H$4&"",'All Data'!$A:$A,0)),"-") | D9: City Center | E9: ==IFERROR(INDEX('All Data'!$M:$M,MATCH($H$4&"",'All Data'!$A:$A,0)),"-") | F9: MF / SFA Acres | G9: ==IFERROR(INDEX('All Data'!$U:$U,MATCH($H$4&"",'All Data'!$A:$A,0)),"-")
B10: OZ 1.0 Acres | C10: ==IFERROR(INDEX('All Data'!$H:$H,MATCH($H$4&"",'All Data'!$A:$A,0)),"-") | D10: Neighborhood Center | E10: ==IFERROR(INDEX('All Data'!$N:$N,MATCH($H$4&"",'All Data'!$A:$A,0)),"-") | F10: Poverty Rate | G10: ==IFERROR(INDEX('All Data'!$AL:$AL,MATCH($H$4&"",'All Data'!$A:$A,0)),"-")
B11: OZ 1.0 % of Tract | C11: ==IFERROR(INDEX('All Data'!$I:$I,MATCH($H$4&"",'All Data'!$A:$A,0)),"-") | D11: Employment District | E11: ==IFERROR(INDEX('All Data'!$O:$O,MATCH($H$4&"",'All Data'!$A:$A,0)),"-") | F11: Unemployment Rate | G11: ==IFERROR(INDEX('All Data'!$AM:$AM,MATCH($H$4&"",'All Data'!$A:$A,0)),"-")
D12: Industrial District | E12: ==IFERROR(INDEX('All Data'!$P:$P,MATCH($H$4&"",'All Data'!$A:$A,0)),"-") | F12: Median Family Income | G12: ==IFERROR(INDEX('All Data'!$AN:$AN,MATCH($H$4&"",'All Data'!$A:$A,0)),"-")
D13: Retail District | E13: ==IFERROR(INDEX('All Data'!$Q:$Q,MATCH($H$4&"",'All Data'!$A:$A,0)),"-")
B14: TRANSIT ACCESS | D14: AUTO ACCESS | F14: PROJECTED GROWTH 2027-37
B15: Rail / BRT Stops | C15: ==IFERROR(INDEX('All Data'!$V:$V,MATCH($H$4&"",'All Data'!$A:$A,0)),"-") | D15: Freeway Exits | E15: ==IFERROR(INDEX('All Data'!$AB:$AB,MATCH($H$4&"",'All Data'!$A:$A,0)),"-") | F15: Households Added | G15: ==IFERROR(INDEX('All Data'!$AG:$AG,MATCH($H$4&"",'All Data'!$A:$A,0)),"-")
B16: SAP Acres | C16: ==IFERROR(INDEX('All Data'!$W:$W,MATCH($H$4&"",'All Data'!$A:$A,0)),"-") | D16: Exit Distance (mi) | E16: ==IFERROR(INDEX('All Data'!$AC:$AC,MATCH($H$4&"",'All Data'!$A:$A,0)),"-") | F16: Population Added | G16: ==IFERROR(INDEX('All Data'!$AH:$AH,MATCH($H$4&"",'All Data'!$A:$A,0)),"-")
B17: SAP % of Tract | C17: ==IFERROR(INDEX('All Data'!$X:$X,MATCH($H$4&"",'All Data'!$A:$A,0)),"-") | D17: ATO Jobs (Auto) | E17: ==IFERROR(INDEX('All Data'!$AD:$AD,MATCH($H$4&"",'All Data'!$A:$A,0)),"-") | F17: Jobs Added | G17: ==IFERROR(INDEX('All Data'!$AI:$AI,MATCH($H$4&"",'All Data'!$A:$A,0)),"-")
B18: ATO Jobs (Transit) | C18: ==IFERROR(INDEX('All Data'!$Y:$Y,MATCH($H$4&"",'All Data'!$A:$A,0)),"-") | D18: ATO Households (Auto) | E18: ==IFERROR(INDEX('All Data'!$AE:$AE,MATCH($H$4&"",'All Data'!$A:$A,0)),"-") | F18: ERU Added | G18: ==IFERROR(INDEX('All Data'!$AJ:$AJ,MATCH($H$4&"",'All Data'!$A:$A,0)),"-")
B19: ATO Households (Transit) | C19: ==IFERROR(INDEX('All Data'!$Z:$Z,MATCH($H$4&"",'All Data'!$A:$A,0)),"-") | F19: ERU per Acre | G19: ==IFERROR(INDEX('All Data'!$AK:$AK,MATCH($H$4&"",'All Data'!$A:$A,0)),"-")
B20: SAP Planned HH/ac | C20: ==IFERROR(INDEX('All Data'!$AA:$AA,MATCH($H$4&"",'All Data'!$A:$A,0)),"-")
B22: INCOME | D22: POVERTY RATE | F22: UNEMPLOYMENT
C23: ==IFERROR(INDEX('All Data'!$AN:$AN,MATCH($H$4&"",'All Data'!$A:$A,0)),"-") | E23: ==IFERROR(INDEX('All Data'!$AL:$AL,MATCH($H$4&"",'All Data'!$A:$A,0)),"-") | G23: ==IFERROR(INDEX('All Data'!$AM:$AM,MATCH($H$4&"",'All Data'!$A:$A,0)),"-")
B24: =="Investment Likelihood: "&IFERROR(INDEX('All Data'!$AP:$AP,MATCH($H$4&"",'All Data'!$A:$A,0)),"—")
B25: Access to Opportunities (ATO) Composite Score /100 | F25: ==IFERROR(INDEX('All Data'!$AF:$AF,MATCH($H$4&"",'All Data'!$A:$A,0)),"-")
A29: =="02 — "&IFERROR(INDEX('All Data'!$C:$C,MATCH($H$29&"",'All Data'!$A:$A,0)),"")&" | GEOID "&$H$29&" | "&TEXT(IFERROR(INDEX('All Data'!$F:$F,MATCH($H$29&"",'All Data'!$A:$A,0)),0),"0")&" ac | "&IFERROR(INDEX('All Data'!$AP:$AP,MATCH($H$29&"",'All Data'!$A:$A,0)),"—") | H29: 49035100308
B30: TRACT PROFILE | D30: CENTERS & DISTRICTS | F30: HOUSING & DEMOGRAPHICS
B31: Population | C31: ==IFERROR(INDEX('All Data'!$D:$D,MATCH($H$29&"",'All Data'!$A:$A,0)),"-") | D31: WC MUorC % Total | E31: ==IFERROR(INDEX('All Data'!$J:$J,MATCH($H$29&"",'All Data'!$A:$A,0)),"-") | F31: Total Units | G31: ==IFERROR(INDEX('All Data'!$R:$R,MATCH($H$29&"",'All Data'!$A:$A,0)),"-")
B32: Households | C32: ==IFERROR(INDEX('All Data'!$E:$E,MATCH($H$29&"",'All Data'!$A:$A,0)),"-") | D32: Metropolitan Center | E32: ==IFERROR(INDEX('All Data'!$K:$K,MATCH($H$29&"",'All Data'!$A:$A,0)),"-") | F32: Residential Acres | G32: ==IFERROR(INDEX('All Data'!$S:$S,MATCH($H$29&"",'All Data'!$A:$A,0)),"-")
B33: Total Acres | C33: ==IFERROR(INDEX('All Data'!$F:$F,MATCH($H$29&"",'All Data'!$A:$A,0)),"-") | D33: Urban Center | E33: ==IFERROR(INDEX('All Data'!$L:$L,MATCH($H$29&"",'All Data'!$A:$A,0)),"-") | F33: SFD Acres | G33: ==IFERROR(INDEX('All Data'!$T:$T,MATCH($H$29&"",'All Data'!$A:$A,0)),"-")
B34: Developable Acres | C34: ==IFERROR(INDEX('All Data'!$G:$G,MATCH($H$29&"",'All Data'!$A:$A,0)),"-") | D34: City Center | E34: ==IFERROR(INDEX('All Data'!$M:$M,MATCH($H$29&"",'All Data'!$A:$A,0)),"-") | F34: MF / SFA Acres | G34: ==IFERROR(INDEX('All Data'!$U:$U,MATCH($H$29&"",'All Data'!$A:$A,0)),"-")
B35: OZ 1.0 Acres | C35: ==IFERROR(INDEX('All Data'!$H:$H,MATCH($H$29&"",'All Data'!$A:$A,0)),"-") | D35: Neighborhood Center | E35: ==IFERROR(INDEX('All Data'!$N:$N,MATCH($H$29&"",'All Data'!$A:$A,0)),"-") | F35: Poverty Rate | G35: ==IFERROR(INDEX('All Data'!$AL:$AL,MATCH($H$29&"",'All Data'!$A:$A,0)),"-")
B36: OZ 1.0 % of Tract | C36: ==IFERROR(INDEX('All Data'!$I:$I,MATCH($H$29&"",'All Data'!$A:$A,0)),"-") | D36: Employment District | E36: ==IFERROR(INDEX('All Data'!$O:$O,MATCH($H$29&"",'All Data'!$A:$A,0)),"-") | F36: Unemployment Rate | G36: ==IFERROR(INDEX('All Data'!$AM:$AM,MATCH($H$29&"",'All Data'!$A:$A,0)),"-")
D37: Industrial District | E37: ==IFERROR(INDEX('All Data'!$P:$P,MATCH($H$29&"",'All Data'!$A:$A,0)),"-") | F37: Median Family Income | G37: ==IFERROR(INDEX('All Data'!$AN:$AN,MATCH($H$29&"",'All Data'!$A:$A,0)),"-")
D38: Retail District | E38: ==IFERROR(INDEX('All Data'!$Q:$Q,MATCH($H$29&"",'All Data'!$A:$A,0)),"-")
B39: TRANSIT ACCESS | D39: AUTO ACCESS | F39: PROJECTED GROWTH 2027-37
B40: Rail / BRT Stops | C40: ==IFERROR(INDEX('All Data'!$V:$V,MATCH($H$29&"",'All Data'!$A:$A,0)),"-") | D40: Freeway Exits | E40: ==IFERROR(INDEX('All Data'!$AB:$AB,MATCH($H$29&"",'All Data'!$A:$A,0)),"-") | F40: Households Added | G40: ==IFERROR(INDEX('All Data'!$AG:$AG,MATCH($H$29&"",'All Data'!$A:$A,0)),"-")
B41: SAP Acres | C41: ==IFERROR(INDEX('All Data'!$W:$W,MATCH($H$29&"",'All Data'!$A:$A,0)),"-") | D41: Exit Distance (mi) | E41: ==IFERROR(INDEX('All Data'!$AC:$AC,MATCH($H$29&"",'All Data'!$A:$A,0)),"-") | F41: Population Added | G41: ==IFERROR(INDEX('All Data'!$AH:$AH,MATCH($H$29&"",'All Data'!$A:$A,0)),"-")
B42: SAP % of Tract | C42: ==IFERROR(INDEX('All Data'!$X:$X,MATCH($H$29&"",'All Data'!$A:$A,0)),"-") | D42: ATO Jobs (Auto) | E42: ==IFERROR(INDEX('All Data'!$AD:$AD,MATCH($H$29&"",'All Data'!$A:$A,0)),"-") | F42: Jobs Added | G42: ==IFERROR(INDEX('All Data'!$AI:$AI,MATCH($H$29&"",'All Data'!$A:$A,0)),"-")
B43: ATO Jobs (Transit) | C43: ==IFERROR(INDEX('All Data'!$Y:$Y,MATCH($H$29&"",'All Data'!$A:$A,0)),"-") | D43: ATO Households (Auto) | E43: ==IFERROR(INDEX('All Data'!$AE:$AE,MATCH($H$29&"",'All Data'!$A:$A,0)),"-") | F43: ERU Added | G43: ==IFERROR(INDEX('All Data'!$AJ:$AJ,MATCH($H$29&"",'All Data'!$A:$A,0)),"-")
B44: ATO Households (Transit) | C44: ==IFERROR(INDEX('All Data'!$Z:$Z,MATCH($H$29&"",'All Data'!$A:$A,0)),"-") | F44: ERU per Acre | G44: ==IFERROR(INDEX('All Data'!$AK:$AK,MATCH($H$29&"",'All Data'!$A:$A,0)),"-")
B45: SAP Planned HH/ac | C45: ==IFERROR(INDEX('All Data'!$AA:$AA,MATCH($H$29&"",'All Data'!$A:$A,0)),"-")
B47: INCOME | D47: POVERTY RATE | F47: UNEMPLOYMENT
C48: ==IFERROR(INDEX('All Data'!$AN:$AN,MATCH($H$29&"",'All Data'!$A:$A,0)),"-") | E48: ==IFERROR(INDEX('All Data'!$AL:$AL,MATCH($H$29&"",'All Data'!$A:$A,0)),"-") | G48: ==IFERROR(INDEX('All Data'!$AM:$AM,MATCH($H$29&"",'All Data'!$A:$A,0)),"-")
B49: =="Investment Likelihood: "&IFERROR(INDEX('All Data'!$AP:$AP,MATCH($H$29&"",'All Data'!$A:$A,0)),"—")
B50: Access to Opportunities (ATO) Composite Score /100 | F50: ==IFERROR(INDEX('All Data'!$AF:$AF,MATCH($H$29&"",'All Data'!$A:$A,0)),"-")
A54: =="03 — "&IFERROR(INDEX('All Data'!$C:$C,MATCH($H$54&"",'All Data'!$A:$A,0)),"")&" | GEOID "&$H$54&" | "&TEXT(IFERROR(INDEX('All Data'!$F:$F,MATCH($H$54&"",'All Data'!$A:$A,0)),0),"0")&" ac | "&IFERROR(INDEX('All Data'!$AP:$AP,MATCH($H$54&"",'All Data'!$A:$A,0)),"—") | H54: 49035100500
B55: TRACT PROFILE | D55: CENTERS & DISTRICTS | F55: HOUSING & DEMOGRAPHICS
B56: Population | C56: ==IFERROR(INDEX('All Data'!$D:$D,MATCH($H$54&"",'All Data'!$A:$A,0)),"-") | D56: WC MUorC % Total | E56: ==IFERROR(INDEX('All Data'!$J:$J,MATCH($H$54&"",'All Data'!$A:$A,0)),"-") | F56: Total Units | G56: ==IFERROR(INDEX('All Data'!$R:$R,MATCH($H$54&"",'All Data'!$A:$A,0)),"-")
B57: Households | C57: ==IFERROR(INDEX('All Data'!$E:$E,MATCH($H$54&"",'All Data'!$A:$A,0)),"-") | D57: Metropolitan Center | E57: ==IFERROR(INDEX('All Data'!$K:$K,MATCH($H$54&"",'All Data'!$A:$A,0)),"-") | F57: Residential Acres | G57: ==IFERROR(INDEX('All Data'!$S:$S,MATCH($H$54&"",'All Data'!$A:$A,0)),"-")
B58: Total Acres | C58: ==IFERROR(INDEX('All Data'!$F:$F,MATCH($H$54&"",'All Data'!$A:$A,0)),"-") | D58: Urban Center | E58: ==IFERROR(INDEX('All Data'!$L:$L,MATCH($H$54&"",'All Data'!$A:$A,0)),"-") | F58: SFD Acres | G58: ==IFERROR(INDEX('All Data'!$T:$T,MATCH($H$54&"",'All Data'!$A:$A,0)),"-")
B59: Developable Acres | C59: ==IFERROR(INDEX('All Data'!$G:$G,MATCH($H$54&"",'All Data'!$A:$A,0)),"-") | D59: City Center | E59: ==IFERROR(INDEX('All Data'!$M:$M,MATCH($H$54&"",'All Data'!$A:$A,0)),"-") | F59: MF / SFA Acres | G59: ==IFERROR(INDEX('All Data'!$U:$U,MATCH($H$54&"",'All Data'!$A:$A,0)),"-")
B60: OZ 1.0 Acres | C60: ==IFERROR(INDEX('All Data'!$H:$H,MATCH($H$54&"",'All Data'!$A:$A,0)),"-") | D60: Neighborhood Center | E60: ==IFERROR(INDEX('All Data'!$N:$N,MATCH($H$54&"",'All Data'!$A:$A,0)),"-") | F60: Poverty Rate | G60: ==IFERROR(INDEX('All Data'!$AL:$AL,MATCH($H$54&"",'All Data'!$A:$A,0)),"-")
B61: OZ 1.0 % of Tract | C61: ==IFERROR(INDEX('All Data'!$I:$I,MATCH($H$54&"",'All Data'!$A:$A,0)),"-") | D61: Employment District | E61: ==IFERROR(INDEX('All Data'!$O:$O,MATCH($H$54&"",'All Data'!$A:$A,0)),"-") | F61: Unemployment Rate | G61: ==IFERROR(INDEX('All Data'!$AM:$AM,MATCH($H$54&"",'All Data'!$A:$A,0)),"-")
D62: Industrial District | E62: ==IFERROR(INDEX('All Data'!$P:$P,MATCH($H$54&"",'All Data'!$A:$A,0)),"-") | F62: Median Family Income | G62: ==IFERROR(INDEX('All Data'!$AN:$AN,MATCH($H$54&"",'All Data'!$A:$A,0)),"-")
D63: Retail District | E63: ==IFERROR(INDEX('All Data'!$Q:$Q,MATCH($H$54&"",'All Data'!$A:$A,0)),"-")
B64: TRANSIT ACCESS | D64: AUTO ACCESS | F64: PROJECTED GROWTH 2027-37
B65: Rail / BRT Stops | C65: ==IFERROR(INDEX('All Data'!$V:$V,MATCH($H$54&"",'All Data'!$A:$A,0)),"-") | D65: Freeway Exits | E65: ==IFERROR(INDEX('All Data'!$AB:$AB,MATCH($H$54&"",'All Data'!$A:$A,0)),"-") | F65: Households Added | G65: ==IFERROR(INDEX('All Data'!$AG:$AG,MATCH($H$54&"",'All Data'!$A:$A,0)),"-")
B66: SAP Acres | C66: ==IFERROR(INDEX('All Data'!$W:$W,MATCH($H$54&"",'All Data'!$A:$A,0)),"-") | D66: Exit Distance (mi) | E66: ==IFERROR(INDEX('All Data'!$AC:$AC,MATCH($H$54&"",'All Data'!$A:$A,0)),"-") | F66: Population Added | G66: ==IFERROR(INDEX('All Data'!$AH:$AH,MATCH($H$54&"",'All Data'!$A:$A,0)),"-")
B67: SAP % of Tract | C67: ==IFERROR(INDEX('All Data'!$X:$X,MATCH($H$54&"",'All Data'!$A:$A,0)),"-") | D67: ATO Jobs (Auto) | E67: ==IFERROR(INDEX('All Data'!$AD:$AD,MATCH($H$54&"",'All Data'!$A:$A,0)),"-") | F67: Jobs Added | G67: ==IFERROR(INDEX('All Data'!$AI:$AI,MATCH($H$54&"",'All Data'!$A:$A,0)),"-")
B68: ATO Jobs (Transit) | C68: ==IFERROR(INDEX('All Data'!$Y:$Y,MATCH($H$54&"",'All Data'!$A:$A,0)),"-") | D68: ATO Households (Auto) | E68: ==IFERROR(INDEX('All Data'!$AE:$AE,MATCH($H$54&"",'All Data'!$A:$A,0)),"-") | F68: ERU Added | G68: ==IFERROR(INDEX('All Data'!$AJ:$AJ,MATCH($H$54&"",'All Data'!$A:$A,0)),"-")
B69: ATO Households (Transit) | C69: ==IFERROR(INDEX('All Data'!$Z:$Z,MATCH($H$54&"",'All Data'!$A:$A,0)),"-") | F69: ERU per Acre | G69: ==IFERROR(INDEX('All Data'!$AK:$AK,MATCH($H$54&"",'All Data'!$A:$A,0)),"-")
B70: SAP Planned HH/ac | C70: ==IFERROR(INDEX('All Data'!$AA:$AA,MATCH($H$54&"",'All Data'!$A:$A,0)),"-")
B72: INCOME | D72: POVERTY RATE | F72: UNEMPLOYMENT
C73: ==IFERROR(INDEX('All Data'!$AN:$AN,MATCH($H$54&"",'All Data'!$A:$A,0)),"-") | E73: ==IFERROR(INDEX('All Data'!$AL:$AL,MATCH($H$54&"",'All Data'!$A:$A,0)),"-") | G73: ==IFERROR(INDEX('All Data'!$AM:$AM,MATCH($H$54&"",'All Data'!$A:$A,0)),"-")
B74: =="Investment Likelihood: "&IFERROR(INDEX('All Data'!$AP:$AP,MATCH($H$54&"",'All Data'!$A:$A,0)),"—")
B75: Access to Opportunities (ATO) Composite Score /100 | F75: ==IFERROR(INDEX('All Data'!$AF:$AF,MATCH($H$54&"",'All Data'!$A:$A,0)),"-")
A79: =="04 — "&IFERROR(INDEX('All Data'!$C:$C,MATCH($H$79&"",'All Data'!$A:$A,0)),"")&" | GEOID "&$H$79&" | "&TEXT(IFERROR(INDEX('All Data'!$F:$F,MATCH($H$79&"",'All Data'!$A:$A,0)),0),"0")&" ac | "&IFERROR(INDEX('All Data'!$AP:$AP,MATCH($H$79&"",'All Data'!$A:$A,0)),"—") | H79: 49035100600
B80: TRACT PROFILE | D80: CENTERS & DISTRICTS | F80: HOUSING & DEMOGRAPHICS
B81: Population | C81: ==IFERROR(INDEX('All Data'!$D:$D,MATCH($H$79&"",'All Data'!$A:$A,0)),"-") | D81: WC MUorC % Total | E81: ==IFERROR(INDEX('All Data'!$J:$J,MATCH($H$79&"",'All Data'!$A:$A,0)),"-") | F81: Total Units | G81: ==IFERROR(INDEX('All Data'!$R:$R,MATCH($H$79&"",'All Data'!$A:$A,0)),"-")
B82: Households | C82: ==IFERROR(INDEX('All Data'!$E:$E,MATCH($H$79&"",'All Data'!$A:$A,0)),"-") | D82: Metropolitan Center | E82: ==IFERROR(INDEX('All Data'!$K:$K,MATCH($H$79&"",'All Data'!$A:$A,0)),"-") | F82: Residential Acres | G82: ==IFERROR(INDEX('All Data'!$S:$S,MATCH($H$79&"",'All Data'!$A:$A,0)),"-")
B83: Total Acres | C83: ==IFERROR(INDEX('All Data'!$F:$F,MATCH($H$79&"",'All Data'!$A:$A,0)),"-") | D83: Urban Center | E83: ==IFERROR(INDEX('All Data'!$L:$L,MATCH($H$79&"",'All Data'!$A:$A,0)),"-") | F83: SFD Acres | G83: ==IFERROR(INDEX('All Data'!$T:$T,MATCH($H$79&"",'All Data'!$A:$A,0)),"-")
B84: Developable Acres | C84: ==IFERROR(INDEX('All Data'!$G:$G,MATCH($H$79&"",'All Data'!$A:$A,0)),"-") | D84: City Center | E84: ==IFERROR(INDEX('All Data'!$M:$M,MATCH($H$79&"",'All Data'!$A:$A,0)),"-") | F84: MF / SFA Acres | G84: ==IFERROR(INDEX('All Data'!$U:$U,MATCH($H$79&"",'All Data'!$A:$A,0)),"-")
B85: OZ 1.0 Acres | C85: ==IFERROR(INDEX('All Data'!$H:$H,MATCH($H$79&"",'All Data'!$A:$A,0)),"-") | D85: Neighborhood Center | E85: ==IFERROR(INDEX('All Data'!$N:$N,MATCH($H$79&"",'All Data'!$A:$A,0)),"-") | F85: Poverty Rate | G85: ==IFERROR(INDEX('All Data'!$AL:$AL,MATCH($H$79&"",'All Data'!$A:$A,0)),"-")
B86: OZ 1.0 % of Tract | C86: ==IFERROR(INDEX('All Data'!$I:$I,MATCH($H$79&"",'All Data'!$A:$A,0)),"-") | D86: Employment District | E86: ==IFERROR(INDEX('All Data'!$O:$O,MATCH($H$79&"",'All Data'!$A:$A,0)),"-") | F86: Unemployment Rate | G86: ==IFERROR(INDEX('All Data'!$AM:$AM,MATCH($H$79&"",'All Data'!$A:$A,0)),"-")
D87: Industrial District | E87: ==IFERROR(INDEX('All Data'!$P:$P,MATCH($H$79&"",'All Data'!$A:$A,0)),"-") | F87: Median Family Income | G87: ==IFERROR(INDEX('All Data'!$AN:$AN,MATCH($H$79&"",'All Data'!$A:$A,0)),"-")
D88: Retail District | E88: ==IFERROR(INDEX('All Data'!$Q:$Q,MATCH($H$79&"",'All Data'!$A:$A,0)),"-")
B89: TRANSIT ACCESS | D89: AUTO ACCESS | F89: PROJECTED GROWTH 2027-37
B90: Rail / BRT Stops | C90: ==IFERROR(INDEX('All Data'!$V:$V,MATCH($H$79&"",'All Data'!$A:$A,0)),"-") | D90: Freeway Exits | E90: ==IFERROR(INDEX('All Data'!$AB:$AB,MATCH($H$79&"",'All Data'!$A:$A,0)),"-") | F90: Households Added | G90: ==IFERROR(INDEX('All Data'!$AG:$AG,MATCH($H$79&"",'All Data'!$A:$A,0)),"-")
B91: SAP Acres | C91: ==IFERROR(INDEX('All Data'!$W:$W,MATCH($H$79&"",'All Data'!$A:$A,0)),"-") | D91: Exit Distance (mi) | E91: ==IFERROR(INDEX('All Data'!$AC:$AC,MATCH($H$79&"",'All Data'!$A:$A,0)),"-") | F91: Population Added | G91: ==IFERROR(INDEX('All Data'!$AH:$AH,MATCH($H$79&"",'All Data'!$A:$A,0)),"-")
B92: SAP % of Tract | C92: ==IFERROR(INDEX('All Data'!$X:$X,MATCH($H$79&"",'All Data'!$A:$A,0)),"-") | D92: ATO Jobs (Auto) | E92: ==IFERROR(INDEX('All Data'!$AD:$AD,MATCH($H$79&"",'All Data'!$A:$A,0)),"-") | F92: Jobs Added | G92: ==IFERROR(INDEX('All Data'!$AI:$AI,MATCH($H$79&"",'All Data'!$A:$A,0)),"-")
B93: ATO Jobs (Transit) | C93: ==IFERROR(INDEX('All Data'!$Y:$Y,MATCH($H$79&"",'All Data'!$A:$A,0)),"-") | D93: ATO Households (Auto) | E93: ==IFERROR(INDEX('All Data'!$AE:$AE,MATCH($H$79&"",'All Data'!$A:$A,0)),"-") | F93: ERU Added | G93: ==IFERROR(INDEX('All Data'!$AJ:$AJ,MATCH($H$79&"",'All Data'!$A:$A,0)),"-")
B94: ATO Households (Transit) | C94: ==IFERROR(INDEX('All Data'!$Z:$Z,MATCH($H$79&"",'All Data'!$A:$A,0)),"-") | F94: ERU per Acre | G94: ==IFERROR(INDEX('All Data'!$AK:$AK,MATCH($H$79&"",'All Data'!$A:$A,0)),"-")
B95: SAP Planned HH/ac | C95: ==IFERROR(INDEX('All Data'!$AA:$AA,MATCH($H$79&"",'All Data'!$A:$A,0)),"-")
B97: INCOME | D97: POVERTY RATE | F97: UNEMPLOYMENT
C98: ==IFERROR(INDEX('All Data'!$AN:$AN,MATCH($H$79&"",'All Data'!$A:$A,0)),"-") | E98: ==IFERROR(INDEX('All Data'!$AL:$AL,MATCH($H$79&"",'All Data'!$A:$A,0)),"-") | G98: ==IFERROR(INDEX('All Data'!$AM:$AM,MATCH($H$79&"",'All Data'!$A:$A,0)),"-")
B99: =="Investment Likelihood: "&IFERROR(INDEX('All Data'!$AP:$AP,MATCH($H$79&"",'All Data'!$A:$A,0)),"—")
B100: Access to Opportunities (ATO) Composite Score /100 | F100: ==IFERROR(INDEX('All Data'!$AF:$AF,MATCH($H$79&"",'All Data'!$A:$A,0)),"-")
A104: =="05 — "&IFERROR(INDEX('All Data'!$C:$C,MATCH($H$104&"",'All Data'!$A:$A,0)),"")&" | GEOID "&$H$104&" | "&TEXT(IFERROR(INDEX('All Data'!$F:$F,MATCH($H$104&"",'All Data'!$A:$A,0)),0),"0")&" ac | "&IFERROR(INDEX('All Data'!$AP:$AP,MATCH($H$104&"",'All Data'!$A:$A,0)),"—") | H104: 49035100800
B105: TRACT PROFILE | D105: CENTERS & DISTRICTS | F105: HOUSING & DEMOGRAPHICS
B106: Population | C106: ==IFERROR(INDEX('All Data'!$D:$D,MATCH($H$104&"",'All Data'!$A:$A,0)),"-") | D106: WC MUorC % Total | E106: ==IFERROR(INDEX('All Data'!$J:$J,MATCH($H$104&"",'All Data'!$A:$A,0)),"-") | F106: Total Units | G106: ==IFERROR(INDEX('All Data'!$R:$R,MATCH($H$104&"",'All Data'!$A:$A,0)),"-")
B107: Households | C107: ==IFERROR(INDEX('All Data'!$E:$E,MATCH($H$104&"",'All Data'!$A:$A,0)),"-") | D107: Metropolitan Center | E107: ==IFERROR(INDEX('All Data'!$K:$K,MATCH($H$104&"",'All Data'!$A:$A,0)),"-") | F107: Residential Acres | G107: ==IFERROR(INDEX('All Data'!$S:$S,MATCH($H$104&"",'All Data'!$A:$A,0)),"-")
B108: Total Acres | C108: ==IFERROR(INDEX('All Data'!$F:$F,MATCH($H$104&"",'All Data'!$A:$A,0)),"-") | D108: Urban Center | E108: ==IFERROR(INDEX('All Data'!$L:$L,MATCH($H$104&"",'All Data'!$A:$A,0)),"-") | F108: SFD Acres | G108: ==IFERROR(INDEX('All Data'!$T:$T,MATCH($H$104&"",'All Data'!$A:$A,0)),"-")
B109: Developable Acres | C109: ==IFERROR(INDEX('All Data'!$G:$G,MATCH($H$104&"",'All Data'!$A:$A,0)),"-") | D109: City Center | E109: ==IFERROR(INDEX('All Data'!$M:$M,MATCH($H$104&"",'All Data'!$A:$A,0)),"-") | F109: MF / SFA Acres | G109: ==IFERROR(INDEX('All Data'!$U:$U,MATCH($H$104&"",'All Data'!$A:$A,0)),"-")
B110: OZ 1.0 Acres | C110: ==IFERROR(INDEX('All Data'!$H:$H,MATCH($H$104&"",'All Data'!$A:$A,0)),"-") | D110: Neighborhood Center | E110: ==IFERROR(INDEX('All Data'!$N:$N,MATCH($H$104&"",'All Data'!$A:$A,0)),"-") | F110: Poverty Rate | G110: ==IFERROR(INDEX('All Data'!$AL:$AL,MATCH($H$104&"",'All Data'!$A:$A,0)),"-")
B111: OZ 1.0 % of Tract | C111: ==IFERROR(INDEX('All Data'!$I:$I,MATCH($H$104&"",'All Data'!$A:$A,0)),"-") | D111: Employment District | E111: ==IFERROR(INDEX('All Data'!$O:$O,MATCH($H$104&"",'All Data'!$A:$A,0)),"-") | F111: Unemployment Rate | G111: ==IFERROR(INDEX('All Data'!$AM:$AM,MATCH($H$104&"",'All Data'!$A:$A,0)),"-")
D112: Industrial District | E112: ==IFERROR(INDEX('All Data'!$P:$P,MATCH($H$104&"",'All Data'!$A:$A,0)),"-") | F112: Median Family Income | G112: ==IFERROR(INDEX('All Data'!$AN:$AN,MATCH($H$104&"",'All Data'!$A:$A,0)),"-")
D113: Retail District | E113: ==IFERROR(INDEX('All Data'!$Q:$Q,MATCH($H$104&"",'All Data'!$A:$A,0)),"-")
B114: TRANSIT ACCESS | D114: AUTO ACCESS | F114: PROJECTED GROWTH 2027-37
B115: Rail / BRT Stops | C115: ==IFERROR(INDEX('All Data'!$V:$V,MATCH($H$104&"",'All Data'!$A:$A,0)),"-") | D115: Freeway Exits | E115: ==IFERROR(INDEX('All Data'!$AB:$AB,MATCH($H$104&"",'All Data'!$A:$A,0)),"-") | F115: Households Added | G115: ==IFERROR(INDEX('All Data'!$AG:$AG,MATCH($H$104&"",'All Data'!$A:$A,0)),"-")
B116: SAP Acres | C116: ==IFERROR(INDEX('All Data'!$W:$W,MATCH($H$104&"",'All Data'!$A:$A,0)),"-") | D116: Exit Distance (mi) | E116: ==IFERROR(INDEX('All Data'!$AC:$AC,MATCH($H$104&"",'All Data'!$A:$A,0)),"-") | F116: Population Added | G116: ==IFERROR(INDEX('All Data'!$AH:$AH,MATCH($H$104&"",'All Data'!$A:$A,0)),"-")
B117: SAP % of Tract | C117: ==IFERROR(INDEX('All Data'!$X:$X,MATCH($H$104&"",'All Data'!$A:$A,0)),"-") | D117: ATO Jobs (Auto) | E117: ==IFERROR(INDEX('All Data'!$AD:$AD,MATCH($H$104&"",'All Data'!$A:$A,0)),"-") | F117: Jobs Added | G117: ==IFERROR(INDEX('All Data'!$AI:$AI,MATCH($H$104&"",'All Data'!$A:$A,0)),"-")
...

Sheet Tooele County
A1: Tooele County — OZ 2.0 Candidate Tracts — Detail
A2: WFRC & MAG Region | Generated June 01, 2026
A4: =="01 — "&IFERROR(INDEX('All Data'!$C:$C,MATCH($H$4&"",'All Data'!$A:$A,0)),"")&" | GEOID "&$H$4&" | "&TEXT(IFERROR(INDEX('All Data'!$F:$F,MATCH($H$4&"",'All Data'!$A:$A,0)),0),"0")&" ac | "&IFERROR(INDEX('All Data'!$AP:$AP,MATCH($H$4&"",'All Data'!$A:$A,0)),"—") | H4: 49045130600
B5: TRACT PROFILE | D5: CENTERS & DISTRICTS | F5: HOUSING & DEMOGRAPHICS
B6: Population | C6: ==IFERROR(INDEX('All Data'!$D:$D,MATCH($H$4&"",'All Data'!$A:$A,0)),"-") | D6: WC MUorC % Total | E6: ==IFERROR(INDEX('All Data'!$J:$J,MATCH($H$4&"",'All Data'!$A:$A,0)),"-") | F6: Total Units | G6: ==IFERROR(INDEX('All Data'!$R:$R,MATCH($H$4&"",'All Data'!$A:$A,0)),"-")
B7: Households | C7: ==IFERROR(INDEX('All Data'!$E:$E,MATCH($H$4&"",'All Data'!$A:$A,0)),"-") | D7: Metropolitan Center | E7: ==IFERROR(INDEX('All Data'!$K:$K,MATCH($H$4&"",'All Data'!$A:$A,0)),"-") | F7: Residential Acres | G7: ==IFERROR(INDEX('All Data'!$S:$S,MATCH($H$4&"",'All Data'!$A:$A,0)),"-")
B8: Total Acres | C8: ==IFERROR(INDEX('All Data'!$F:$F,MATCH($H$4&"",'All Data'!$A:$A,0)),"-") | D8: Urban Center | E8: ==IFERROR(INDEX('All Data'!$L:$L,MATCH($H$4&"",'All Data'!$A:$A,0)),"-") | F8: SFD Acres | G8: ==IFERROR(INDEX('All Data'!$T:$T,MATCH($H$4&"",'All Data'!$A:$A,0)),"-")
B9: Developable Acres | C9: ==IFERROR(INDEX('All Data'!$G:$G,MATCH($H$4&"",'All Data'!$A:$A,0)),"-") | D9: City Center | E9: ==IFERROR(INDEX('All Data'!$M:$M,MATCH($H$4&"",'All Data'!$A:$A,0)),"-") | F9: MF / SFA Acres | G9: ==IFERROR(INDEX('All Data'!$U:$U,MATCH($H$4&"",'All Data'!$A:$A,0)),"-")
B10: OZ 1.0 Acres | C10: ==IFERROR(INDEX('All Data'!$H:$H,MATCH($H$4&"",'All Data'!$A:$A,0)),"-") | D10: Neighborhood Center | E10: ==IFERROR(INDEX('All Data'!$N:$N,MATCH($H$4&"",'All Data'!$A:$A,0)),"-") | F10: Poverty Rate | G10: ==IFERROR(INDEX('All Data'!$AL:$AL,MATCH($H$4&"",'All Data'!$A:$A,0)),"-")
B11: OZ 1.0 % of Tract | C11: ==IFERROR(INDEX('All Data'!$I:$I,MATCH($H$4&"",'All Data'!$A:$A,0)),"-") | D11: Employment District | E11: ==IFERROR(INDEX('All Data'!$O:$O,MATCH($H$4&"",'All Data'!$A:$A,0)),"-") | F11: Unemployment Rate | G11: ==IFERROR(INDEX('All Data'!$AM:$AM,MATCH($H$4&"",'All Data'!$A:$A,0)),"-")
D12: Industrial District | E12: ==IFERROR(INDEX('All Data'!$P:$P,MATCH($H$4&"",'All Data'!$A:$A,0)),"-") | F12: Median Family Income | G12: ==IFERROR(INDEX('All Data'!$AN:$AN,MATCH($H$4&"",'All Data'!$A:$A,0)),"-")
D13: Retail District | E13: ==IFERROR(INDEX('All Data'!$Q:$Q,MATCH($H$4&"",'All Data'!$A:$A,0)),"-")
B14: TRANSIT ACCESS | D14: AUTO ACCESS | F14: PROJECTED GROWTH 2027-37
B15: Rail / BRT Stops | C15: ==IFERROR(INDEX('All Data'!$V:$V,MATCH($H$4&"",'All Data'!$A:$A,0)),"-") | D15: Freeway Exits | E15: ==IFERROR(INDEX('All Data'!$AB:$AB,MATCH($H$4&"",'All Data'!$A:$A,0)),"-") | F15: Households Added | G15: ==IFERROR(INDEX('All Data'!$AG:$AG,MATCH($H$4&"",'All Data'!$A:$A,0)),"-")
B16: SAP Acres | C16: ==IFERROR(INDEX('All Data'!$W:$W,MATCH($H$4&"",'All Data'!$A:$A,0)),"-") | D16: Exit Distance (mi) | E16: ==IFERROR(INDEX('All Data'!$AC:$AC,MATCH($H$4&"",'All Data'!$A:$A,0)),"-") | F16: Population Added | G16: ==IFERROR(INDEX('All Data'!$AH:$AH,MATCH($H$4&"",'All Data'!$A:$A,0)),"-")
B17: SAP % of Tract | C17: ==IFERROR(INDEX('All Data'!$X:$X,MATCH($H$4&"",'All Data'!$A:$A,0)),"-") | D17: ATO Jobs (Auto) | E17: ==IFERROR(INDEX('All Data'!$AD:$AD,MATCH($H$4&"",'All Data'!$A:$A,0)),"-") | F17: Jobs Added | G17: ==IFERROR(INDEX('All Data'!$AI:$AI,MATCH($H$4&"",'All Data'!$A:$A,0)),"-")
B18: ATO Jobs (Transit) | C18: ==IFERROR(INDEX('All Data'!$Y:$Y,MATCH($H$4&"",'All Data'!$A:$A,0)),"-") | D18: ATO Households (Auto) | E18: ==IFERROR(INDEX('All Data'!$AE:$AE,MATCH($H$4&"",'All Data'!$A:$A,0)),"-") | F18: ERU Added | G18: ==IFERROR(INDEX('All Data'!$AJ:$AJ,MATCH($H$4&"",'All Data'!$A:$A,0)),"-")
B19: ATO Households (Transit) | C19: ==IFERROR(INDEX('All Data'!$Z:$Z,MATCH($H$4&"",'All Data'!$A:$A,0)),"-") | F19: ERU per Acre | G19: ==IFERROR(INDEX('All Data'!$AK:$AK,MATCH($H$4&"",'All Data'!$A:$A,0)),"-")
B20: SAP Planned HH/ac | C20: ==IFERROR(INDEX('All Data'!$AA:$AA,MATCH($H$4&"",'All Data'!$A:$A,0)),"-")
B22: INCOME | D22: POVERTY RATE | F22: UNEMPLOYMENT
C23: ==IFERROR(INDEX('All Data'!$AN:$AN,MATCH($H$4&"",'All Data'!$A:$A,0)),"-") | E23: ==IFERROR(INDEX('All Data'!$AL:$AL,MATCH($H$4&"",'All Data'!$A:$A,0)),"-") | G23: ==IFERROR(INDEX('All Data'!$AM:$AM,MATCH($H$4&"",'All Data'!$A:$A,0)),"-")
B24: =="Investment Likelihood: "&IFERROR(INDEX('All Data'!$AP:$AP,MATCH($H$4&"",'All Data'!$A:$A,0)),"—")
B25: Access to Opportunities (ATO) Composite Score /100 | F25: ==IFERROR(INDEX('All Data'!$AF:$AF,MATCH($H$4&"",'All Data'!$A:$A,0)),"-")
A29: =="02 — "&IFERROR(INDEX('All Data'!$C:$C,MATCH($H$29&"",'All Data'!$A:$A,0)),"")&" | GEOID "&$H$29&" | "&TEXT(IFERROR(INDEX('All Data'!$F:$F,MATCH($H$29&"",'All Data'!$A:$A,0)),0),"0")&" ac | "&IFERROR(INDEX('All Data'!$AP:$AP,MATCH($H$29&"",'All Data'!$A:$A,0)),"—") | H29: 49045131003
B30: TRACT PROFILE | D30: CENTERS & DISTRICTS | F30: HOUSING & DEMOGRAPHICS
B31: Population | C31: ==IFERROR(INDEX('All Data'!$D:$D,MATCH($H$29&"",'All Data'!$A:$A,0)),"-") | D31: WC MUorC % Total | E31: ==IFERROR(INDEX('All Data'!$J:$J,MATCH($H$29&"",'All Data'!$A:$A,0)),"-") | F31: Total Units | G31: ==IFERROR(INDEX('All Data'!$R:$R,MATCH($H$29&"",'All Data'!$A:$A,0)),"-")
B32: Households | C32: ==IFERROR(INDEX('All Data'!$E:$E,MATCH($H$29&"",'All Data'!$A:$A,0)),"-") | D32: Metropolitan Center | E32: ==IFERROR(INDEX('All Data'!$K:$K,MATCH($H$29&"",'All Data'!$A:$A,0)),"-") | F32: Residential Acres | G32: ==IFERROR(INDEX('All Data'!$S:$S,MATCH($H$29&"",'All Data'!$A:$A,0)),"-")
B33: Total Acres | C33: ==IFERROR(INDEX('All Data'!$F:$F,MATCH($H$29&"",'All Data'!$A:$A,0)),"-") | D33: Urban Center | E33: ==IFERROR(INDEX('All Data'!$L:$L,MATCH($H$29&"",'All Data'!$A:$A,0)),"-") | F33: SFD Acres | G33: ==IFERROR(INDEX('All Data'!$T:$T,MATCH($H$29&"",'All Data'!$A:$A,0)),"-")
B34: Developable Acres | C34: ==IFERROR(INDEX('All Data'!$G:$G,MATCH($H$29&"",'All Data'!$A:$A,0)),"-") | D34: City Center | E34: ==IFERROR(INDEX('All Data'!$M:$M,MATCH($H$29&"",'All Data'!$A:$A,0)),"-") | F34: MF / SFA Acres | G34: ==IFERROR(INDEX('All Data'!$U:$U,MATCH($H$29&"",'All Data'!$A:$A,0)),"-")
B35: OZ 1.0 Acres | C35: ==IFERROR(INDEX('All Data'!$H:$H,MATCH($H$29&"",'All Data'!$A:$A,0)),"-") | D35: Neighborhood Center | E35: ==IFERROR(INDEX('All Data'!$N:$N,MATCH($H$29&"",'All Data'!$A:$A,0)),"-") | F35: Poverty Rate | G35: ==IFERROR(INDEX('All Data'!$AL:$AL,MATCH($H$29&"",'All Data'!$A:$A,0)),"-")
B36: OZ 1.0 % of Tract | C36: ==IFERROR(INDEX('All Data'!$I:$I,MATCH($H$29&"",'All Data'!$A:$A,0)),"-") | D36: Employment District | E36: ==IFERROR(INDEX('All Data'!$O:$O,MATCH($H$29&"",'All Data'!$A:$A,0)),"-") | F36: Unemployment Rate | G36: ==IFERROR(INDEX('All Data'!$AM:$AM,MATCH($H$29&"",'All Data'!$A:$A,0)),"-")
D37: Industrial District | E37: ==IFERROR(INDEX('All Data'!$P:$P,MATCH($H$29&"",'All Data'!$A:$A,0)),"-") | F37: Median Family Income | G37: ==IFERROR(INDEX('All Data'!$AN:$AN,MATCH($H$29&"",'All Data'!$A:$A,0)),"-")
D38: Retail District | E38: ==IFERROR(INDEX('All Data'!$Q:$Q,MATCH($H$29&"",'All Data'!$A:$A,0)),"-")
B39: TRANSIT ACCESS | D39: AUTO ACCESS | F39: PROJECTED GROWTH 2027-37
B40: Rail / BRT Stops | C40: ==IFERROR(INDEX('All Data'!$V:$V,MATCH($H$29&"",'All Data'!$A:$A,0)),"-") | D40: Freeway Exits | E40: ==IFERROR(INDEX('All Data'!$AB:$AB,MATCH($H$29&"",'All Data'!$A:$A,0)),"-") | F40: Households Added | G40: ==IFERROR(INDEX('All Data'!$AG:$AG,MATCH($H$29&"",'All Data'!$A:$A,0)),"-")
B41: SAP Acres | C41: ==IFERROR(INDEX('All Data'!$W:$W,MATCH($H$29&"",'All Data'!$A:$A,0)),"-") | D41: Exit Distance (mi) | E41: ==IFERROR(INDEX('All Data'!$AC:$AC,MATCH($H$29&"",'All Data'!$A:$A,0)),"-") | F41: Population Added | G41: ==IFERROR(INDEX('All Data'!$AH:$AH,MATCH($H$29&"",'All Data'!$A:$A,0)),"-")
B42: SAP % of Tract | C42: ==IFERROR(INDEX('All Data'!$X:$X,MATCH($H$29&"",'All Data'!$A:$A,0)),"-") | D42: ATO Jobs (Auto) | E42: ==IFERROR(INDEX('All Data'!$AD:$AD,MATCH($H$29&"",'All Data'!$A:$A,0)),"-") | F42: Jobs Added | G42: ==IFERROR(INDEX('All Data'!$AI:$AI,MATCH($H$29&"",'All Data'!$A:$A,0)),"-")
B43: ATO Jobs (Transit) | C43: ==IFERROR(INDEX('All Data'!$Y:$Y,MATCH($H$29&"",'All Data'!$A:$A,0)),"-") | D43: ATO Households (Auto) | E43: ==IFERROR(INDEX('All Data'!$AE:$AE,MATCH($H$29&"",'All Data'!$A:$A,0)),"-") | F43: ERU Added | G43: ==IFERROR(INDEX('All Data'!$AJ:$AJ,MATCH($H$29&"",'All Data'!$A:$A,0)),"-")
B44: ATO Households (Transit) | C44: ==IFERROR(INDEX('All Data'!$Z:$Z,MATCH($H$29&"",'All Data'!$A:$A,0)),"-") | F44: ERU per Acre | G44: ==IFERROR(INDEX('All Data'!$AK:$AK,MATCH($H$29&"",'All Data'!$A:$A,0)),"-")
B45: SAP Planned HH/ac | C45: ==IFERROR(INDEX('All Data'!$AA:$AA,MATCH($H$29&"",'All Data'!$A:$A,0)),"-")
B47: INCOME | D47: POVERTY RATE | F47: UNEMPLOYMENT
C48: ==IFERROR(INDEX('All Data'!$AN:$AN,MATCH($H$29&"",'All Data'!$A:$A,0)),"-") | E48: ==IFERROR(INDEX('All Data'!$AL:$AL,MATCH($H$29&"",'All Data'!$A:$A,0)),"-") | G48: ==IFERROR(INDEX('All Data'!$AM:$AM,MATCH($H$29&"",'All Data'!$A:$A,0)),"-")
B49: =="Investment Likelihood: "&IFERROR(INDEX('All Data'!$AP:$AP,MATCH($H$29&"",'All Data'!$A:$A,0)),"—")
B50: Access to Opportunities (ATO) Composite Score /100 | F50: ==IFERROR(INDEX('All Data'!$AF:$AF,MATCH($H$29&"",'All Data'!$A:$A,0)),"-")
A54: =="03 — "&IFERROR(INDEX('All Data'!$C:$C,MATCH($H$54&"",'All Data'!$A:$A,0)),"")&" | GEOID "&$H$54&" | "&TEXT(IFERROR(INDEX('All Data'!$F:$F,MATCH($H$54&"",'All Data'!$A:$A,0)),0),"0")&" ac | "&IFERROR(INDEX('All Data'!$AP:$AP,MATCH($H$54&"",'All Data'!$A:$A,0)),"—") | H54: 49045131102
B55: TRACT PROFILE | D55: CENTERS & DISTRICTS | F55: HOUSING & DEMOGRAPHICS
B56: Population | C56: ==IFERROR(INDEX('All Data'!$D:$D,MATCH($H$54&"",'All Data'!$A:$A,0)),"-") | D56: WC MUorC % Total | E56: ==IFERROR(INDEX('All Data'!$J:$J,MATCH($H$54&"",'All Data'!$A:$A,0)),"-") | F56: Total Units | G56: ==IFERROR(INDEX('All Data'!$R:$R,MATCH($H$54&"",'All Data'!$A:$A,0)),"-")
B57: Households | C57: ==IFERROR(INDEX('All Data'!$E:$E,MATCH($H$54&"",'All Data'!$A:$A,0)),"-") | D57: Metropolitan Center | E57: ==IFERROR(INDEX('All Data'!$K:$K,MATCH($H$54&"",'All Data'!$A:$A,0)),"-") | F57: Residential Acres | G57: ==IFERROR(INDEX('All Data'!$S:$S,MATCH($H$54&"",'All Data'!$A:$A,0)),"-")
B58: Total Acres | C58: ==IFERROR(INDEX('All Data'!$F:$F,MATCH($H$54&"",'All Data'!$A:$A,0)),"-") | D58: Urban Center | E58: ==IFERROR(INDEX('All Data'!$L:$L,MATCH($H$54&"",'All Data'!$A:$A,0)),"-") | F58: SFD Acres | G58: ==IFERROR(INDEX('All Data'!$T:$T,MATCH($H$54&"",'All Data'!$A:$A,0)),"-")
B59: Developable Acres | C59: ==IFERROR(INDEX('All Data'!$G:$G,MATCH($H$54&"",'All Data'!$A:$A,0)),"-") | D59: City Center | E59: ==IFERROR(INDEX('All Data'!$M:$M,MATCH($H$54&"",'All Data'!$A:$A,0)),"-") | F59: MF / SFA Acres | G59: ==IFERROR(INDEX('All Data'!$U:$U,MATCH($H$54&"",'All Data'!$A:$A,0)),"-")
B60: OZ 1.0 Acres | C60: ==IFERROR(INDEX('All Data'!$H:$H,MATCH($H$54&"",'All Data'!$A:$A,0)),"-") | D60: Neighborhood Center | E60: ==IFERROR(INDEX('All Data'!$N:$N,MATCH($H$54&"",'All Data'!$A:$A,0)),"-") | F60: Poverty Rate | G60: ==IFERROR(INDEX('All Data'!$AL:$AL,MATCH($H$54&"",'All Data'!$A:$A,0)),"-")
B61: OZ 1.0 % of Tract | C61: ==IFERROR(INDEX('All Data'!$I:$I,MATCH($H$54&"",'All Data'!$A:$A,0)),"-") | D61: Employment District | E61: ==IFERROR(INDEX('All Data'!$O:$O,MATCH($H$54&"",'All Data'!$A:$A,0)),"-") | F61: Unemployment Rate | G61: ==IFERROR(INDEX('All Data'!$AM:$AM,MATCH($H$54&"",'All Data'!$A:$A,0)),"-")
D62: Industrial District | E62: ==IFERROR(INDEX('All Data'!$P:$P,MATCH($H$54&"",'All Data'!$A:$A,0)),"-") | F62: Median Family Income | G62: ==IFERROR(INDEX('All Data'!$AN:$AN,MATCH($H$54&"",'All Data'!$A:$A,0)),"-")
D63: Retail District | E63: ==IFERROR(INDEX('All Data'!$Q:$Q,MATCH($H$54&"",'All Data'!$A:$A,0)),"-")
B64: TRANSIT ACCESS | D64: AUTO ACCESS | F64: PROJECTED GROWTH 2027-37
B65: Rail / BRT Stops | C65: ==IFERROR(INDEX('All Data'!$V:$V,MATCH($H$54&"",'All Data'!$A:$A,0)),"-") | D65: Freeway Exits | E65: ==IFERROR(INDEX('All Data'!$AB:$AB,MATCH($H$54&"",'All Data'!$A:$A,0)),"-") | F65: Households Added | G65: ==IFERROR(INDEX('All Data'!$AG:$AG,MATCH($H$54&"",'All Data'!$A:$A,0)),"-")
B66: SAP Acres | C66: ==IFERROR(INDEX('All Data'!$W:$W,MATCH($H$54&"",'All Data'!$A:$A,0)),"-") | D66: Exit Distance (mi) | E66: ==IFERROR(INDEX('All Data'!$AC:$AC,MATCH($H$54&"",'All Data'!$A:$A,0)),"-") | F66: Population Added | G66: ==IFERROR(INDEX('All Data'!$AH:$AH,MATCH($H$54&"",'All Data'!$A:$A,0)),"-")
B67: SAP % of Tract | C67: ==IFERROR(INDEX('All Data'!$X:$X,MATCH($H$54&"",'All Data'!$A:$A,0)),"-") | D67: ATO Jobs (Auto) | E67: ==IFERROR(INDEX('All Data'!$AD:$AD,MATCH($H$54&"",'All Data'!$A:$A,0)),"-") | F67: Jobs Added | G67: ==IFERROR(INDEX('All Data'!$AI:$AI,MATCH($H$54&"",'All Data'!$A:$A,0)),"-")
B68: ATO Jobs (Transit) | C68: ==IFERROR(INDEX('All Data'!$Y:$Y,MATCH($H$54&"",'All Data'!$A:$A,0)),"-") | D68: ATO Households (Auto) | E68: ==IFERROR(INDEX('All Data'!$AE:$AE,MATCH($H$54&"",'All Data'!$A:$A,0)),"-") | F68: ERU Added | G68: ==IFERROR(INDEX('All Data'!$AJ:$AJ,MATCH($H$54&"",'All Data'!$A:$A,0)),"-")
B69: ATO Households (Transit) | C69: ==IFERROR(INDEX('All Data'!$Z:$Z,MATCH($H$54&"",'All Data'!$A:$A,0)),"-") | F69: ERU per Acre | G69: ==IFERROR(INDEX('All Data'!$AK:$AK,MATCH($H$54&"",'All Data'!$A:$A,0)),"-")
B70: SAP Planned HH/ac | C70: ==IFERROR(INDEX('All Data'!$AA:$AA,MATCH($H$54&"",'All Data'!$A:$A,0)),"-")
B72: INCOME | D72: POVERTY RATE | F72: UNEMPLOYMENT
C73: ==IFERROR(INDEX('All Data'!$AN:$AN,MATCH($H$54&"",'All Data'!$A:$A,0)),"-") | E73: ==IFERROR(INDEX('All Data'!$AL:$AL,MATCH($H$54&"",'All Data'!$A:$A,0)),"-") | G73: ==IFERROR(INDEX('All Data'!$AM:$AM,MATCH($H$54&"",'All Data'!$A:$A,0)),"-")
B74: =="Investment Likelihood: "&IFERROR(INDEX('All Data'!$AP:$AP,MATCH($H$54&"",'All Data'!$A:$A,0)),"—")
B75: Access to Opportunities (ATO) Composite Score /100 | F75: ==IFERROR(INDEX('All Data'!$AF:$AF,MATCH($H$54&"",'All Data'!$A:$A,0)),"-")

Sheet Utah County
A1: Utah County — OZ 2.0 Candidate Tracts — Detail
A2: WFRC & MAG Region | Generated June 01, 2026
A4: =="01 — "&IFERROR(INDEX('All Data'!$C:$C,MATCH($H$4&"",'All Data'!$A:$A,0)),"")&" | GEOID "&$H$4&" | "&TEXT(IFERROR(INDEX('All Data'!$F:$F,MATCH($H$4&"",'All Data'!$A:$A,0)),0),"0")&" ac | "&IFERROR(INDEX('All Data'!$AP:$AP,MATCH($H$4&"",'All Data'!$A:$A,0)),"—") | H4: 49049000511
B5: TRACT PROFILE | D5: CENTERS & DISTRICTS | F5: HOUSING & DEMOGRAPHICS
B6: Population | C6: ==IFERROR(INDEX('All Data'!$D:$D,MATCH($H$4&"",'All Data'!$A:$A,0)),"-") | D6: WC MUorC % Total | E6: ==IFERROR(INDEX('All Data'!$J:$J,MATCH($H$4&"",'All Data'!$A:$A,0)),"-") | F6: Total Units | G6: ==IFERROR(INDEX('All Data'!$R:$R,MATCH($H$4&"",'All Data'!$A:$A,0)),"-")
B7: Households | C7: ==IFERROR(INDEX('All Data'!$E:$E,MATCH($H$4&"",'All Data'!$A:$A,0)),"-") | D7: Metropolitan Center | E7: ==IFERROR(INDEX('All Data'!$K:$K,MATCH($H$4&"",'All Data'!$A:$A,0)),"-") | F7: Residential Acres | G7: ==IFERROR(INDEX('All Data'!$S:$S,MATCH($H$4&"",'All Data'!$A:$A,0)),"-")
B8: Total Acres | C8: ==IFERROR(INDEX('All Data'!$F:$F,MATCH($H$4&"",'All Data'!$A:$A,0)),"-") | D8: Urban Center | E8: ==IFERROR(INDEX('All Data'!$L:$L,MATCH($H$4&"",'All Data'!$A:$A,0)),"-") | F8: SFD Acres | G8: ==IFERROR(INDEX('All Data'!$T:$T,MATCH($H$4&"",'All Data'!$A:$A,0)),"-")
B9: Developable Acres | C9: ==IFERROR(INDEX('All Data'!$G:$G,MATCH($H$4&"",'All Data'!$A:$A,0)),"-") | D9: City Center | E9: ==IFERROR(INDEX('All Data'!$M:$M,MATCH($H$4&"",'All Data'!$A:$A,0)),"-") | F9: MF / SFA Acres | G9: ==IFERROR(INDEX('All Data'!$U:$U,MATCH($H$4&"",'All Data'!$A:$A,0)),"-")
B10: OZ 1.0 Acres | C10: ==IFERROR(INDEX('All Data'!$H:$H,MATCH($H$4&"",'All Data'!$A:$A,0)),"-") | D10: Neighborhood Center | E10: ==IFERROR(INDEX('All Data'!$N:$N,MATCH($H$4&"",'All Data'!$A:$A,0)),"-") | F10: Poverty Rate | G10: ==IFERROR(INDEX('All Data'!$AL:$AL,MATCH($H$4&"",'All Data'!$A:$A,0)),"-")
B11: OZ 1.0 % of Tract | C11: ==IFERROR(INDEX('All Data'!$I:$I,MATCH($H$4&"",'All Data'!$A:$A,0)),"-") | D11: Employment District | E11: ==IFERROR(INDEX('All Data'!$O:$O,MATCH($H$4&"",'All Data'!$A:$A,0)),"-") | F11: Unemployment Rate | G11: ==IFERROR(INDEX('All Data'!$AM:$AM,MATCH($H$4&"",'All Data'!$A:$A,0)),"-")
D12: Industrial District | E12: ==IFERROR(INDEX('All Data'!$P:$P,MATCH($H$4&"",'All Data'!$A:$A,0)),"-") | F12: Median Family Income | G12: ==IFERROR(INDEX('All Data'!$AN:$AN,MATCH($H$4&"",'All Data'!$A:$A,0)),"-")
D13: Retail District | E13: ==IFERROR(INDEX('All Data'!$Q:$Q,MATCH($H$4&"",'All Data'!$A:$A,0)),"-")
B14: TRANSIT ACCESS | D14: AUTO ACCESS | F14: PROJECTED GROWTH 2027-37
B15: Rail / BRT Stops | C15: ==IFERROR(INDEX('All Data'!$V:$V,MATCH($H$4&"",'All Data'!$A:$A,0)),"-") | D15: Freeway Exits | E15: ==IFERROR(INDEX('All Data'!$AB:$AB,MATCH($H$4&"",'All Data'!$A:$A,0)),"-") | F15: Households Added | G15: ==IFERROR(INDEX('All Data'!$AG:$AG,MATCH($H$4&"",'All Data'!$A:$A,0)),"-")
B16: SAP Acres | C16: ==IFERROR(INDEX('All Data'!$W:$W,MATCH($H$4&"",'All Data'!$A:$A,0)),"-") | D16: Exit Distance (mi) | E16: ==IFERROR(INDEX('All Data'!$AC:$AC,MATCH($H$4&"",'All Data'!$A:$A,0)),"-") | F16: Population Added | G16: ==IFERROR(INDEX('All Data'!$AH:$AH,MATCH($H$4&"",'All Data'!$A:$A,0)),"-")
B17: SAP % of Tract | C17: ==IFERROR(INDEX('All Data'!$X:$X,MATCH($H$4&"",'All Data'!$A:$A,0)),"-") | D17: ATO Jobs (Auto) | E17: ==IFERROR(INDEX('All Data'!$AD:$AD,MATCH($H$4&"",'All Data'!$A:$A,0)),"-") | F17: Jobs Added | G17: ==IFERROR(INDEX('All Data'!$AI:$AI,MATCH($H$4&"",'All Data'!$A:$A,0)),"-")
B18: ATO Jobs (Transit) | C18: ==IFERROR(INDEX('All Data'!$Y:$Y,MATCH($H$4&"",'All Data'!$A:$A,0)),"-") | D18: ATO Households (Auto) | E18: ==IFERROR(INDEX('All Data'!$AE:$AE,MATCH($H$4&"",'All Data'!$A:$A,0)),"-") | F18: ERU Added | G18: ==IFERROR(INDEX('All Data'!$AJ:$AJ,MATCH($H$4&"",'All Data'!$A:$A,0)),"-")
B19: ATO Households (Transit) | C19: ==IFERROR(INDEX('All Data'!$Z:$Z,MATCH($H$4&"",'All Data'!$A:$A,0)),"-") | F19: ERU per Acre | G19: ==IFERROR(INDEX('All Data'!$AK:$AK,MATCH($H$4&"",'All Data'!$A:$A,0)),"-")
B20: SAP Planned HH/ac | C20: ==IFERROR(INDEX('All Data'!$AA:$AA,MATCH($H$4&"",'All Data'!$A:$A,0)),"-")
B22: INCOME | D22: POVERTY RATE | F22: UNEMPLOYMENT
C23: ==IFERROR(INDEX('All Data'!$AN:$AN,MATCH($H$4&"",'All Data'!$A:$A,0)),"-") | E23: ==IFERROR(INDEX('All Data'!$AL:$AL,MATCH($H$4&"",'All Data'!$A:$A,0)),"-") | G23: ==IFERROR(INDEX('All Data'!$AM:$AM,MATCH($H$4&"",'All Data'!$A:$A,0)),"-")
B24: =="Investment Likelihood: "&IFERROR(INDEX('All Data'!$AP:$AP,MATCH($H$4&"",'All Data'!$A:$A,0)),"—")
B25: Access to Opportunities (ATO) Composite Score /100 | F25: ==IFERROR(INDEX('All Data'!$AF:$AF,MATCH($H$4&"",'All Data'!$A:$A,0)),"-")
A29: =="02 — "&IFERROR(INDEX('All Data'!$C:$C,MATCH($H$29&"",'All Data'!$A:$A,0)),"")&" | GEOID "&$H$29&" | "&TEXT(IFERROR(INDEX('All Data'!$F:$F,MATCH($H$29&"",'All Data'!$A:$A,0)),0),"0")&" ac | "&IFERROR(INDEX('All Data'!$AP:$AP,MATCH($H$29&"",'All Data'!$A:$A,0)),"—") | H29: 49049000801
B30: TRACT PROFILE | D30: CENTERS & DISTRICTS | F30: HOUSING & DEMOGRAPHICS
B31: Population | C31: ==IFERROR(INDEX('All Data'!$D:$D,MATCH($H$29&"",'All Data'!$A:$A,0)),"-") | D31: WC MUorC % Total | E31: ==IFERROR(INDEX('All Data'!$J:$J,MATCH($H$29&"",'All Data'!$A:$A,0)),"-") | F31: Total Units | G31: ==IFERROR(INDEX('All Data'!$R:$R,MATCH($H$29&"",'All Data'!$A:$A,0)),"-")
B32: Households | C32: ==IFERROR(INDEX('All Data'!$E:$E,MATCH($H$29&"",'All Data'!$A:$A,0)),"-") | D32: Metropolitan Center | E32: ==IFERROR(INDEX('All Data'!$K:$K,MATCH($H$29&"",'All Data'!$A:$A,0)),"-") | F32: Residential Acres | G32: ==IFERROR(INDEX('All Data'!$S:$S,MATCH($H$29&"",'All Data'!$A:$A,0)),"-")
B33: Total Acres | C33: ==IFERROR(INDEX('All Data'!$F:$F,MATCH($H$29&"",'All Data'!$A:$A,0)),"-") | D33: Urban Center | E33: ==IFERROR(INDEX('All Data'!$L:$L,MATCH($H$29&"",'All Data'!$A:$A,0)),"-") | F33: SFD Acres | G33: ==IFERROR(INDEX('All Data'!$T:$T,MATCH($H$29&"",'All Data'!$A:$A,0)),"-")
B34: Developable Acres | C34: ==IFERROR(INDEX('All Data'!$G:$G,MATCH($H$29&"",'All Data'!$A:$A,0)),"-") | D34: City Center | E34: ==IFERROR(INDEX('All Data'!$M:$M,MATCH($H$29&"",'All Data'!$A:$A,0)),"-") | F34: MF / SFA Acres | G34: ==IFERROR(INDEX('All Data'!$U:$U,MATCH($H$29&"",'All Data'!$A:$A,0)),"-")
B35: OZ 1.0 Acres | C35: ==IFERROR(INDEX('All Data'!$H:$H,MATCH($H$29&"",'All Data'!$A:$A,0)),"-") | D35: Neighborhood Center | E35: ==IFERROR(INDEX('All Data'!$N:$N,MATCH($H$29&"",'All Data'!$A:$A,0)),"-") | F35: Poverty Rate | G35: ==IFERROR(INDEX('All Data'!$AL:$AL,MATCH($H$29&"",'All Data'!$A:$A,0)),"-")
B36: OZ 1.0 % of Tract | C36: ==IFERROR(INDEX('All Data'!$I:$I,MATCH($H$29&"",'All Data'!$A:$A,0)),"-") | D36: Employment District | E36: ==IFERROR(INDEX('All Data'!$O:$O,MATCH($H$29&"",'All Data'!$A:$A,0)),"-") | F36: Unemployment Rate | G36: ==IFERROR(INDEX('All Data'!$AM:$AM,MATCH($H$29&"",'All Data'!$A:$A,0)),"-")
D37: Industrial District | E37: ==IFERROR(INDEX('All Data'!$P:$P,MATCH($H$29&"",'All Data'!$A:$A,0)),"-") | F37: Median Family Income | G37: ==IFERROR(INDEX('All Data'!$AN:$AN,MATCH($H$29&"",'All Data'!$A:$A,0)),"-")
D38: Retail District | E38: ==IFERROR(INDEX('All Data'!$Q:$Q,MATCH($H$29&"",'All Data'!$A:$A,0)),"-")
B39: TRANSIT ACCESS | D39: AUTO ACCESS | F39: PROJECTED GROWTH 2027-37
B40: Rail / BRT Stops | C40: ==IFERROR(INDEX('All Data'!$V:$V,MATCH($H$29&"",'All Data'!$A:$A,0)),"-") | D40: Freeway Exits | E40: ==IFERROR(INDEX('All Data'!$AB:$AB,MATCH($H$29&"",'All Data'!$A:$A,0)),"-") | F40: Households Added | G40: ==IFERROR(INDEX('All Data'!$AG:$AG,MATCH($H$29&"",'All Data'!$A:$A,0)),"-")
B41: SAP Acres | C41: ==IFERROR(INDEX('All Data'!$W:$W,MATCH($H$29&"",'All Data'!$A:$A,0)),"-") | D41: Exit Distance (mi) | E41: ==IFERROR(INDEX('All Data'!$AC:$AC,MATCH($H$29&"",'All Data'!$A:$A,0)),"-") | F41: Population Added | G41: ==IFERROR(INDEX('All Data'!$AH:$AH,MATCH($H$29&"",'All Data'!$A:$A,0)),"-")
B42: SAP % of Tract | C42: ==IFERROR(INDEX('All Data'!$X:$X,MATCH($H$29&"",'All Data'!$A:$A,0)),"-") | D42: ATO Jobs (Auto) | E42: ==IFERROR(INDEX('All Data'!$AD:$AD,MATCH($H$29&"",'All Data'!$A:$A,0)),"-") | F42: Jobs Added | G42: ==IFERROR(INDEX('All Data'!$AI:$AI,MATCH($H$29&"",'All Data'!$A:$A,0)),"-")
B43: ATO Jobs (Transit) | C43: ==IFERROR(INDEX('All Data'!$Y:$Y,MATCH($H$29&"",'All Data'!$A:$A,0)),"-") | D43: ATO Households (Auto) | E43: ==IFERROR(INDEX('All Data'!$AE:$AE,MATCH($H$29&"",'All Data'!$A:$A,0)),"-") | F43: ERU Added | G43: ==IFERROR(INDEX('All Data'!$AJ:$AJ,MATCH($H$29&"",'All Data'!$A:$A,0)),"-")
B44: ATO Households (Transit) | C44: ==IFERROR(INDEX('All Data'!$Z:$Z,MATCH($H$29&"",'All Data'!$A:$A,0)),"-") | F44: ERU per Acre | G44: ==IFERROR(INDEX('All Data'!$AK:$AK,MATCH($H$29&"",'All Data'!$A:$A,0)),"-")
B45: SAP Planned HH/ac | C45: ==IFERROR(INDEX('All Data'!$AA:$AA,MATCH($H$29&"",'All Data'!$A:$A,0)),"-")
B47: INCOME | D47: POVERTY RATE | F47: UNEMPLOYMENT
C48: ==IFERROR(INDEX('All Data'!$AN:$AN,MATCH($H$29&"",'All Data'!$A:$A,0)),"-") | E48: ==IFERROR(INDEX('All Data'!$AL:$AL,MATCH($H$29&"",'All Data'!$A:$A,0)),"-") | G48: ==IFERROR(INDEX('All Data'!$AM:$AM,MATCH($H$29&"",'All Data'!$A:$A,0)),"-")
B49: =="Investment Likelihood: "&IFERROR(INDEX('All Data'!$AP:$AP,MATCH($H$29&"",'All Data'!$A:$A,0)),"—")
B50: Access to Opportunities (ATO) Composite Score /100 | F50: ==IFERROR(INDEX('All Data'!$AF:$AF,MATCH($H$29&"",'All Data'!$A:$A,0)),"-")
A54: =="03 — "&IFERROR(INDEX('All Data'!$C:$C,MATCH($H$54&"",'All Data'!$A:$A,0)),"")&" | GEOID "&$H$54&" | "&TEXT(IFERROR(INDEX('All Data'!$F:$F,MATCH($H$54&"",'All Data'!$A:$A,0)),0),"0")&" ac | "&IFERROR(INDEX('All Data'!$AP:$AP,MATCH($H$54&"",'All Data'!$A:$A,0)),"—") | H54: 49049000803
B55: TRACT PROFILE | D55: CENTERS & DISTRICTS | F55: HOUSING & DEMOGRAPHICS
B56: Population | C56: ==IFERROR(INDEX('All Data'!$D:$D,MATCH($H$54&"",'All Data'!$A:$A,0)),"-") | D56: WC MUorC % Total | E56: ==IFERROR(INDEX('All Data'!$J:$J,MATCH($H$54&"",'All Data'!$A:$A,0)),"-") | F56: Total Units | G56: ==IFERROR(INDEX('All Data'!$R:$R,MATCH($H$54&"",'All Data'!$A:$A,0)),"-")
B57: Households | C57: ==IFERROR(INDEX('All Data'!$E:$E,MATCH($H$54&"",'All Data'!$A:$A,0)),"-") | D57: Metropolitan Center | E57: ==IFERROR(INDEX('All Data'!$K:$K,MATCH($H$54&"",'All Data'!$A:$A,0)),"-") | F57: Residential Acres | G57: ==IFERROR(INDEX('All Data'!$S:$S,MATCH($H$54&"",'All Data'!$A:$A,0)),"-")
B58: Total Acres | C58: ==IFERROR(INDEX('All Data'!$F:$F,MATCH($H$54&"",'All Data'!$A:$A,0)),"-") | D58: Urban Center | E58: ==IFERROR(INDEX('All Data'!$L:$L,MATCH($H$54&"",'All Data'!$A:$A,0)),"-") | F58: SFD Acres | G58: ==IFERROR(INDEX('All Data'!$T:$T,MATCH($H$54&"",'All Data'!$A:$A,0)),"-")
B59: Developable Acres | C59: ==IFERROR(INDEX('All Data'!$G:$G,MATCH($H$54&"",'All Data'!$A:$A,0)),"-") | D59: City Center | E59: ==IFERROR(INDEX('All Data'!$M:$M,MATCH($H$54&"",'All Data'!$A:$A,0)),"-") | F59: MF / SFA Acres | G59: ==IFERROR(INDEX('All Data'!$U:$U,MATCH($H$54&"",'All Data'!$A:$A,0)),"-")
B60: OZ 1.0 Acres | C60: ==IFERROR(INDEX('All Data'!$H:$H,MATCH($H$54&"",'All Data'!$A:$A,0)),"-") | D60: Neighborhood Center | E60: ==IFERROR(INDEX('All Data'!$N:$N,MATCH($H$54&"",'All Data'!$A:$A,0)),"-") | F60: Poverty Rate | G60: ==IFERROR(INDEX('All Data'!$AL:$AL,MATCH($H$54&"",'All Data'!$A:$A,0)),"-")
B61: OZ 1.0 % of Tract | C61: ==IFERROR(INDEX('All Data'!$I:$I,MATCH($H$54&"",'All Data'!$A:$A,0)),"-") | D61: Employment District | E61: ==IFERROR(INDEX('All Data'!$O:$O,MATCH($H$54&"",'All Data'!$A:$A,0)),"-") | F61: Unemployment Rate | G61: ==IFERROR(INDEX('All Data'!$AM:$AM,MATCH($H$54&"",'All Data'!$A:$A,0)),"-")
D62: Industrial District | E62: ==IFERROR(INDEX('All Data'!$P:$P,MATCH($H$54&"",'All Data'!$A:$A,0)),"-") | F62: Median Family Income | G62: ==IFERROR(INDEX('All Data'!$AN:$AN,MATCH($H$54&"",'All Data'!$A:$A,0)),"-")
D63: Retail District | E63: ==IFERROR(INDEX('All Data'!$Q:$Q,MATCH($H$54&"",'All Data'!$A:$A,0)),"-")
B64: TRANSIT ACCESS | D64: AUTO ACCESS | F64: PROJECTED GROWTH 2027-37
B65: Rail / BRT Stops | C65: ==IFERROR(INDEX('All Data'!$V:$V,MATCH($H$54&"",'All Data'!$A:$A,0)),"-") | D65: Freeway Exits | E65: ==IFERROR(INDEX('All Data'!$AB:$AB,MATCH($H$54&"",'All Data'!$A:$A,0)),"-") | F65: Households Added | G65: ==IFERROR(INDEX('All Data'!$AG:$AG,MATCH($H$54&"",'All Data'!$A:$A,0)),"-")
B66: SAP Acres | C66: ==IFERROR(INDEX('All Data'!$W:$W,MATCH($H$54&"",'All Data'!$A:$A,0)),"-") | D66: Exit Distance (mi) | E66: ==IFERROR(INDEX('All Data'!$AC:$AC,MATCH($H$54&"",'All Data'!$A:$A,0)),"-") | F66: Population Added | G66: ==IFERROR(INDEX('All Data'!$AH:$AH,MATCH($H$54&"",'All Data'!$A:$A,0)),"-")
B67: SAP % of Tract | C67: ==IFERROR(INDEX('All Data'!$X:$X,MATCH($H$54&"",'All Data'!$A:$A,0)),"-") | D67: ATO Jobs (Auto) | E67: ==IFERROR(INDEX('All Data'!$AD:$AD,MATCH($H$54&"",'All Data'!$A:$A,0)),"-") | F67: Jobs Added | G67: ==IFERROR(INDEX('All Data'!$AI:$AI,MATCH($H$54&"",'All Data'!$A:$A,0)),"-")
B68: ATO Jobs (Transit) | C68: ==IFERROR(INDEX('All Data'!$Y:$Y,MATCH($H$54&"",'All Data'!$A:$A,0)),"-") | D68: ATO Households (Auto) | E68: ==IFERROR(INDEX('All Data'!$AE:$AE,MATCH($H$54&"",'All Data'!$A:$A,0)),"-") | F68: ERU Added | G68: ==IFERROR(INDEX('All Data'!$AJ:$AJ,MATCH($H$54&"",'All Data'!$A:$A,0)),"-")
B69: ATO Households (Transit) | C69: ==IFERROR(INDEX('All Data'!$Z:$Z,MATCH($H$54&"",'All Data'!$A:$A,0)),"-") | F69: ERU per Acre | G69: ==IFERROR(INDEX('All Data'!$AK:$AK,MATCH($H$54&"",'All Data'!$A:$A,0)),"-")
B70: SAP Planned HH/ac | C70: ==IFERROR(INDEX('All Data'!$AA:$AA,MATCH($H$54&"",'All Data'!$A:$A,0)),"-")
B72: INCOME | D72: POVERTY RATE | F72: UNEMPLOYMENT
C73: ==IFERROR(INDEX('All Data'!$AN:$AN,MATCH($H$54&"",'All Data'!$A:$A,0)),"-") | E73: ==IFERROR(INDEX('All Data'!$AL:$AL,MATCH($H$54&"",'All Data'!$A:$A,0)),"-") | G73: ==IFERROR(INDEX('All Data'!$AM:$AM,MATCH($H$54&"",'All Data'!$A:$A,0)),"-")
B74: =="Investment Likelihood: "&IFERROR(INDEX('All Data'!$AP:$AP,MATCH($H$54&"",'All Data'!$A:$A,0)),"—")
B75: Access to Opportunities (ATO) Composite Score /100 | F75: ==IFERROR(INDEX('All Data'!$AF:$AF,MATCH($H$54&"",'All Data'!$A:$A,0)),"-")
A79: =="04 — "&IFERROR(INDEX('All Data'!$C:$C,MATCH($H$79&"",'All Data'!$A:$A,0)),"")&" | GEOID "&$H$79&" | "&TEXT(IFERROR(INDEX('All Data'!$F:$F,MATCH($H$79&"",'All Data'!$A:$A,0)),0),"0")&" ac | "&IFERROR(INDEX('All Data'!$AP:$AP,MATCH($H$79&"",'All Data'!$A:$A,0)),"—") | H79: 49049000804
B80: TRACT PROFILE | D80: CENTERS & DISTRICTS | F80: HOUSING & DEMOGRAPHICS
B81: Population | C81: ==IFERROR(INDEX('All Data'!$D:$D,MATCH($H$79&"",'All Data'!$A:$A,0)),"-") | D81: WC MUorC % Total | E81: ==IFERROR(INDEX('All Data'!$J:$J,MATCH($H$79&"",'All Data'!$A:$A,0)),"-") | F81: Total Units | G81: ==IFERROR(INDEX('All Data'!$R:$R,MATCH($H$79&"",'All Data'!$A:$A,0)),"-")
B82: Households | C82: ==IFERROR(INDEX('All Data'!$E:$E,MATCH($H$79&"",'All Data'!$A:$A,0)),"-") | D82: Metropolitan Center | E82: ==IFERROR(INDEX('All Data'!$K:$K,MATCH($H$79&"",'All Data'!$A:$A,0)),"-") | F82: Residential Acres | G82: ==IFERROR(INDEX('All Data'!$S:$S,MATCH($H$79&"",'All Data'!$A:$A,0)),"-")
B83: Total Acres | C83: ==IFERROR(INDEX('All Data'!$F:$F,MATCH($H$79&"",'All Data'!$A:$A,0)),"-") | D83: Urban Center | E83: ==IFERROR(INDEX('All Data'!$L:$L,MATCH($H$79&"",'All Data'!$A:$A,0)),"-") | F83: SFD Acres | G83: ==IFERROR(INDEX('All Data'!$T:$T,MATCH($H$79&"",'All Data'!$A:$A,0)),"-")
B84: Developable Acres | C84: ==IFERROR(INDEX('All Data'!$G:$G,MATCH($H$79&"",'All Data'!$A:$A,0)),"-") | D84: City Center | E84: ==IFERROR(INDEX('All Data'!$M:$M,MATCH($H$79&"",'All Data'!$A:$A,0)),"-") | F84: MF / SFA Acres | G84: ==IFERROR(INDEX('All Data'!$U:$U,MATCH($H$79&"",'All Data'!$A:$A,0)),"-")
B85: OZ 1.0 Acres | C85: ==IFERROR(INDEX('All Data'!$H:$H,MATCH($H$79&"",'All Data'!$A:$A,0)),"-") | D85: Neighborhood Center | E85: ==IFERROR(INDEX('All Data'!$N:$N,MATCH($H$79&"",'All Data'!$A:$A,0)),"-") | F85: Poverty Rate | G85: ==IFERROR(INDEX('All Data'!$AL:$AL,MATCH($H$79&"",'All Data'!$A:$A,0)),"-")
B86: OZ 1.0 % of Tract | C86: ==IFERROR(INDEX('All Data'!$I:$I,MATCH($H$79&"",'All Data'!$A:$A,0)),"-") | D86: Employment District | E86: ==IFERROR(INDEX('All Data'!$O:$O,MATCH($H$79&"",'All Data'!$A:$A,0)),"-") | F86: Unemployment Rate | G86: ==IFERROR(INDEX('All Data'!$AM:$AM,MATCH($H$79&"",'All Data'!$A:$A,0)),"-")
D87: Industrial District | E87: ==IFERROR(INDEX('All Data'!$P:$P,MATCH($H$79&"",'All Data'!$A:$A,0)),"-") | F87: Median Family Income | G87: ==IFERROR(INDEX('All Data'!$AN:$AN,MATCH($H$79&"",'All Data'!$A:$A,0)),"-")
D88: Retail District | E88: ==IFERROR(INDEX('All Data'!$Q:$Q,MATCH($H$79&"",'All Data'!$A:$A,0)),"-")
B89: TRANSIT ACCESS | D89: AUTO ACCESS | F89: PROJECTED GROWTH 2027-37
B90: Rail / BRT Stops | C90: ==IFERROR(INDEX('All Data'!$V:$V,MATCH($H$79&"",'All Data'!$A:$A,0)),"-") | D90: Freeway Exits | E90: ==IFERROR(INDEX('All Data'!$AB:$AB,MATCH($H$79&"",'All Data'!$A:$A,0)),"-") | F90: Households Added | G90: ==IFERROR(INDEX('All Data'!$AG:$AG,MATCH($H$79&"",'All Data'!$A:$A,0)),"-")
B91: SAP Acres | C91: ==IFERROR(INDEX('All Data'!$W:$W,MATCH($H$79&"",'All Data'!$A:$A,0)),"-") | D91: Exit Distance (mi) | E91: ==IFERROR(INDEX('All Data'!$AC:$AC,MATCH($H$79&"",'All Data'!$A:$A,0)),"-") | F91: Population Added | G91: ==IFERROR(INDEX('All Data'!$AH:$AH,MATCH($H$79&"",'All Data'!$A:$A,0)),"-")
B92: SAP % of Tract | C92: ==IFERROR(INDEX('All Data'!$X:$X,MATCH($H$79&"",'All Data'!$A:$A,0)),"-") | D92: ATO Jobs (Auto) | E92: ==IFERROR(INDEX('All Data'!$AD:$AD,MATCH($H$79&"",'All Data'!$A:$A,0)),"-") | F92: Jobs Added | G92: ==IFERROR(INDEX('All Data'!$AI:$AI,MATCH($H$79&"",'All Data'!$A:$A,0)),"-")
B93: ATO Jobs (Transit) | C93: ==IFERROR(INDEX('All Data'!$Y:$Y,MATCH($H$79&"",'All Data'!$A:$A,0)),"-") | D93: ATO Households (Auto) | E93: ==IFERROR(INDEX('All Data'!$AE:$AE,MATCH($H$79&"",'All Data'!$A:$A,0)),"-") | F93: ERU Added | G93: ==IFERROR(INDEX('All Data'!$AJ:$AJ,MATCH($H$79&"",'All Data'!$A:$A,0)),"-")
B94: ATO Households (Transit) | C94: ==IFERROR(INDEX('All Data'!$Z:$Z,MATCH($H$79&"",'All Data'!$A:$A,0)),"-") | F94: ERU per Acre | G94: ==IFERROR(INDEX('All Data'!$AK:$AK,MATCH($H$79&"",'All Data'!$A:$A,0)),"-")
B95: SAP Planned HH/ac | C95: ==IFERROR(INDEX('All Data'!$AA:$AA,MATCH($H$79&"",'All Data'!$A:$A,0)),"-")
B97: INCOME | D97: POVERTY RATE | F97: UNEMPLOYMENT
C98: ==IFERROR(INDEX('All Data'!$AN:$AN,MATCH($H$79&"",'All Data'!$A:$A,0)),"-") | E98: ==IFERROR(INDEX('All Data'!$AL:$AL,MATCH($H$79&"",'All Data'!$A:$A,0)),"-") | G98: ==IFERROR(INDEX('All Data'!$AM:$AM,MATCH($H$79&"",'All Data'!$A:$A,0)),"-")
B99: =="Investment Likelihood: "&IFERROR(INDEX('All Data'!$AP:$AP,MATCH($H$79&"",'All Data'!$A:$A,0)),"—")
B100: Access to Opportunities (ATO) Composite Score /100 | F100: ==IFERROR(INDEX('All Data'!$AF:$AF,MATCH($H$79&"",'All Data'!$A:$A,0)),"-")
A104: =="05 — "&IFERROR(INDEX('All Data'!$C:$C,MATCH($H$104&"",'All Data'!$A:$A,0)),"")&" | GEOID "&$H$104&" | "&TEXT(IFERROR(INDEX('All Data'!$F:$F,MATCH($H$104&"",'All Data'!$A:$A,0)),0),"0")&" ac | "&IFERROR(INDEX('All Data'!$AP:$AP,MATCH($H$104&"",'All Data'!$A:$A,0)),"—") | H104: 49049000901
B105: TRACT PROFILE | D105: CENTERS & DISTRICTS | F105: HOUSING & DEMOGRAPHICS
B106: Population | C106: ==IFERROR(INDEX('All Data'!$D:$D,MATCH($H$104&"",'All Data'!$A:$A,0)),"-") | D106: WC MUorC % Total | E106: ==IFERROR(INDEX('All Data'!$J:$J,MATCH($H$104&"",'All Data'!$A:$A,0)),"-") | F106: Total Units | G106: ==IFERROR(INDEX('All Data'!$R:$R,MATCH($H$104&"",'All Data'!$A:$A,0)),"-")
B107: Households | C107: ==IFERROR(INDEX('All Data'!$E:$E,MATCH($H$104&"",'All Data'!$A:$A,0)),"-") | D107: Metropolitan Center | E107: ==IFERROR(INDEX('All Data'!$K:$K,MATCH($H$104&"",'All Data'!$A:$A,0)),"-") | F107: Residential Acres | G107: ==IFERROR(INDEX('All Data'!$S:$S,MATCH($H$104&"",'All Data'!$A:$A,0)),"-")
B108: Total Acres | C108: ==IFERROR(INDEX('All Data'!$F:$F,MATCH($H$104&"",'All Data'!$A:$A,0)),"-") | D108: Urban Center | E108: ==IFERROR(INDEX('All Data'!$L:$L,MATCH($H$104&"",'All Data'!$A:$A,0)),"-") | F108: SFD Acres | G108: ==IFERROR(INDEX('All Data'!$T:$T,MATCH($H$104&"",'All Data'!$A:$A,0)),"-")
B109: Developable Acres | C109: ==IFERROR(INDEX('All Data'!$G:$G,MATCH($H$104&"",'All Data'!$A:$A,0)),"-") | D109: City Center | E109: ==IFERROR(INDEX('All Data'!$M:$M,MATCH($H$104&"",'All Data'!$A:$A,0)),"-") | F109: MF / SFA Acres | G109: ==IFERROR(INDEX('All Data'!$U:$U,MATCH($H$104&"",'All Data'!$A:$A,0)),"-")
B110: OZ 1.0 Acres | C110: ==IFERROR(INDEX('All Data'!$H:$H,MATCH($H$104&"",'All Data'!$A:$A,0)),"-") | D110: Neighborhood Center | E110: ==IFERROR(INDEX('All Data'!$N:$N,MATCH($H$104&"",'All Data'!$A:$A,0)),"-") | F110: Poverty Rate | G110: ==IFERROR(INDEX('All Data'!$AL:$AL,MATCH($H$104&"",'All Data'!$A:$A,0)),"-")
B111: OZ 1.0 % of Tract | C111: ==IFERROR(INDEX('All Data'!$I:$I,MATCH($H$104&"",'All Data'!$A:$A,0)),"-") | D111: Employment District | E111: ==IFERROR(INDEX('All Data'!$O:$O,MATCH($H$104&"",'All Data'!$A:$A,0)),"-") | F111: Unemployment Rate | G111: ==IFERROR(INDEX('All Data'!$AM:$AM,MATCH($H$104&"",'All Data'!$A:$A,0)),"-")
D112: Industrial District | E112: ==IFERROR(INDEX('All Data'!$P:$P,MATCH($H$104&"",'All Data'!$A:$A,0)),"-") | F112: Median Family Income | G112: ==IFERROR(INDEX('All Data'!$AN:$AN,MATCH($H$104&"",'All Data'!$A:$A,0)),"-")
D113: Retail District | E113: ==IFERROR(INDEX('All Data'!$Q:$Q,MATCH($H$104&"",'All Data'!$A:$A,0)),"-")
B114: TRANSIT ACCESS | D114: AUTO ACCESS | F114: PROJECTED GROWTH 2027-37
B115: Rail / BRT Stops | C115: ==IFERROR(INDEX('All Data'!$V:$V,MATCH($H$104&"",'All Data'!$A:$A,0)),"-") | D115: Freeway Exits | E115: ==IFERROR(INDEX('All Data'!$AB:$AB,MATCH($H$104&"",'All Data'!$A:$A,0)),"-") | F115: Households Added | G115: ==IFERROR(INDEX('All Data'!$AG:$AG,MATCH($H$104&"",'All Data'!$A:$A,0)),"-")
B116: SAP Acres | C116: ==IFERROR(INDEX('All Data'!$W:$W,MATCH($H$104&"",'All Data'!$A:$A,0)),"-") | D116: Exit Distance (mi) | E116: ==IFERROR(INDEX('All Data'!$AC:$AC,MATCH($H$104&"",'All Data'!$A:$A,0)),"-") | F116: Population Added | G116: ==IFERROR(INDEX('All Data'!$AH:$AH,MATCH($H$104&"",'All Data'!$A:$A,0)),"-")
B117: SAP % of Tract | C117: ==IFERROR(INDEX('All Data'!$X:$X,MATCH($H$104&"",'All Data'!$A:$A,0)),"-") | D117: ATO Jobs (Auto) | E117: ==IFERROR(INDEX('All Data'!$AD:$AD,MATCH($H$104&"",'All Data'!$A:$A,0)),"-") | F117: Jobs Added | G117: ==IFERROR(INDEX('All Data'!$AI:$AI,MATCH($H$104&"",'All Data'!$A:$A,0)),"-")
...

Sheet All Data
A1: OZ 2.0 Candidate Tracts — All Data | June 01, 2026
A2: GEOID | B2: County | C2: Tract | D2: Population | E2: Households | F2: Total Acres | G2: Dev Acres | H2: OZ 1.0 Acres | I2: OZ 1.0 % | J2: WC MUorC % | K2: Metropolitan Center % | L2: Urban Center % | M2: City Center % | N2: Neighborhood Center % | O2: Employment District % | P2: Industrial District % | Q2: Retail District % | R2: Total Units | S2: Residential Acres | T2: SFD Acres | U2: MF/SFA Acres | V2: Rail/BRT Stops | W2: SAP Acres | X2: SAP % | Y2: ATO Jobs Transit | Z2: ATO HH Transit | AA2: SAP HH/ac Planned | AB2: Freeway Exits | AC2: Exit Distance (mi) | AD2: ATO Jobs Auto | AE2: ATO HH Auto | AF2: ATO Composite /100 | AG2: HH Added | AH2: Pop Added | AI2: Jobs Added | AJ2: ERU Added | AK2: ERU/ac | AL2: Poverty Rate | AM2: Unemployment Rate | AN2: Median Family Income | AO2: OZ Tool Classification | AP2: Likelihood (Short)
A3: 49003960601 | B3: Box Elder | C3: Tract 9606.01 | D3: 3776 | E3: 1400 | F3: 541.35146 | G3: 541.35085 | H3: 535.90831 | I3: ==IFERROR(H3/F3*100,0) | J3: ==K3+L3+M3 | K3: 0 | L3: 0 | M3: 4.4 | N3: 5.1 | O3: 0 | P3: 0 | Q3: 0 | R3: 1311 | S3: 313.12 | T3: 300.15 | U3: 12.97 | V3: 0 | W3: 0 | X3: ==IFERROR(W3/F3*100,0) | Y3: 2648.3742 | Z3: 1763.7524 | AA3: #N/A | AB3: 0 | AC3: 0.93748801 | AD3: 66645.151 | AE3: 39810.292 | AF3: 1.5925411 | AG3: 37 | AH3: -175 | AI3: 53 | AJ3: ==AG3+AI3*0.4 | AK3: ==IFERROR(AJ3/G3,0) | AL3: 12.61% | AM3: 3.02% | AN3: 76000 | AO3: More likely to attract OZ investment, with larger impact | AP3: More Likely
A4: 49003960702 | B4: Box Elder | C4: Tract 9607.02 | D4: 2696 | E4: 1019 | F4: 773.98059 | G4: 769.16491 | H4: 0.39185187 | I4: ==IFERROR(H4/F4*100,0) | J4: ==K4+L4+M4 | K4: 0 | L4: 0 | M4: 0.6 | N4: 0 | O4: 0 | P4: 0 | Q4: 0 | R4: 960 | S4: 176.87 | T4: 134.24 | U4: 42.63 | V4: 0 | W4: 0 | X4: ==IFERROR(W4/F4*100,0) | Y4: 1754.2866 | Z4: 1161.3127 | AA4: #N/A | AB4: 0 | AC4: 0.11208845 | AD4: 73099.739 | AE4: 43836.828 | AF4: 1.7051365 | AG4: 47 | AH4: -127 | AI4: 62 | AJ4: ==AG4+AI4*0.4 | AK4: ==IFERROR(AJ4/G4,0) | AL4: 17.03% | AM4: 2.87% | AN4: 71630 | AO4: Less likely to attract OZ investment | AP4: Less Likely
A5: 49057200202 | B5: Weber | C5: Tract 2002.02 | D5: 3984 | E5: 1755 | F5: 502.20932 | G5: 502.20876 | H5: 0 | I5: ==IFERROR(H5/F5*100,0) | J5: ==K5+L5+M5 | K5: 0 | L5: 0 | M5: 13.1 | N5: 0 | O5: 0 | P5: 0 | Q5: 0 | R5: 1683 | S5: 204.58 | T5: 145.78 | U5: 58.8 | V5: 0 | W5: 0 | X5: ==IFERROR(W5/F5*100,0) | Y5: 15509.393 | Z5: 8930.8502 | AA5: #N/A | AB5: 0 | AC5: 2.451765 | AD5: 150870.11 | AE5: 90850.635 | AF5: 20.966577 | AG5: 208 | AH5: 296 | AI5: 47 | AJ5: ==AG5+AI5*0.4 | AK5: ==IFERROR(AJ5/G5,0) | AL5: 9.73% | AM5: 4.15% | AN5: 73348 | AO5: More likely to attract OZ investment, with larger impact | AP5: More Likely
A6: 49057200302 | B6: Weber | C6: Tract 2003.02 | D6: 3824 | E6: 1145 | F6: 1949.5127 | G6: 1945.2813 | H6: 0.35179647 | I6: ==IFERROR(H6/F6*100,0) | J6: ==K6+L6+M6 | K6: 0 | L6: 0 | M6: 0.4 | N6: 0.3 | O6: 0 | P6: 71.9 | Q6: 0 | R6: 1239 | S6: 170.5 | T6: 80.43 | U6: 90.07 | V6: 0 | W6: 0 | X6: ==IFERROR(W6/F6*100,0) | Y6: 7748.3376 | Z6: 3555.7269 | AA6: #N/A | AB6: 0 | AC6: 0.33417474 | AD6: 164351.99 | AE6: 97013.996 | AF6: 16.148418 | AG6: 66 | AH6: -35 | AI6: 28 | AJ6: ==AG6+AI6*0.4 | AK6: ==IFERROR(AJ6/G6,0) | AL6: 22.86% | AM6: 0% | AN6: 63521 | AO6: More likely to attract OZ investment, with larger impact | AP6: More Likely
A7: 49057200400 | B7: Weber | C7: Tract 2004 | D7: 2091 | E7: 754 | F7: 585.35187 | G7: 585.34542 | H7: 584.53707 | I7: ==IFERROR(H7/F7*100,0) | J7: ==K7+L7+M7 | K7: 9.2 | L7: 7.3 | M7: 13.3 | N7: 0 | O7: 0 | P7: 28.2 | Q7: 0 | R7: 1197 | S7: 124.15 | T7: 87.02 | U7: 37.13 | V7: 0 | W7: 0 | X7: ==IFERROR(W7/F7*100,0) | Y7: 20959.135 | Z7: 8978.8626 | AA7: #N/A | AB7: 0 | AC7: 1.1947084 | AD7: 165045.56 | AE7: 95715.751 | AF7: 23.499329 | AG7: 127 | AH7: 191 | AI7: 157 | AJ7: ==AG7+AI7*0.4 | AK7: ==IFERROR(AJ7/G7,0) | AL7: 33.01% | AM7: 11.05% | AN7: 43686 | AO7: Likely to attract capital even without OZ designation | AP7: Likely to Attract Investment
A8: 49057200500 | B8: Weber | C8: Tract 2005 | D8: 6124 | E8: 2624 | F8: 773.17829 | G8: 772.86555 | H8: 0.74903723 | I8: ==IFERROR(H8/F8*100,0) | J8: ==K8+L8+M8 | K8: 0 | L8: 0 | M8: 9.2 | N8: 1 | O8: 0 | P8: 0 | Q8: 0 | R8: 2684 | S8: 448.54 | T8: 325.21 | U8: 123.33 | V8: 0 | W8: 0 | X8: ==IFERROR(W8/F8*100,0) | Y8: 14495.18 | Z8: 8042.2307 | AA8: #N/A | AB8: 0 | AC8: 2.0685155 | AD8: 161135.86 | AE8: 95195.181 | AF8: 21.039135 | AG8: 227 | AH8: 211 | AI8: 56 | AJ8: ==AG8+AI8*0.4 | AK8: ==IFERROR(AJ8/G8,0) | AL8: 21.77% | AM8: 1.86% | AN8: 67294 | AO8: More likely to attract OZ investment, with larger impact | AP8: More Likely
A9: 49057200800 | B9: Weber | C9: Tract 2008 | D9: 4557 | E9: 1795 | F9: 446.58598 | G9: 446.55409 | H9: 443.84439 | I9: ==IFERROR(H9/F9*100,0) | J9: ==K9+L9+M9 | K9: 0 | L9: 0 | M9: 4.2 | N9: 2.3 | O9: 0 | P9: 0 | Q9: 0 | R9: 2030 | S9: 220.97 | T9: 188.98 | U9: 31.99 | V9: 3 | W9: 0 | X9: ==IFERROR(W9/F9*100,0) | Y9: 15286.151 | Z9: 8401.5091 | AA9: #N/A | AB9: 0 | AC9: 2.0195812 | AD9: 162047.88 | AE9: 94380.01 | AF9: 21.460885 | AG9: 74 | AH9: -46 | AI9: 19 | AJ9: ==AG9+AI9*0.4 | AK9: ==IFERROR(AJ9/G9,0) | AL9: 14.66% | AM9: 5.85% | AN9: 76932 | AO9: More likely to attract OZ investment, with larger impact | AP9: More Likely
A10: 49057200900 | B10: Weber | C10: Tract 2009 | D10: 3758 | E10: 1989 | F10: 395.632 | G10: 395.63156 | H10: 394.53756 | I10: ==IFERROR(H10/F10*100,0) | J10: ==K10+L10+M10 | K10: 31.9 | L10: 0 | M10: 2.8 | N10: 0 | O10: 0 | P10: 0 | Q10: 0 | R10: 2184 | S10: 130.11 | T10: 70.68 | U10: 59.43 | V10: 3 | W10: 0 | X10: ==IFERROR(W10/F10*100,0) | Y10: 23717.701 | Z10: 10608.606 | AA10: #N/A | AB10: 0 | AC10: 1.6413425 | AD10: 170095.66 | AE10: 98218.67 | AF10: 26.042952 | AG10: 146 | AH10: 95 | AI10: 131 | AJ10: ==AG10+AI10*0.4 | AK10: ==IFERROR(AJ10/G10,0) | AL10: 18.59% | AM10: 2.99% | AN10: 57147 | AO10: More likely to attract OZ investment, with larger impact | AP10: More Likely
A11: 49057201100 | B11: Weber | C11: Tract 2011 | D11: 2449 | E11: 1354 | F11: 954.55872 | G11: 940.81461 | H11: 950.43567 | I11: ==IFERROR(H11/F11*100,0) | J11: ==K11+L11+M11 | K11: 65.2 | L11: 0 | M11: 0 | N11: 0 | O11: 0.2 | P11: 20.3 | Q11: 0 | R11: 1668 | S11: 42.99 | T11: 9.24 | U11: 33.75 | V11: 6 | W11: 460.63168 | X11: ==IFERROR(W11/F11*100,0) | Y11: 25599.119 | Z11: 10352.584 | AA11: #N/A | AB11: 0 | AC11: 0.19041701 | AD11: 177209.88 | AE11: 100907.54 | AF11: 26.921129 | AG11: 476 | AH11: 949 | AI11: 766 | AJ11: ==AG11+AI11*0.4 | AK11: ==IFERROR(AJ11/G11,0) | AL11: 20.93% | AM11: 6.22% | AN11: 85375 | AO11: Likely to attract capital even without OZ designation | AP11: Likely to Attract Investment
A12: 49057201200 | B12: Weber | C12: Tract 2012 | D12: 2785 | E12: 941 | F12: 295.46004 | G12: 295.36559 | H12: 0.042675122 | I12: ==IFERROR(H12/F12*100,0) | J12: ==K12+L12+M12 | K12: 22.6 | L12: 0 | M12: 0 | N12: 1 | O12: 0 | P12: 18.2 | Q12: 29 | R12: 1117 | S12: 81.51 | T12: 59.54 | U12: 21.97 | V12: 0 | W12: 0 | X12: ==IFERROR(W12/F12*100,0) | Y12: 28462.518 | Z12: 11521.282 | AA12: #N/A | AB12: 0 | AC12: 0.55857116 | AD12: 185298.36 | AE12: 105035.11 | AF12: 29.44812 | AG12: 134 | AH12: 194 | AI12: 423 | AJ12: ==AG12+AI12*0.4 | AK12: ==IFERROR(AJ12/G12,0) | AL12: 19.78% | AM12: 4.31% | AN12: 67273 | AO12: More likely to attract OZ investment, with larger impact | AP12: More Likely
A13: 49057201301 | B13: Weber | C13: Tract 2013.01 | D13: 3020 | E13: 1258 | F13: 187.39695 | G13: 187.39674 | H13: 0.0060760861 | I13: ==IFERROR(H13/F13*100,0) | J13: ==K13+L13+M13 | K13: 14.3 | L13: 0 | M13: 1.4 | N13: 0.7 | O13: 0 | P13: 0 | Q13: 0 | R13: 1150 | S13: 107.19 | T13: 77.22 | U13: 29.97 | V13: 0 | W13: 0 | X13: ==IFERROR(W13/F13*100,0) | Y13: 20954.658 | Z13: 9829.9877 | AA13: #N/A | AB13: 0 | AC13: 1.503162 | AD13: 164541.67 | AE13: 94594.574 | AF13: 24.057132 | AG13: 86 | AH13: 66 | AI13: 9 | AJ13: ==AG13+AI13*0.4 | AK13: ==IFERROR(AJ13/G13,0) | AL13: 16.19% | AM13: 5.48% | AN13: 75000 | AO13: More likely to attract OZ investment, with larger impact | AP13: More Likely
A14: 49057201302 | B14: Weber | C14: Tract 2013.02 | D14: 2921 | E14: 1139 | F14: 266.117 | G14: 266.11671 | H14: 0 | I14: ==IFERROR(H14/F14*100,0) | J14: ==K14+L14+M14 | K14: 0 | L14: 0 | M14: 9.9 | N14: 3.2 | O14: 0 | P14: 0 | Q14: 0 | R14: 1255 | S14: 144.12 | T14: 112.74 | U14: 31.38 | V14: 3 | W14: 34.56731 | X14: ==IFERROR(W14/F14*100,0) | Y14: 20299.771 | Z14: 10021.891 | AA14: #N/A | AB14: 0 | AC14: 1.411961 | AD14: 172058.17 | AE14: 98969.206 | AF14: 24.991694 | AG14: 79 | AH14: -1 | AI14: 10 | AJ14: ==AG14+AI14*0.4 | AK14: ==IFERROR(AJ14/G14,0) | AL14: 19.68% | AM14: 8.6% | AN14: 65637 | AO14: More likely to attract OZ investment, with larger impact | AP14: More Likely
... A16: 49057201800 | B16: Weber | C16: Tract 2018 | D16: 2506 | E16: 939 | F16: 398.10376 | G16: 395.2451 | H16: 0.15156297 | I16: ==IFERROR(H16/F16*100,0) | J16: ==K16+L16+M16 | K16: 0 | L16: 3.2 | M16: 0 | N16: 0.6 | O16: 0 | P16: 16.2 | Q16: 53.1 | R16: 724 | S16: 93.04 | T16: 83.95 | U16: 9.09 | V16: 0 | W16: 0 | X16: ==IFERROR(W16/F16*100,0) | Y16: 24140.973 | Z16: 9841.8472 | AA16: #N/A | AB16: 0 | AC16: 0.51053358 | AD16: 187536.84 | AE16: 105776.44 | AF16: 27.28555 | AG16: 28 | AH16: -49 | AI16: 203 | AJ16: ==AG16+AI16*0.4 | AK16: ==IFERROR(AJ16/G16,0) | AL16: 14.99% | AM16: 3.98% | AN16: 73051 | AO16: More likely to attract OZ investment, with larger impact | AP16: More Likely
A17: 49057201900 | B17: Weber | C17: Tract 2019 | D17: 1231 | E17: 383 | F17: 2606.0412 | G17: 2586.8974 | H17: 6.7408842 | I17: ==IFERROR(H17/F17*100,0) | J17: ==K17+L17+M17 | K17: 0 | L17: 0 | M17: 2.8 | N17: 0 | O17: 7.5 | P17: 42.2 | Q17: 0 | R17: 423 | S17: 91.82 | T17: 86.27 | U17: 5.55 | V17: 0 | W17: 40.948232 | X17: ==IFERROR(W17/F17*100,0) | Y17: 8535.6351 | Z17: 3661.2524 | AA17: #N/A | AB17: 2 | AC17: #N/A | AD17: 188924.3 | AE17: 108505.68 | AF17: 19.051072 | AG17: 154 | AH17: 252 | AI17: 187 | AJ17: ==AG17+AI17*0.4 | AK17: ==IFERROR(AJ17/G17,0) | AL17: 20.9% | AM17: 0% | AN17: 64773 | AO17: Likely to attract capital even without OZ designation | AP17: Likely to Attract Investment
A18: 49057210512 | B18: Weber | C18: Tract 2105.12 | D18: 5315 | E18: 2022 | F18: 2327.0952 | G18: 2246.8719 | H18: 0.44173823 | I18: ==IFERROR(H18/F18*100,0) | J18: ==K18+L18+M18 | K18: 0 | L18: 1.1 | M18: 10.7 | N18: 1 | O18: 8.2 | P18: 10.6 | Q18: 12 | R18: 1939 | S18: 461.62 | T18: 377.48 | U18: 84.14 | V18: 0 | W18: 0 | X18: ==IFERROR(W18/F18*100,0) | Y18: 5914.5499 | Z18: 2634.4968 | AA18: #N/A | AB18: 3 | AC18: #N/A | AD18: 202857.26 | AE18: 114415.23 | AF18: 19.032511 | AG18: 560 | AH18: 965 | AI18: 4018 | AJ18: ==AG18+AI18*0.4 | AK18: ==IFERROR(AJ18/G18,0) | AL18: 16.41% | AM18: 3.18% | AN18: 79167 | AO18: More likely to attract OZ investment, with larger impact | AP18: More Likely
A19: 49057210701 | B19: Weber | C19: Tract 2107.01 | D19: 5792 | E19: 1999 | F19: 739.0346 | G19: 736.59631 | H19: 0 | I19: ==IFERROR(H19/F19*100,0) | J19: ==K19+L19+M19 | K19: 0 | L19: 25.8 | M19: 0 | N19: 0 | O19: 0 | P19: 0 | Q19: 1.9 | R19: 2105 | S19: 395.79 | T19: 339.35 | U19: 56.44 | V19: 0 | W19: 0 | X19: ==IFERROR(W19/F19*100,0) | Y19: 10654.908 | Z19: 5530.731 | AA19: #N/A | AB19: 1 | AC19: #N/A | AD19: 193851.94 | AE19: 112434.2 | AF19: 21.828939 | AG19: 103 | AH19: -72 | AI19: 140 | AJ19: ==AG19+AI19*0.4 | AK19: ==IFERROR(AJ19/G19,0) | AL19: 5.33% | AM19: 3.74% | AN19: 72267 | AO19: More likely to attract OZ investment, with larger impact | AP19: More Likely
A20: 49057210800 | B20: Weber | C20: Tract 2108 | D20: 3375 | E20: 1365 | F20: 392.18497 | G20: 392.18454 | H20: 387.99277 | I20: ==IFERROR(H20/F20*100,0) | J20: ==K20+L20+M20 | K20: 0 | L20: 0 | M20: 40.2 | N20: 0 | O20: 0 | P20: 0 | Q20: 9.2 | R20: 1380 | S20: 192.18 | T20: 167.48 | U20: 24.7 | V20: 0 | W20: 0 | X20: ==IFERROR(W20/F20*100,0) | Y20: 19284.847 | Z20: 8489.453 | AA20: #N/A | AB20: 0 | AC20: 0.95614932 | AD20: 183017.89 | AE20: 103239.93 | AF20: 24.543173 | AG20: 34 | AH20: -99 | AI20: 228 | AJ20: ==AG20+AI20*0.4 | AK20: ==IFERROR(AJ20/G20,0) | AL20: 3.73% | AM20: 2.23% | AN20: 72375 | AO20: More likely to attract OZ investment, with larger impact | AP20: More Likely
A21: 49011125201 | B21: Davis | C21: Tract 1252.01 | D21: 3378 | E21: 1024 | F21: 422.32446 | G21: 420.17208 | H21: 33.863534 | I21: ==IFERROR(H21/F21*100,0) | J21: ==K21+L21+M21 | K21: 0 | L21: 0 | M21: 0 | N21: 1.8 | O21: 6.3 | P21: 0 | Q21: 0 | R21: 1096 | S21: 280.82 | T21: 0.83 | U21: 279.99 | V21: 0 | W21: 0 | X21: ==IFERROR(W21/F21*100,0) | Y21: 4325.7889 | Z21: 1654.9946 | AA21: #N/A | AB21: 0 | AC21: 0.087414031 | AD21: 143340.47 | AE21: 78227.744 | AF21: 10.425589 | AG21: 17 | AH21: -181 | AI21: 1610 | AJ21: ==AG21+AI21*0.4 | AK21: ==IFERROR(AJ21/G21,0) | AL21: 1.48% | AM21: 6.19% | AN21: 69120 | AO21: Likely to attract capital even without OZ designation | AP21: Likely to Attract Investment
A22: 49011125301 | B22: Davis | C22: Tract 1253.01 | D22: 5530 | E22: 1718 | F22: 683.39735 | G22: 678.17312 | H22: 0.026325763 | I22: ==IFERROR(H22/F22*100,0) | J22: ==K22+L22+M22 | K22: 0 | L22: 0 | M22: 22.7 | N22: 4.7 | O22: 0 | P22: 0 | Q22: 0 | R22: 1967 | S22: 333.92 | T22: 305.44 | U22: 28.48 | V22: 0 | W22: 0 | X22: ==IFERROR(W22/F22*100,0) | Y22: 10197.53 | Z22: 5032.765 | AA22: #N/A | AB22: 0 | AC22: 0.10654777 | AD22: 196056.72 | AE22: 111266.66 | AF22: 21.272437 | AG22: 443 | AH22: 748 | AI22: 400 | AJ22: ==AG22+AI22*0.4 | AK22: ==IFERROR(AJ22/G22,0) | AL22: 10.57% | AM22: 2.89% | AN22: 77202 | AO22: More likely to attract OZ investment, with larger impact | AP22: More Likely
A23: 49011125600 | B23: Davis | C23: Tract 1256 | D23: 307 | E23: 100 | F23: 1001.0013 | G23: 993.9971 | H23: 0.36012347 | I23: ==IFERROR(H23/F23*100,0) | J23: ==K23+L23+M23 | K23: 0 | L23: 0 | M23: 0 | N23: 7.5 | O23: 0 | P23: 92.5 | Q23: 0 | R23: 155 | S23: 15.34 | T23: 7.59 | U23: 7.75 | V23: 0 | W23: 113.57989 | X23: ==IFERROR(W23/F23*100,0) | Y23: 9886.5342 | Z23: 5129.6179 | AA23: #N/A | AB23: 0 | AC23: 0.95330711 | AD23: 173447.89 | AE23: 98120.48 | AF23: 18.538631 | AG23: 6 | AH23: -29 | AI23: 190 | AJ23: ==AG23+AI23*0.4 | AK23: ==IFERROR(AJ23/G23,0) | AL23: 21.11% | AM23: 3.29% | AN23: 95250 | AO23: More likely to attract OZ investment, with larger impact | AP23: More Likely
A24: 49011125701 | B24: Davis | C24: Tract 1257.01 | D24: 5452 | E24: 2345 | F24: 808.36639 | G24: 807.67307 | H24: 735.00529 | I24: ==IFERROR(H24/F24*100,0) | J24: ==K24+L24+M24 | K24: 0 | L24: 35.3 | M24: 11.6 | N24: 0 | O24: 0 | P24: 23 | Q24: 5.7 | R24: 2765 | S24: 218.45 | T24: 99.79 | U24: 118.66 | V24: 1 | W24: 357.78004 | X24: ==IFERROR(W24/F24*100,0) | Y24: 17443.087 | Z24: 7688.3857 | AA24: #N/A | AB24: 0 | AC24: 0.015282427 | AD24: 209493.93 | AE24: 114337.41 | AF24: 26.150514 | AG24: 756 | AH24: 1436 | AI24: 902 | AJ24: ==AG24+AI24*0.4 | AK24: ==IFERROR(AJ24/G24,0) | AL24: 21.86% | AM24: 1.99% | AN24: 61189 | AO24: More likely to attract OZ investment, with larger impact | AP24: More Likely
A25: 49011125702 | B25: Davis | C25: Tract 1257.02 | D25: 4090 | E25: 1532 | F25: 518.0901 | G25: 515.73298 | H25: 518.03867 | I25: ==IFERROR(H25/F25*100,0) | J25: ==K25+L25+M25 | K25: 0 | L25: 15.1 | M25: 6.6 | N25: 0 | O25: 0 | P25: 0 | Q25: 0 | R25: 1575 | S25: 245.9 | T25: 220.95 | U25: 24.95 | V25: 0 | W25: 0 | X25: ==IFERROR(W25/F25*100,0) | Y25: 11644.775 | Z25: 5066.947 | AA25: #N/A | AB25: 2 | AC25: #N/A | AD25: 210910.62 | AE25: 115100.67 | AF25: 22.829023 | AG25: 840 | AH25: 1726 | AI25: 123 | AJ25: ==AG25+AI25*0.4 | AK25: ==IFERROR(AJ25/G25,0) | AL25: 22.33% | AM25: 5.05% | AN25: 73441 | AO25: Less likely to attract OZ investment | AP25: Less Likely
A26: 49011125801 | B26: Davis | C26: Tract 1258.01 | D26: 6439 | E26: 2621 | F26: 838.59788 | G26: 835.54272 | H26: 0.37374348 | I26: ==IFERROR(H26/F26*100,0) | J26: ==K26+L26+M26 | K26: 0 | L26: 1.1 | M26: 14.8 | N26: 0 | O26: 3.9 | P26: 7.2 | Q26: 2.7 | R26: 2623 | S26: 354.64 | T26: 275.16 | U26: 79.48 | V26: 0 | W26: 0 | X26: ==IFERROR(W26/F26*100,0) | Y26: 13485.832 | Z26: 6122.3269 | AA26: #N/A | AB26: 2 | AC26: #N/A | AD26: 215023.11 | AE26: 116169.91 | AF26: 24.461926 | AG26: 602 | AH26: 1095 | AI26: 171 | AJ26: ==AG26+AI26*0.4 | AK26: ==IFERROR(AJ26/G26,0) | AL26: 17.89% | AM26: 3.04% | AN26: 72697 | AO26: More likely to attract OZ investment, with larger impact | AP26: More Likely
A27: 49011125810 | B27: Davis | C27: Tract 1258.10 | D27: 2900 | E27: 1147 | F27: 348.00501 | G27: 347.95046 | H27: 0.012698576 | I27: ==IFERROR(H27/F27*100,0) | J27: ==K27+L27+M27 | K27: 0 | L27: 22.2 | M27: 20.7 | N27: 0 | O27: 0 | P27: 0 | Q27: 2.4 | R27: 1641 | S27: 131.45 | T27: 59.76 | U27: 71.69 | V27: 0 | W27: 0 | X27: ==IFERROR(W27/F27*100,0) | Y27: 13342.854 | Z27: 5560.2697 | AA27: #N/A | AB27: 0 | AC27: 0.0096378156 | AD27: 216469.2 | AE27: 115653.8 | AF27: 23.962106 | AG27: 393 | AH27: 755 | AI27: 156 | AJ27: ==AG27+AI27*0.4 | AK27: ==IFERROR(AJ27/G27,0) | AL27: 20.03% | AM27: 1.46% | AN27: 68021 | AO27: More likely to attract OZ investment, with larger impact | AP27: More Likely
A28: 49011126700 | B28: Davis | C28: Tract 1267 | D28: 4097 | E28: 1469 | F28: 528.20538 | G28: 528.20478 | H28: 0 | I28: ==IFERROR(H28/F28*100,0) | J28: ==K28+L28+M28 | K28: 0 | L28: 18.6 | M28: 10.4 | N28: 24.3 | O28: 0 | P28: 0 | Q28: 14.1 | R28: 1678 | S28: 222.38 | T28: 158.9 | U28: 63.48 | V28: 0 | W28: 3.8068832 | X28: ==IFERROR(W28/F28*100,0) | Y28: 10339.274 | Z28: 4826.214 | AA28: #N/A | AB28: 0 | AC28: 0.0085336427 | AD28: 309537.63 | AE28: 148746.44 | AF28: 31.403545 | AG28: 262 | AH28: 443 | AI28: -153 | AJ28: ==AG28+AI28*0.4 | AK28: ==IFERROR(AJ28/G28,0) | AL28: 14.41% | AM28: 7.04% | AN28: 77750 | AO28: Likely to attract capital even without OZ designation | AP28: Likely to Attract Investment
A29: 49035100306 | B29: Salt Lake | C29: Tract 1003.06 | D29: 7303 | E29: 2734 | F29: 443.04242 | G29: 442.06047 | H29: 0.85944083 | I29: ==IFERROR(H29/F29*100,0) | J29: ==K29+L29+M29 | K29: 0 | L29: 38.1 | M29: 0 | N29: 0.4 | O29: 0 | P29: 0 | Q29: 0 | R29: 3631 | S29: 171.33 | T29: 96.49 | U29: 74.84 | V29: 2 | W29: 375.58206 | X29: ==IFERROR(W29/F29*100,0) | Y29: 47182.35 | Z29: 13178.413 | AA29: #N/A | AB29: 1 | AC29: #N/A | AD29: 511399.35 | AE29: 214888.26 | AF29: 64.721135 | AG29: 342 | AH29: 409 | AI29: 171 | AJ29: ==AG29+AI29*0.4 | AK29: ==IFERROR(AJ29/G29,0) | AL29: 9.39% | AM29: 2.47% | AN29: 66353 | AO29: More likely to attract OZ investment, with larger impact | AP29: More Likely
A30: 49035100308 | B30: Salt Lake | C30: Tract 1003.08 | D30: 4168 | E30: 1222 | F30: 352.03117 | G30: 348.9531 | H30: 1.4026208 | I30: ==IFERROR(H30/F30*100,0) | J30: ==K30+L30+M30 | K30: 0 | L30: 0 | M30: 0 | N30: 8.1 | O30: 0 | P30: 0 | Q30: 0 | R30: 1392 | S30: 129.94 | T30: 75.61 | U30: 54.33 | V30: 0 | W30: 0 | X30: ==IFERROR(W30/F30*100,0) | Y30: 23040.815 | Z30: 7422.198 | AA30: #N/A | AB30: 0 | AC30: 0.28828735 | AD30: 497092.99 | AE30: 213707.62 | AF30: 53.725558 | AG30: 22 | AH30: -178 | AI30: 37 | AJ30: ==AG30+AI30*0.4 | AK30: ==IFERROR(AJ30/G30,0) | AL30: 13.32% | AM30: 11.45% | AN30: 81023 | AO30: Less likely to attract OZ investment | AP30: Less Likely
A31: 49035100500 | B31: Salt Lake | C31: Tract 1005 | D31: 5554 | E31: 2337 | F31: 460.47758 | G31: 459.25582 | H31: 0.31615917 | I31: ==IFERROR(H31/F31*100,0) | J31: ==K31+L31+M31 | K31: 0 | L31: 0 | M31: 0 | N31: 0 | O31: 0 | P31: 0 | Q31: 0 | R31: 2283 | S31: 258.99 | T31: 214.23 | U31: 44.76 | V31: 0 | W31: 0 | X31: ==IFERROR(W31/F31*100,0) | Y31: 37281.611 | Z31: 11855.03 | AA31: #N/A | AB31: 2 | AC31: #N/A | AD31: 536178.25 | AE31: 227561.9 | AF31: 64.241801 | AG31: 65 | AH31: -206 | AI31: 25 | AJ31: ==AG31+AI31*0.4 | AK31: ==IFERROR(AJ31/G31,0) | AL31: 9.67% | AM31: 3.37% | AN31: 78910 | AO31: Less likely to attract OZ investment | AP31: Less Likely
A32: 49035100600 | B32: Salt Lake | C32: Tract 1006 | D32: 7099 | E32: 2957 | F32: 726.0086 | G32: 714.41157 | H32: 722.61276 | I32: ==IFERROR(H32/F32*100,0) | J32: ==K32+L32+M32 | K32: 0 | L32: 23.7 | M32: 0 | N32: 0 | O32: 0 | P32: 0 | Q32: 0 | R32: 3084 | S32: 295.75 | T32: 214.75 | U32: 81 | V32: 0 | W32: 778.55912 | X32: ==IFERROR(W32/F32*100,0) | Y32: 47636.208 | Z32: 13288.061 | AA32: #N/A | AB32: 0 | AC32: 0.020420523 | AD32: 508957 | AE32: 212822.78 | AF32: 64.536373 | AG32: 302 | AH32: 417 | AI32: 246 | AJ32: ==AG32+AI32*0.4 | AK32: ==IFERROR(AJ32/G32,0) | AL32: 16.66% | AM32: 9.09% | AN32: 81169 | AO32: Less likely to attract OZ investment | AP32: Less Likely
A33: 49035100800 | B33: Salt Lake | C33: Tract 1008 | D33: 2656 | E33: 1688 | F33: 178.58695 | G33: 176.63547 | H33: 0.16186351 | I33: ==IFERROR(H33/F33*100,0) | J33: ==K33+L33+M33 | K33: 24.6 | L33: 0 | M33: 0 | N33: 0 | O33: 0 | P33: 0 | Q33: 0 | R33: 1751 | S33: 45.4 | T33: 11.91 | U33: 33.49 | V33: 1 | W33: 505.61151 | X33: ==IFERROR(W33/F33*100,0) | Y33: 103690.17 | Z33: 25715.528 | AA33: #N/A | AB33: 0 | AC33: 0.75012731 | AD33: 475284.44 | AE33: 191405.96 | AF33: 82.959137 | AG33: 154 | AH33: 221 | AI33: 652 | AJ33: ==AG33+AI33*0.4 | AK33: ==IFERROR(AJ33/G33,0) | AL33: 20.1% | AM33: 5.86% | AN33: 83482 | AO33: More likely to attract OZ investment, with larger impact | AP33: More Likely
A34: 49035101401 | B34: Salt Lake | C34: Tract 1014.01 | D34: 2678 | E34: 372 | F34: 331.5305 | G34: 331.51325 | H34: 0 | I34: ==IFERROR(H34/F34*100,0) | J34: ==K34+L34+M34 | K34: 0 | L34: 0 | M34: 0 | N34: 0 | O34: 0 | P34: 0 | Q34: 0 | R34: 634 | S34: 44.35 | T34: 0 | U34: 44.35 | V34: 0 | W34: 313.36584 | X34: ==IFERROR(W34/F34*100,0) | Y34: 65143.203 | Z34: 19066.172 | AA34: #N/A | AB34: 0 | AC34: 2.1665794 | AD34: 428629.39 | AE34: 179330.43 | AF34: 65.115982 | AG34: 71 | AH34: 51 | AI34: 30 | AJ34: ==AG34+AI34*0.4 | AK34: ==IFERROR(AJ34/G34,0) | AL34: 27.97% | AM34: 5.61% | AN34: 52500 | AO34: Likely to attract capital even without OZ designation | AP34: Likely to Attract Investment
A35: 49035101402 | B35: Salt Lake | C35: Tract 1014.02 | D35: 4302 | E35: 407 | F35: 2314.0854 | G35: 1227.7731 | H35: 0 | I35: ==IFERROR(H35/F35*100,0) | J35: ==K35+L35+M35 | K35: 0 | L35: 0 | M35: 16.4 | N35: 0 | O35: 0 | P35: 0 | Q35: 0 | R35: 993 | S35: 26.79 | T35: 0 | U35: 26.79 | V35: 8 | W35: 1855.4604 | X35: ==IFERROR(W35/F35*100,0) | Y35: 50186.858 | Z35: 15654.876 | AA35: #N/A | AB35: 0 | AC35: 2.451887 | AD35: 328613.38 | AE35: 137925.1 | AF35: 48.876783 | AG35: 1013 | AH35: 2561 | AI35: 4408 | AJ35: ==AG35+AI35*0.4 | AK35: ==IFERROR(AJ35/G35,0) | AL35: 29.15% | AM35: 6.65% | AN35: 54167 | AO35: Likely to attract capital even without OZ designation | AP35: Likely to Attract Investment
A36: 49035101500 | B36: Salt Lake | C36: Tract 1015 | D36: 3438 | E36: 1706 | F36: 203.48978 | G36: 203.48842 | H36: 0 | I36: ==IFERROR(H36/F36*100,0) | J36: ==K36+L36+M36 | K36: 0 | L36: 0 | M36: 0 | N36: 16.9 | O36: 0 | P36: 0 | Q36: 0 | R36: 1649 | S36: 96.43 | T36: 57.6 | U36: 38.83 | V36: 0 | W36: 166.27971 | X36: ==IFERROR(W36/F36*100,0) | Y36: 84591.767 | Z36: 23675.3 | AA36: #N/A | AB36: 0 | AC36: 2.3769226 | AD36: 447165.77 | AE36: 182368.63 | AF36: 74.556862 | AG36: 109 | AH36: 136 | AI36: 34 | AJ36: ==AG36+AI36*0.4 | AK36: ==IFERROR(AJ36/G36,0) | AL36: 41.26% | AM36: 1.65% | AN36: 99219 | AO36: Likely to attract capital even without OZ designation | AP36: Likely to Attract Investment
A37: 49035101600 | B37: Salt Lake | C37: Tract 1016 | D37: 3333 | E37: 1800 | F37: 244.1956 | G37: 244.19532 | H37: 0 | I37: ==IFERROR(H37/F37*100,0) | J37: ==K37+L37+M37 | K37: 0 | L37: 0 | M37: 0 | N37: 1.6 | O37: 0 | P37: 0 | Q37: 0 | R37: 1852 | S37: 116.28 | T37: 88.82 | U37: 27.46 | V37: 0 | W37: 205.94604 | X37: ==IFERROR(W37/F37*100,0) | Y37: 71932.229 | Z37: 22971.517 | AA37: #N/A | AB37: 0 | AC37: 2.0797437 | AD37: 462480.53 | AE37: 191581.52 | AF37: 73.104718 | AG37: 41 | AH37: -57 | AI37: 22 | AJ37: ==AG37+AI37*0.4 | AK37: ==IFERROR(AJ37/G37,0) | AL37: 27.99% | AM37: 2.8% | AN37: 136473 | AO37: Likely to attract capital even without OZ designation | AP37: Likely to Attract Investment
A38: 49035101700 | B38: Salt Lake | C38: Tract 1017 | D38: 3435 | E38: 2146 | F38: 173.16575 | G38: 173.16556 | H38: 0 | I38: ==IFERROR(H38/F38*100,0) | J38: ==K38+L38+M38 | K38: 0 | L38: 0 | M38: 0 | N38: 6 | O38: 0 | P38: 0 | Q38: 0 | R38: 2273 | S38: 79.52 | T38: 29.63 | U38: 49.89 | V38: 2 | W38: 231.59645 | X38: ==IFERROR(W38/F38*100,0) | Y38: 94961.322 | Z38: 28137.325 | AA38: #N/A | AB38: 0 | AC38: 1.9724725 | AD38: 472929.08 | AE38: 192484.49 | AF38: 83.130916 | AG38: 70 | AH38: 5 | AI38: 17 | AJ38: ==AG38+AI38*0.4 | AK38: ==IFERROR(AJ38/G38,0) | AL38: 23.36% | AM38: 2.28% | AN38: 107419 | AO38: More likely to attract OZ investment, with larger impact | AP38: More Likely
A39: 49035101800 | B39: Salt Lake | C39: Tract 1018 | D39: 3485 | E39: 1974 | F39: 217.46101 | G39: 217.46076 | H39: 0 | I39: ==IFERROR(H39/F39*100,0) | J39: ==K39+L39+M39 | K39: 0 | L39: 0 | M39: 0 | N39: 10.4 | O39: 0 | P39: 0 | Q39: 0 | R39: 1950 | S39: 99.45 | T39: 59.58 | U39: 39.87 | V39: 0 | W39: 231.35679 | X39: ==IFERROR(W39/F39*100,0) | Y39: 71278.686 | Z39: 24512.677 | AA39: #N/A | AB39: 0 | AC39: 1.736373 | AD39: 491430.8 | AE39: 202818.26 | AF39: 77.09859 | AG39: 68 | AH39: 6 | AI39: 52 | AJ39: ==AG39+AI39*0.4 | AK39: ==IFERROR(AJ39/G39,0) | AL39: 20.88% | AM39: 8.15% | AN39: 126618 | AO39: More likely to attract OZ investment, with larger impact | AP39: More Likely
A40: 49035101900 | B40: Salt Lake | C40: Tract 1019 | D40: 3582 | E40: 2242 | F40: 172.71915 | G40: 172.71895 | H40: 0 | I40: ==IFERROR(H40/F40*100,0) | J40: ==K40+L40+M40 | K40: 0 | L40: 99.9 | M40: 0 | N40: 0 | O40: 0 | P40: 0 | Q40: 0 | R40: 2862 | S40: 43.27 | T40: 5.72 | U40: 37.55 | V40: 2 | W40: 229.37977 | X40: ==IFERROR(W40/F40*100,0) | Y40: 100936.57 | Z40: 27570.852 | AA40: #N/A | AB40: 0 | AC40: 1.5943592 | AD40: 451915.72 | AE40: 183113.06 | AF40: 81.74746 | AG40: 668 | AH40: 1673 | AI40: 1670 | AJ40: ==AG40+AI40*0.4 | AK40: ==IFERROR(AJ40/G40,0) | AL40: 34.31% | AM40: 2.59% | AN40: 83309 | AO40: More likely to attract OZ investment, with larger impact | AP40: More Likely
A41: 49035102000 | B41: Salt Lake | C41: Tract 1020 | D41: 2926 | E41: 1835 | F41: 215.91331 | G41: 215.89965 | H41: 0 | I41: ==IFERROR(H41/F41*100,0) | J41: ==K41+L41+M41 | K41: 0 | L41: 39.9 | M41: 0 | N41: 0 | O41: 0 | P41: 0 | Q41: 0 | R41: 2163 | S41: 82.89 | T41: 47.17 | U41: 35.72 | V41: 0 | W41: 229.50155 | X41: ==IFERROR(W41/F41*100,0) | Y41: 80681.043 | Z41: 24040.916 | AA41: #N/A | AB41: 0 | AC41: 1.2909788 | AD41: 514095.12 | AE41: 211140.73 | AF41: 80.899665 | AG41: 562 | AH41: 1371 | AI41: -405 | AJ41: ==AG41+AI41*0.4 | AK41: ==IFERROR(AJ41/G41,0) | AL41: 20.44% | AM41: 7.73% | AN41: 136923 | AO41: More likely to attract OZ investment, with larger impact | AP41: More Likely
A42: 49035102100 | B42: Salt Lake | C42: Tract 1021 | D42: 2386 | E42: 1706 | F42: 115.32182 | G42: 115.32169 | H42: 0 | I42: ==IFERROR(H42/F42*100,0) | J42: ==K42+L42+M42 | K42: 49.8 | L42: 50.2 | M42: 0 | N42: 0 | O42: 0 | P42: 0 | Q42: 0 | R42: 2894 | S42: 21.85 | T42: 0.04 | U42: 21.81 | V42: 0 | W42: 245.98166 | X42: ==IFERROR(W42/F42*100,0) | Y42: 115798.4 | Z42: 29794.471 | AA42: #N/A | AB42: 0 | AC42: 1.3662151 | AD42: 471542.18 | AE42: 188743.06 | AF42: 88.540179 | AG42: 262 | AH42: 697 | AI42: 1591 | AJ42: ==AG42+AI42*0.4 | AK42: ==IFERROR(AJ42/G42,0) | AL42: 22.52% | AM42: 2.25% | AN42: #N/A | AO42: More likely to attract OZ investment, with larger impact | AP42: More Likely
A43: 49035102300 | B43: Salt Lake | C43: Tract 1023 | D43: 3050 | E43: 1897 | F43: 201.79279 | G43: 201.79257 | H43: 0 | I43: ==IFERROR(H43/F43*100,0) | J43: ==K43+L43+M43 | K43: 35.6 | L43: 14.3 | M43: 0 | N43: 0 | O43: 0 | P43: 0 | Q43: 0 | R43: 2409 | S43: 55.17 | T43: 20.41 | U43: 34.76 | V43: 2 | W43: 391.14305 | X43: ==IFERROR(W43/F43*100,0) | Y43: 98523.127 | Z43: 25600.192 | AA43: #N/A | AB43: 0 | AC43: 0.84956253 | AD43: 526947.65 | AE43: 214387.07 | AF43: 87.14564 | AG43: 431 | AH43: 994 | AI43: -217 | AJ43: ==AG43+AI43*0.4 | AK43: ==IFERROR(AJ43/G43,0) | AL43: 21.4% | AM43: 8.59% | AN43: 73602 | AO43: More likely to attract OZ investment, with larger impact | AP43: More Likely
A44: 49035102701 | B44: Salt Lake | C44: Tract 1027.01 | D44: 5409 | E44: 1947 | F44: 344.4577 | G44: 342.48729 | H44: 3.3827467 | I44: ==IFERROR(H44/F44*100,0) | J44: ==K44+L44+M44 | K44: 0 | L44: 0 | M44: 0 | N44: 1.6 | O44: 0 | P44: 0 | Q44: 0 | R44: 1685 | S44: 212.72 | T44: 166.61 | U44: 46.11 | V44: 0 | W44: 0 | X44: ==IFERROR(W44/F44*100,0) | Y44: 44323.481 | Z44: 12640.532 | AA44: #N/A | AB44: 0 | AC44: 0.44016986 | AD44: 541770.97 | AE44: 225090.42 | AF44: 66.41387 | AG44: 55 | AH44: -215 | AI44: 25 | AJ44: ==AG44+AI44*0.4 | AK44: ==IFERROR(AJ44/G44,0) | AL44: 10.5% | AM44: 3.18% | AN44: 79318 | AO44: Less likely to attract OZ investment | AP44: Less Likely
A45: 49035102702 | B45: Salt Lake | C45: Tract 1027.02 | D45: 3018 | E45: 1092 | F45: 422.43551 | G45: 416.52104 | H45: 419.8051 | I45: ==IFERROR(H45/F45*100,0) | J45: ==K45+L45+M45 | K45: 0 | L45: 27.4 | M45: 0 | N45: 0 | O45: 0 | P45: 0 | Q45: 0 | R45: 1327 | S45: 127.94 | T45: 79.78 | U45: 48.16 | V45: 2 | W45: 317.88453 | X45: ==IFERROR(W45/F45*100,0) | Y45: 53211.942 | Z45: 14613.944 | AA45: #N/A | AB45: 1 | AC45: #N/A | AD45: 530556.28 | AE45: 220052.77 | AF45: 68.842432 | AG45: 59 | AH45: -100 | AI45: 215 | AJ45: ==AG45+AI45*0.4 | AK45: ==IFERROR(AJ45/G45,0) | AL45: 33.72% | AM45: 7.63% | AN45: 34568 | AO45: Less likely to attract OZ investment | AP45: Less Likely
A46: 49035102802 | B46: Salt Lake | C46: Tract 1028.02 | D46: 4884 | E46: 1289 | F46: 1300.653 | G46: 1272.745 | H46: 2.2162277 | I46: ==IFERROR(H46/F46*100,0) | J46: ==K46+L46+M46 | K46: 0 | L46: 15.5 | M46: 14.6 | N46: 8.3 | O46: 0 | P46: 0 | Q46: 0 | R46: 1388 | S46: 195.95 | T46: 165.18 | U46: 30.77 | V46: 0 | W46: 109.25872 | X46: ==IFERROR(W46/F46*100,0) | Y46: 40080.242 | Z46: 11399.703 | AA46: #N/A | AB46: 1 | AC46: #N/A | AD46: 552795.08 | AE46: 235759.85 | AF46: 66.303543 | AG46: 206 | AH46: 166 | AI46: 170 | AJ46: ==AG46+AI46*0.4 | AK46: ==IFERROR(AJ46/G46,0) | AL46: 24.44% | AM46: 4.98% | AN46: 65208 | AO46: More likely to attract OZ investment, with larger impact | AP46: More Likely
A47: 49035102900 | B47: Salt Lake | C47: Tract 1029 | D47: 6149 | E47: 3457 | F47: 930.1124 | G47: 930.11137 | H47: 0.060012807 | I47: ==IFERROR(H47/F47*100,0) | J47: ==K47+L47+M47 | K47: 0 | L47: 81.7 | M47: 11 | N47: 0 | O47: 0 | P47: 0 | Q47: 0 | R47: 4217 | S47: 167.8 | T47: 84.16 | U47: 83.64 | V47: 2 | W47: 1151.4629 | X47: ==IFERROR(W47/F47*100,0) | Y47: 90552.574 | Z47: 25540.041 | AA47: #N/A | AB47: 1 | AC47: #N/A | AD47: 568917.86 | AE47: 238608.75 | AF47: 90.43966 | AG47: 2399 | AH47: 6164 | AI47: -2732 | AJ47: ==AG47+AI47*0.4 | AK47: ==IFERROR(AJ47/G47,0) | AL47: 27.18% | AM47: 6.01% | AN47: 63849 | AO47: Likely to attract capital even without OZ designation | AP47: Likely to Attract Investment
A48: 49035111105 | B48: Salt Lake | C48: Tract 1111.05 | D48: 3288 | E48: 1608 | F48: 416.97621 | G48: 416.97387 | H48: 0 | I48: ==IFERROR(H48/F48*100,0) | J48: ==K48+L48+M48 | K48: 0 | L48: 0 | M48: 0 | N48: 7.9 | O48: 0 | P48: 0 | Q48: 0 | R48: 1618 | S48: 237.43 | T48: 143.14 | U48: 94.29 | V48: 0 | W48: 0 | X48: ==IFERROR(W48/F48*100,0) | Y48: 38162.771 | Z48: 17237.262 | AA48: #N/A | AB48: 0 | AC48: 1.3356872 | AD48: 421122.16 | AE48: 206858.66 | AF48: 60.718205 | AG48: 60 | AH48: -24 | AI48: 32 | AJ48: ==AG48+AI48*0.4 | AK48: ==IFERROR(AJ48/G48,0) | AL48: 6.78% | AM48: 4.82% | AN48: 66727 | AO48: Less likely to attract OZ investment | AP48: Less Likely
A49: 49035111400 | B49: Salt Lake | C49: Tract 1114 | D49: 7312 | E49: 3000 | F49: 531.01741 | G49: 530.98855 | H49: 0.00045959272 | I49: ==IFERROR(H49/F49*100,0) | J49: ==K49+L49+M49 | K49: 0 | L49: 0 | M49: 3.9 | N49: 6.8 | O49: 0 | P49: 0 | Q49: 0 | R49: 3315 | S49: 289.02 | T49: 216.34 | U49: 72.68 | V49: 2 | W49: 687.79429 | X49: ==IFERROR(W49/F49*100,0) | Y49: 65582.092 | Z49: 21897.918 | AA49: #N/A | AB49: 1 | AC49: #N/A | AD49: 538447.13 | AE49: 234450.45 | AF49: 79.885579 | AG49: 268 | AH49: 318 | AI49: 146 | AJ49: ==AG49+AI49*0.4 | AK49: ==IFERROR(AJ49/G49,0) | AL49: 22.68% | AM49: 2.02% | AN49: 84355 | AO49: More likely to attract OZ investment, with larger impact | AP49: More Likely
A50: 49035111500 | B50: Salt Lake | C50: Tract 1115 | D50: 2772 | E50: 1358 | F50: 1865.0747 | G50: 1843.6194 | H50: 1861.9263 | I50: ==IFERROR(H50/F50*100,0) | J50: ==K50+L50+M50 | K50: 0 | L50: 11.9 | M50: 1.1 | N50: 6.1 | O50: 0 | P50: 51.4 | Q50: 0 | R50: 1647 | S50: 82.13 | T50: 42.49 | U50: 39.64 | V50: 4 | W50: 1148.4784 | X50: ==IFERROR(W50/F50*100,0) | Y50: 44773.976 | Z50: 14333.605 | AA50: #N/A | AB50: 7 | AC50: #N/A | AD50: 535924.57 | AE50: 232709.04 | AF50: 68.598238 | AG50: 1292 | AH50: 3186 | AI50: -827 | AJ50: ==AG50+AI50*0.4 | AK50: ==IFERROR(AJ50/G50,0) | AL50: 17.87% | AM50: 5.4% | AN50: 63580 | AO50: Likely to attract capital even without OZ designation | AP50: Likely to Attract Investment
A51: 49035111601 | B51: Salt Lake | C51: Tract 1116.01 | D51: 4733 | E51: 2159 | F51: 854.4106 | G51: 854.40964 | H51: 850.99143 | I51: ==IFERROR(H51/F51*100,0) | J51: ==K51+L51+M51 | K51: 0 | L51: 0 | M51: 47 | N51: 15.9 | O51: 0 | P51: 0 | Q51: 0 | R51: 2623 | S51: 99.65 | T51: 35.27 | U51: 64.38 | V51: 4 | W51: 894.26651 | X51: ==IFERROR(W51/F51*100,0) | Y51: 83814.188 | Z51: 27464.35 | AA51: #N/A | AB51: 0 | AC51: 0.0046222667 | AD51: 541680.03 | AE51: 242308.41 | AF51: 89.707473 | AG51: 1268 | AH51: 3156 | AI51: 325 | AJ51: ==AG51+AI51*0.4 | AK51: ==IFERROR(AJ51/G51,0) | AL51: 14.36% | AM51: 4.42% | AN51: 60690 | AO51: More likely to attract OZ investment, with larger impact | AP51: More Likely
A52: 49035111602 | B52: Salt Lake | C52: Tract 1116.02 | D52: 4906 | E52: 1971 | F52: 818.44283 | G52: 807.42304 | H52: 809.38916 | I52: ==IFERROR(H52/F52*100,0) | J52: ==K52+L52+M52 | K52: 0 | L52: 0 | M52: 0 | N52: 18.6 | O52: 20.5 | P52: 0 | Q52: 0 | R52: 2205 | S52: 150.97 | T52: 51.45 | U52: 99.52 | V52: 0 | W52: 99.62599 | X52: ==IFERROR(W52/F52*100,0) | Y52: 50351.166 | Z52: 18318.746 | AA52: #N/A | AB52: 0 | AC52: 0.0054041876 | AD52: 520283.58 | AE52: 234710.4 | AF52: 72.662187 | AG52: 101 | AH52: 42 | AI52: 61 | AJ52: ==AG52+AI52*0.4 | AK52: ==IFERROR(AJ52/G52,0) | AL52: 16.96% | AM52: 6.75% | AN52: 54266 | AO52: Likely to attract capital even without OZ designation | AP52: Likely to Attract Investment
A53: 49035111701 | B53: Salt Lake | C53: Tract 1117.01 | D53: 5274 | E53: 2132 | F53: 335.28321 | G53: 335.28283 | H53: 0 | I53: ==IFERROR(H53/F53*100,0) | J53: ==K53+L53+M53 | K53: 0 | L53: 0 | M53: 9.3 | N53: 0 | O53: 0 | P53: 0 | Q53: 0 | R53: 2397 | S53: 184.8 | T53: 92.21 | U53: 92.59 | V53: 0 | W53: 9.89216 | X53: ==IFERROR(W53/F53*100,0) | Y53: 65672.391 | Z53: 23954.177 | AA53: #N/A | AB53: 0 | AC53: 0.72778891 | AD53: 517265.11 | AE53: 233093.63 | AF53: 80.428375 | AG53: 274 | AH53: 351 | AI53: 66 | AJ53: ==AG53+AI53*0.4 | AK53: ==IFERROR(AJ53/G53,0) | AL53: 6.48% | AM53: 8.99% | AN53: 79766 | AO53: More likely to attract OZ investment, with larger impact | AP53: More Likely
A54: 49035111802 | B54: Salt Lake | C54: Tract 1118.02 | D54: 2760 | E54: 1409 | F54: 294.29816 | G54: 294.29783 | H54: 293.22246 | I54: ==IFERROR(H54/F54*100,0) | J54: ==K54+L54+M54 | K54: 0 | L54: 14.9 | M54: 0 | N54: 0 | O54: 0 | P54: 0 | Q54: 0 | R54: 2282 | S54: 149.39 | T54: 102.27 | U54: 47.12 | V54: 0 | W54: 0 | X54: ==IFERROR(W54/F54*100,0) | Y54: 56845.083 | Z54: 24885.779 | AA54: #N/A | AB54: 0 | AC54: 0.54304347 | AD54: 503102.01 | AE54: 227056.67 | AF54: 77.847952 | AG54: 182 | AH54: 366 | AI54: -27 | AJ54: ==AG54+AI54*0.4 | AK54: ==IFERROR(AJ54/G54,0) | AL54: 11.67% | AM54: 2.28% | AN54: 78542 | AO54: More likely to attract OZ investment, with larger impact | AP54: More Likely
